Workbook

Sheet Guide
B1: AHIM: Master Asset Register & Common Record
B2: Asset Health & Integrity Management · Lotus Africa Uranium Plant
B4: Purpose
B5: Every inspection input (vibration and visual routes, IR, substation, statutory, ultrasonic, oil analysis, diesel generator checklists, light vehicle and heavy equipment inspections and prestarts) is entered in ONE format against ONE asset list. The register and records then feed the AHIM dashboard: plant health, criticality, top priorities, open records and machine history.
B7: How it works
B8: Step | C8: What to do | D8: Who
B9: 1. Register the asset | C9: Add it to Asset_Register with its Pronto asset no., area, class, criticality factors and applicable techniques. ACI and class calculate automatically. | D9: RCM Specialist (once per asset)
B10: 2. Enter the result | C10: Each reading, checklist defect or certificate check becomes one row in Records. Pick the asset from the dropdown; description, area and ACI fill in. | D10: Input owner (analyst, electrician, DG operator, fleet mechanic, contractor)
B11: 3. Status is set | C11: Measured values: from the Alert/Danger limits. Checklists, visual, statutory: Inspector status using the severity rules below. | D11: Automatic / inspector
B12: 4. Priority and due date | C12: Alert and Danger rows get a priority score (ACI x severity), P1/P2/P3 and a due date automatically. Any Danger is always P1, whatever the asset criticality. | D12: Automatic
B13: 5. Action and close | C13: Raise the Pronto WO, enter the WO no., move the stage forward. Close only after a re-check confirms the fix, and record who verified it. | D13: RCM Specialist / planner
B14: 6. Review | C14: The asset's Current status in the register always shows the worst open record. Use filters on Records for overdue items. | D14: RCM Specialist (weekly)
B16: Colour legend
B17: Item | C17: Meaning
B18: Dark blue header | C18: Enter data in this column
B19: Grey header, grey cells | C19: Automatic formula: do not type over
B20: Blue italic text | C20: Sample data: replace or delete before go-live
B21: Blue on cream (Lists sheet) | C21: Settings: weights, thresholds, response times
B22: Red key cell (register) | C22: Duplicate Pronto asset no.
B23: Amber Record stage | C23: Alert/Danger row with no stage yet
B25: How each input source maps into the record
B26: Source (input) | C26: Technique(s) | D26: Record type | E26: How status is set | F26: Typical frequency | G26: Owner
B27: Vibration & visual route | C27: Vibration, Visual | D27: Measured + checklist | E27: Limits (ISO 20816-3: 4.5 / 7.1 mm/s); visual by severity rules | F27: Monthly route | G27: RCM Specialist
B28: IR survey | C28: Infrared | D28: Measured | E28: dT limits (NETA: >4 °C Alert, >15 °C Danger) or absolute temperature limits | F28: Monthly | G28: RCM Specialist
B29: Substation inspection | C29: Infrared, Visual, Electrical | D29: Measured + checklist | E29: Limits for readings; severity rules for checklist items | F29: Monthly | G29: Electrical
B30: Statutory inspection | C30: Statutory | D30: Compliance | E30: Inspector status; register also flags expiry (60 days = Alert, expired = Danger) | F30: Per certificate | G30: RCM Specialist / contractor
B31: Ultrasonic report | C31: Ultrasonic thickness, Ultrasonics (airborne) | D31: Measured | E31: Thickness: Lower is worse vs minimum wall. Airborne: dB limits | F31: Quarterly / annual | G31: UT contractor / RCM
B32: Oil analysis | C32: Lubrication / oil | D32: Measured | E32: Lab alarm limits per parameter (water, iron, silicon, viscosity...) | F32: Monthly / per service | G32: RCM Specialist
B33: DG checklist | C33: DG checks | D33: Measured | E33: Enter only the condition parameters (exhaust and turbo temperatures, oil pressure, coolant temperature, crankcase pressure) with limits | F33: Daily; enter weekly summary or any exceedance | G33: DG operator
B34: LV/HV inspection checklist | C34: Fleet inspection | D34: Checklist | E34: Severity rules per component | F34: Per service / monthly | G34: Fleet mechanic
B35: LV/HV prestart checklist | C35: Prestart | D35: Exceptions only | E35: Enter only defects found (severity rules); completion rate tracked separately | F35: Every shift | G35: Operator / supervisor
B37: Severity rules for checklists, visual and prestart items
B38: Status | C38: Definition | D38: Required response | E38: Examples
B39: OK | C39: Item within standard | D39: None (record only if part of a route) | E39: Guards fitted, no leaks
B40: Alert | C40: Defect, but safe to operate | D40: Repair within P2/P3 response time | E40: Minor oil leak, silica gel discoloured, worn seat, reverse alarm faulty
B41: Danger | C41: Unsafe or failure imminent | D41: Stop / isolate / tag out; repair before use (P1) | E41: Brakes or steering ineffective, seatbelt or fire suppression faulty, major leak, exposed live parts
B43: Asset numbering convention (site tag)
B44: Prefix | C44: Area | D44: Example
B45: AP- | C45: Acid plant | D45: AP-P-101 (pump), AP-TK-01 (tank)
B46: CK- | C46: Calciner | D46: CK-1080
B47: SS- | C47: Substation | D47: SS-TX-01, SS-MCC-01
B48: PP- | C48: Power plant | D48: PP-GEN-04
B49: LV- / HV- | C49: Mobile fleet | D49: LV-01 light vehicle, HV-02 compactor
B51: The Pronto asset no. remains the unique key; the site tag is the name people use in the field. Sample Pronto numbers (1001xx...) are placeholders.
B53: Repeat readings rule
B54: Each new reading is a new row. If a reading repeats an issue already raised in an earlier row, set its Record stage to "No action": it updates the trend and the asset status, but does not create a second open recommendation. An asset returns to OK when its recommendation is Closed and the latest reading is within limits.
B56: Dashboard sheets
B57: Sheet | C57: Feeds
B58: Events | C58: Machine history, MTBF/MTTR, availability, bad actors (Pronto WO export)
B59: Schedule | C59: Inspection schedule compliance
B60: CM_Value / Programme_Cost | C60: CM return on investment
B61: Decisions | C61: Management decisions required
B62: Prestart | C62: Fleet prestart compliance
B64: Settings (Lists sheet)
B65: ACI weights, criticality class limits, priority bands and response times (P1 7 days, P2 30, P3 60), severity factors (Danger 1.0, Alert 0.6) and the statutory alert window (60 days) are editable on the Lists sheet. Get them approved by the Engineering Manager before go-live so the numbers are not disputed.

Sheet Asset_Register
A1: AHIM Master Asset Register
A2: Dark headers = enter data. Grey headers = automatic (do not type). Blue italic rows are SAMPLES: replace with the Pronto asset list. Pronto asset no. is the unique key used everywhere.
L3: Criticality factors: 1 = low impact, 5 = severe | U3: Applicable techniques (enter Y)
A4: Pronto asset no. | B4: Site tag | C4: Description | D4: Area | E4: System / location | F4: Asset class | G4: Manufacturer | H4: Model | I4: Serial no. | J4: Operating mode | K4: Asset state | L4: Safety & env. (1-5) | M4: Production (1-5) | N4: Redundancy (1-5) | O4: Repair cost / MTTR (1-5) | P4: Failure history (1-5) | Q4: ACI (0-100) | R4: Class | S4: Current status | T4: Open records | U4: Vibration | V4: Lubrication / oil | W4: Ultrasonics (airborne) | X4: Ultrasonic thickness | Y4: Infrared | Z4: Visual | AA4: Statutory | AB4: Tank & vessel | AC4: Piping | AD4: Structural | AE4: Electrical | AF4: DG checks | AG4: Fleet inspection | AH4: Prestart | AI4: Statutory cert. required | AJ4: Certificate expiry | AK4: Days to expiry | AL4: Statutory status | AM4: Responsible | AN4: Remarks | AO4: Strategy class | AP4: Consequence (1-5) | AQ4: Service | AR4: Bottleneck (Y/N) | AS4: Replacement value (USD) | AT4: Consequence basis | AU4: Install year | AV4: Design life (years)
A5: 100101 | B5: AP-SF-01 | C5: Sulphur furnace | D5: Acid plant | E5: Gas generation | F5: Fired equipment | J5: Duty | K5: Active | L5: 5 | M5: 5 | N5: 5 | O5: 5 | P5: 2 | Q5: =IF(COUNT($L5:$P5)<5,"",ROUND(($L5*Lists!$M$2+$M5*Lists!$M$3+$N5*Lists!$M$4+$O5*Lists!$M$5+$P5*Lists!$M$6)/5*100,0)) -> 94 | R5: =IF($Q5="","",IF($Q5>=Lists!$M$20,"A",IF($Q5>=Lists!$M$21,"B","C"))) -> A | S5: =IF($A5="","",IF(COUNTIF(Records!$C$5:$C$3000,$A5)=0,"No data",CHOOSE(_xlfn.MAXIFS(Records!$R$5:$R$3000,Records!$C$5:$C$3000,$A5,Records!$Y$5:$Y$3000,"<>Closed")+1,"OK","Alert","Danger"))) -> Danger | T5: =IF($A5="","",COUNTIFS(Records!$C$5:$C$3000,$A5,Records!$R$5:$R$3000,">0",Records!$Y$5:$Y$3000,"<>Closed")) -> 1 | Y5: Y | Z5: Y | AA5: Y | AD5: Y | AI5: Y | AJ5: 46464 | AK5: =IF($AJ5="","",$AJ5-TODAY()) -> 164 | AL5: =IF($AJ5="","",IF($AK5<0,"Danger",IF($AK5<=Lists!$M$24,"Alert","OK"))) -> OK | AM5: Mechanical | AO5: Sulphur furnace / refractory-lined equipment | AP5: 5 | AS5: 6000000 | AT5: Default: criticality factors (safety and environment 5, production 5) | AU5: 2008 | AV5: 30
A6: 100102 | B6: AP-WHB-01 | C6: Waste heat boiler | D6: Acid plant | E6: Gas generation | F6: Boiler | J6: Duty | K6: Active | L6: 5 | M6: 5 | N6: 5 | O6: 4 | P6: 2 | Q6: =IF(COUNT($L6:$P6)<5,"",ROUND(($L6*Lists!$M$2+$M6*Lists!$M$3+$N6*Lists!$M$4+$O6*Lists!$M$5+$P6*Lists!$M$6)/5*100,0)) -> 91 | R6: =IF($Q6="","",IF($Q6>=Lists!$M$20,"A",IF($Q6>=Lists!$M$21,"B","C"))) -> A | S6: =IF($A6="","",IF(COUNTIF(Records!$C$5:$C$3000,$A6)=0,"No data",CHOOSE(_xlfn.MAXIFS(Records!$R$5:$R$3000,Records!$C$5:$C$3000,$A6,Records!$Y$5:$Y$3000,"<>Closed")+1,"OK","Alert","Danger"))) -> Alert | T6: =IF($A6="","",COUNTIFS(Records!$C$5:$C$3000,$A6,Records!$R$5:$R$3000,">0",Records!$Y$5:$Y$3000,"<>Closed")) -> 1 | W6: Y | X6: Y | Y6: Y | Z6: Y | AA6: Y | AB6: Y | AI6: Y | AJ6: 46317 | AK6: =IF($AJ6="","",$AJ6-TODAY()) -> 17 | AL6: =IF($AJ6="","",IF($AK6<0,"Danger",IF($AK6<=Lists!$M$24,"Alert","OK"))) -> Alert | AM6: Mechanical | AO6: Pressure vessel / boiler | AP6: 5 | AS6: 4500000 | AT6: Default: criticality factors (safety and environment 5, production 5) | AU6: 2008 | AV6: 25
A7: 100103 | B7: AP-BL-01 | C7: Main air blower | D7: Acid plant | E7: Gas generation | F7: Rotating - fan / blower | J7: Duty | K7: Active | L7: 4 | M7: 5 | N7: 5 | O7: 4 | P7: 3 | Q7: =IF(COUNT($L7:$P7)<5,"",ROUND(($L7*Lists!$M$2+$M7*Lists!$M$3+$N7*Lists!$M$4+$O7*Lists!$M$5+$P7*Lists!$M$6)/5*100,0)) -> 87 | R7: =IF($Q7="","",IF($Q7>=Lists!$M$20,"A",IF($Q7>=Lists!$M$21,"B","C"))) -> A | S7: =IF($A7="","",IF(COUNTIF(Records!$C$5:$C$3000,$A7)=0,"No data",CHOOSE(_xlfn.MAXIFS(Records!$R$5:$R$3000,Records!$C$5:$C$3000,$A7,Records!$Y$5:$Y$3000,"<>Closed")+1,"OK","Alert","Danger"))) -> Alert | T7: =IF($A7="","",COUNTIFS(Records!$C$5:$C$3000,$A7,Records!$R$5:$R$3000,">0",Records!$Y$5:$Y$3000,"<>Closed")) -> 1 | U7: Y | V7: Y | W7: Y | Y7: Y | Z7: Y | AE7: Y | AI7: N | AK7: =IF($AJ7="","",$AJ7-TODAY()) | AL7: =IF($AJ7="","",IF($AK7<0,"Danger",IF($AK7<=Lists!$M$24,"Alert","OK"))) | AM7: Mechanical | AO7: Fan / blower | AP7: 5 | AS7: 2200000 | AT7: Default: criticality factors (safety and environment 4, production 5) | AU7: 2008 | AV7: 25
A8: 100104 | B8: AP-CV-01 | C8: SO2 converter | D8: Acid plant | E8: Conversion | F8: Pressure vessel | J8: Duty | K8: Active | L8: 4 | M8: 5 | N8: 5 | O8: 5 | P8: 1 | Q8: =IF(COUNT($L8:$P8)<5,"",ROUND(($L8*Lists!$M$2+$M8*Lists!$M$3+$N8*Lists!$M$4+$O8*Lists!$M$5+$P8*Lists!$M$6)/5*100,0)) -> 86 | R8: =IF($Q8="","",IF($Q8>=Lists!$M$20,"A",IF($Q8>=Lists!$M$21,"B","C"))) -> A | S8: =IF($A8="","",IF(COUNTIF(Records!$C$5:$C$3000,$A8)=0,"No data",CHOOSE(_xlfn.MAXIFS(Records!$R$5:$R$3000,Records!$C$5:$C$3000,$A8,Records!$Y$5:$Y$3000,"<>Closed")+1,"OK","Alert","Danger"))) -> Alert | T8: =IF($A8="","",COUNTIFS(Records!$C$5:$C$3000,$A8,Records!$R$5:$R$3000,">0",Records!$Y$5:$Y$3000,"<>Closed")) -> 3 | Y8: Y | Z8: Y | AB8: Y | AD8: Y | AI8: N | AK8: =IF($AJ8="","",$AJ8-TODAY()) | AL8: =IF($AJ8="","",IF($AK8<0,"Danger",IF($AK8<=Lists!$M$24,"Alert","OK"))) | AM8: Mechanical | AO8: Pressure vessel / boiler | AP8: 5 | AS8: 5000000 | AT8: Default: criticality factors (safety and environment 4, production 5) | AU8: 2008 | AV8: 30
A9: 100105 | B9: AP-P-101 | C9: Drying tower acid pump | D9: Acid plant | E9: Drying & absorption | F9: Rotating - pump | J9: Duty | K9: Active | L9: 4 | M9: 4 | N9: 3 | O9: 3 | P9: 4 | Q9: =IF(COUNT($L9:$P9)<5,"",ROUND(($L9*Lists!$M$2+$M9*Lists!$M$3+$N9*Lists!$M$4+$O9*Lists!$M$5+$P9*Lists!$M$6)/5*100,0)) -> 74 | R9: =IF($Q9="","",IF($Q9>=Lists!$M$20,"A",IF($Q9>=Lists!$M$21,"B","C"))) -> A | S9: =IF($A9="","",IF(COUNTIF(Records!$C$5:$C$3000,$A9)=0,"No data",CHOOSE(_xlfn.MAXIFS(Records!$R$5:$R$3000,Records!$C$5:$C$3000,$A9,Records!$Y$5:$Y$3000,"<>Closed")+1,"OK","Alert","Danger"))) -> Danger | T9: =IF($A9="","",COUNTIFS(Records!$C$5:$C$3000,$A9,Records!$R$5:$R$3000,">0",Records!$Y$5:$Y$3000,"<>Closed")) -> 2 | U9: Y | V9: Y | W9: Y | Y9: Y | Z9: Y | AE9: Y | AI9: N | AK9: =IF($AJ9="","",$AJ9-TODAY()) | AL9: =IF($AJ9="","",IF($AK9<0,"Danger",IF($AK9<=Lists!$M$24,"Alert","OK"))) | AM9: Mechanical | AO9: Centrifugal process pump | AP9: 4 | AS9: 180000 | AT9: Default: criticality factors (safety and environment 4, production 4) | AU9: 2012 | AV9: 15
A10: 100106 | B10: AP-P-102 | C10: Interpass tower acid pump | D10: Acid plant | E10: Drying & absorption | F10: Rotating - pump | J10: Duty | K10: Active | L10: 4 | M10: 5 | N10: 3 | O10: 3 | P10: 2 | Q10: =IF(COUNT($L10:$P10)<5,"",ROUND(($L10*Lists!$M$2+$M10*Lists!$M$3+$N10*Lists!$M$4+$O10*Lists!$M$5+$P10*Lists!$M$6)/5*100,0)) -> 76 | R10: =IF($Q10="","",IF($Q10>=Lists!$M$20,"A",IF($Q10>=Lists!$M$21,"B","C"))) -> A | S10: =IF($A10="","",IF(COUNTIF(Records!$C$5:$C$3000,$A10)=0,"No data",CHOOSE(_xlfn.MAXIFS(Records!$R$5:$R$3000,Records!$C$5:$C$3000,$A10,Records!$Y$5:$Y$3000,"<>Closed")+1,"OK","Alert","Danger"))) -> OK | T10: =IF($A10="","",COUNTIFS(Records!$C$5:$C$3000,$A10,Records!$R$5:$R$3000,">0",Records!$Y$5:$Y$3000,"<>Closed")) -> 0 | U10: Y | V10: Y | W10: Y | Y10: Y | Z10: Y | AE10: Y | AI10: N | AK10: =IF($AJ10="","",$AJ10-TODAY()) | AL10: =IF($AJ10="","",IF($AK10<0,"Danger",IF($AK10<=Lists!$M$24,"Alert","OK"))) | AM10: Mechanical | AO10: Centrifugal process pump | AP10: 5 | AS10: 180000 | AT10: Default: criticality factors (safety and environment 4, production 5) | AU10: 2012 | AV10: 15
A11: 100107 | B11: AP-P-103 | C11: Final tower acid pump | D11: Acid plant | E11: Drying & absorption | F11: Rotating - pump | J11: Duty | K11: Active | L11: 3 | M11: 4 | N11: 3 | O11: 3 | P11: 3 | Q11: =IF(COUNT($L11:$P11)<5,"",ROUND(($L11*Lists!$M$2+$M11*Lists!$M$3+$N11*Lists!$M$4+$O11*Lists!$M$5+$P11*Lists!$M$6)/5*100,0)) -> 66 | R11: =IF($Q11="","",IF($Q11>=Lists!$M$20,"A",IF($Q11>=Lists!$M$21,"B","C"))) -> B | S11: =IF($A11="","",IF(COUNTIF(Records!$C$5:$C$3000,$A11)=0,"No data",CHOOSE(_xlfn.MAXIFS(Records!$R$5:$R$3000,Records!$C$5:$C$3000,$A11,Records!$Y$5:$Y$3000,"<>Closed")+1,"OK","Alert","Danger"))) -> Alert | T11: =IF($A11="","",COUNTIFS(Records!$C$5:$C$3000,$A11,Records!$R$5:$R$3000,">0",Records!$Y$5:$Y$3000,"<>Closed")) -> 5 | U11: Y | V11: Y | W11: Y | Y11: Y | Z11: Y | AE11: Y | AI11: N | AK11: =IF($AJ11="","",$AJ11-TODAY()) | AL11: =IF($AJ11="","",IF($AK11<0,"Danger",IF($AK11<=Lists!$M$24,"Alert","OK"))) | AM11: Mechanical | AO11: Centrifugal process pump | AP11: 4 | AS11: 160000 | AT11: Default: criticality factors (safety and environment 3, production 4) | AU11: 2009 | AV11: 15
A12: 100108 | B12: AP-P-201 | C12: Boiler feed water pump A | D12: Acid plant | E12: Steam system | F12: Rotating - pump | J12: Duty | K12: Active | L12: 4 | M12: 5 | N12: 2 | O12: 3 | P12: 3 | Q12: =IF(COUNT($L12:$P12)<5,"",ROUND(($L12*Lists!$M$2+$M12*Lists!$M$3+$N12*Lists!$M$4+$O12*Lists!$M$5+$P12*Lists!$M$6)/5*100,0)) -> 75 | R12: =IF($Q12="","",IF($Q12>=Lists!$M$20,"A",IF($Q12>=Lists!$M$21,"B","C"))) -> A | S12: =IF($A12="","",IF(COUNTIF(Records!$C$5:$C$3000,$A12)=0,"No data",CHOOSE(_xlfn.MAXIFS(Records!$R$5:$R$3000,Records!$C$5:$C$3000,$A12,Records!$Y$5:$Y$3000,"<>Closed")+1,"OK","Alert","Danger"))) -> Alert | T12: =IF($A12="","",COUNTIFS(Records!$C$5:$C$3000,$A12,Records!$R$5:$R$3000,">0",Records!$Y$5:$Y$3000,"<>Closed")) -> 1 | U12: Y | V12: Y | W12: Y | Y12: Y | Z12: Y | AE12: Y | AI12: N | AK12: =IF($AJ12="","",$AJ12-TODAY()) | AL12: =IF($AJ12="","",IF($AK12<0,"Danger",IF($AK12<=Lists!$M$24,"Alert","OK"))) | AM12: Mechanical | AO12: Centrifugal process pump | AP12: 5 | AS12: 140000 | AT12: Default: criticality factors (safety and environment 4, production 5) | AU12: 2010 | AV12: 20
A13: 100109 | B13: AP-P-202 | C13: Boiler feed water pump B | D13: Acid plant | E13: Steam system | F13: Rotating - pump | J13: Standby | K13: Active | L13: 4 | M13: 5 | N13: 2 | O13: 3 | P13: 1 | Q13: =IF(COUNT($L13:$P13)<5,"",ROUND(($L13*Lists!$M$2+$M13*Lists!$M$3+$N13*Lists!$M$4+$O13*Lists!$M$5+$P13*Lists!$M$6)/5*100,0)) -> 71 | R13: =IF($Q13="","",IF($Q13>=Lists!$M$20,"A",IF($Q13>=Lists!$M$21,"B","C"))) -> A | S13: =IF($A13="","",IF(COUNTIF(Records!$C$5:$C$3000,$A13)=0,"No data",CHOOSE(_xlfn.MAXIFS(Records!$R$5:$R$3000,Records!$C$5:$C$3000,$A13,Records!$Y$5:$Y$3000,"<>Closed")+1,"OK","Alert","Danger"))) -> OK | T13: =IF($A13="","",COUNTIFS(Records!$C$5:$C$3000,$A13,Records!$R$5:$R$3000,">0",Records!$Y$5:$Y$3000,"<>Closed")) -> 0 | U13: Y | V13: Y | W13: Y | Y13: Y | Z13: Y | AE13: Y | AI13: N | AK13: =IF($AJ13="","",$AJ13-TODAY()) | AL13: =IF($AJ13="","",IF($AK13<0,"Danger",IF($AK13<=Lists!$M$24,"Alert","OK"))) | AM13: Mechanical | AO13: Centrifugal process pump | AP13: 5 | AS13: 140000 | AT13: Default: criticality factors (safety and environment 4, production 5) | AU13: 2010 | AV13: 20
A14: 100110 | B14: AP-P-301 | C14: Molten sulphur pump | D14: Acid plant | E14: Sulphur handling | F14: Rotating - pump | J14: Duty | K14: Active | L14: 3 | M14: 4 | N14: 3 | O14: 2 | P14: 2 | Q14: =IF(COUNT($L14:$P14)<5,"",ROUND(($L14*Lists!$M$2+$M14*Lists!$M$3+$N14*Lists!$M$4+$O14*Lists!$M$5+$P14*Lists!$M$6)/5*100,0)) -> 61 | R14: =IF($Q14="","",IF($Q14>=Lists!$M$20,"A",IF($Q14>=Lists!$M$21,"B","C"))) -> B | S14: =IF($A14="","",IF(COUNTIF(Records!$C$5:$C$3000,$A14)=0,"No data",CHOOSE(_xlfn.MAXIFS(Records!$R$5:$R$3000,Records!$C$5:$C$3000,$A14,Records!$Y$5:$Y$3000,"<>Closed")+1,"OK","Alert","Danger"))) -> OK | T14: =IF($A14="","",COUNTIFS(Records!$C$5:$C$3000,$A14,Records!$R$5:$R$3000,">0",Records!$Y$5:$Y$3000,"<>Closed")) -> 0 | U14: Y | V14: Y | W14: Y | Y14: Y | Z14: Y | AI14: N | AK14: =IF($AJ14="","",$AJ14-TODAY()) | AL14: =IF($AJ14="","",IF($AK14<0,"Danger",IF($AK14<=Lists!$M$24,"Alert","OK"))) | AM14: Mechanical | AO14: Centrifugal process pump | AP14: 4 | AS14: 120000 | AT14: Default: criticality factors (safety and environment 3, production 4) | AU14: 2008 | AV14: 20
A15: 100111 | B15: AP-AG-01 | C15: Sulphur melter agitator | D15: Acid plant | E15: Sulphur handling | F15: Rotating - agitator | J15: Duty | K15: Active | L15: 2 | M15: 2 | N15: 3 | O15: 2 | P15: 2 | Q15: =IF(COUNT($L15:$P15)<5,"",ROUND(($L15*Lists!$M$2+$M15*Lists!$M$3+$N15*Lists!$M$4+$O15*Lists!$M$5+$P15*Lists!$M$6)/5*100,0)) -> 43 | R15: =IF($Q15="","",IF($Q15>=Lists!$M$20,"A",IF($Q15>=Lists!$M$21,"B","C"))) -> C | S15: =IF($A15="","",IF(COUNTIF(Records!$C$5:$C$3000,$A15)=0,"No data",CHOOSE(_xlfn.MAXIFS(Records!$R$5:$R$3000,Records!$C$5:$C$3000,$A15,Records!$Y$5:$Y$3000,"<>Closed")+1,"OK","Alert","Danger"))) -> OK | T15: =IF($A15="","",COUNTIFS(Records!$C$5:$C$3000,$A15,Records!$R$5:$R$3000,">0",Records!$Y$5:$Y$3000,"<>Closed")) -> 0 | U15: Y | V15: Y | Z15: Y | AI15: N | AK15: =IF($AJ15="","",$AJ15-TODAY()) | AL15: =IF($AJ15="","",IF($AK15<0,"Danger",IF($AK15<=Lists!$M$24,"Alert","OK"))) | AM15: Mechanical | AO15: Agitator | AP15: 2 | AS15: 90000 | AT15: Default: criticality factors (safety and environment 2, production 2) | AU15: 2008 | AV15: 20
A16: 100112 | B16: AP-CT-01 | C16: Cooling tower fan 1 | D16: Acid plant | E16: Cooling water | F16: Rotating - gearbox / drive | J16: Duty | K16: Active | L16: 2 | M16: 3 | N16: 2 | O16: 2 | P16: 4 | Q16: =IF(COUNT($L16:$P16)<5,"",ROUND(($L16*Lists!$M$2+$M16*Lists!$M$3+$N16*Lists!$M$4+$O16*Lists!$M$5+$P16*Lists!$M$6)/5*100,0)) -> 50 | R16: =IF($Q16="","",IF($Q16>=Lists!$M$20,"A",IF($Q16>=Lists!$M$21,"B","C"))) -> B | S16: =IF($A16="","",IF(COUNTIF(Records!$C$5:$C$3000,$A16)=0,"No data",CHOOSE(_xlfn.MAXIFS(Records!$R$5:$R$3000,Records!$C$5:$C$3000,$A16,Records!$Y$5:$Y$3000,"<>Closed")+1,"OK","Alert","Danger"))) -> Alert | T16: =IF($A16="","",COUNTIFS(Records!$C$5:$C$3000,$A16,Records!$R$5:$R$3000,">0",Records!$Y$5:$Y$3000,"<>Closed")) -> 10 | U16: Y | V16: Y | Z16: Y | AD16: Y | AE16: Y | AI16: N | AK16: =IF($AJ16="","",$AJ16-TODAY()) | AL16: =IF($AJ16="","",IF($AK16<0,"Danger",IF($AK16<=Lists!$M$24,"Alert","OK"))) | AM16: Mechanical | AO16: Gearbox (stand-alone) | AP16: 3 | AS16: 350000 | AT16: Default: criticality factors (safety and environment 2, production 3) | AU16: 2008 | AV16: 20
A17: 100113 | B17: AP-TK-01 | C17: Product acid storage tank | D17: Acid plant | E17: Product storage | F17: Tank | J17: Duty | K17: Active | L17: 5 | M17: 3 | N17: 4 | O17: 4 | P17: 2 | Q17: =IF(COUNT($L17:$P17)<5,"",ROUND(($L17*Lists!$M$2+$M17*Lists!$M$3+$N17*Lists!$M$4+$O17*Lists!$M$5+$P17*Lists!$M$6)/5*100,0)) -> 76 | R17: =IF($Q17="","",IF($Q17>=Lists!$M$20,"A",IF($Q17>=Lists!$M$21,"B","C"))) -> A | S17: =IF($A17="","",IF(COUNTIF(Records!$C$5:$C$3000,$A17)=0,"No data",CHOOSE(_xlfn.MAXIFS(Records!$R$5:$R$3000,Records!$C$5:$C$3000,$A17,Records!$Y$5:$Y$3000,"<>Closed")+1,"OK","Alert","Danger"))) -> Alert | T17: =IF($A17="","",COUNTIFS(Records!$C$5:$C$3000,$A17,Records!$R$5:$R$3000,">0",Records!$Y$5:$Y$3000,"<>Closed")) -> 2 | X17: Y | Z17: Y | AA17: Y | AB17: Y | AD17: Y | AI17: Y | AJ17: 46479 | AK17: =IF($AJ17="","",$AJ17-TODAY()) -> 179 | AL17: =IF($AJ17="","",IF($AK17<0,"Danger",IF($AK17<=Lists!$M$24,"Alert","OK"))) -> OK | AM17: Mechanical | AO17: Atmospheric storage tank | AP17: 5 | AS17: 1200000 | AT17: Default: criticality factors (safety and environment 5, production 3) | AU17: 2008 | AV17: 25
A18: 100114 | B18: AP-PL-01 | C18: Acid transfer line | D18: Acid plant | E18: Product storage | F18: Piping | J18: Duty | K18: Active | L18: 5 | M18: 4 | N18: 5 | O18: 2 | P18: 3 | Q18: =IF(COUNT($L18:$P18)<5,"",ROUND(($L18*Lists!$M$2+$M18*Lists!$M$3+$N18*Lists!$M$4+$O18*Lists!$M$5+$P18*Lists!$M$6)/5*100,0)) -> 81 | R18: =IF($Q18="","",IF($Q18>=Lists!$M$20,"A",IF($Q18>=Lists!$M$21,"B","C"))) -> A | S18: =IF($A18="","",IF(COUNTIF(Records!$C$5:$C$3000,$A18)=0,"No data",CHOOSE(_xlfn.MAXIFS(Records!$R$5:$R$3000,Records!$C$5:$C$3000,$A18,Records!$Y$5:$Y$3000,"<>Closed")+1,"OK","Alert","Danger"))) -> Danger | T18: =IF($A18="","",COUNTIFS(Records!$C$5:$C$3000,$A18,Records!$R$5:$R$3000,">0",Records!$Y$5:$Y$3000,"<>Closed")) -> 1 | X18: Y | Z18: Y | AC18: Y | AI18: N | AK18: =IF($AJ18="","",$AJ18-TODAY()) | AL18: =IF($AJ18="","",IF($AK18<0,"Danger",IF($AK18<=Lists!$M$24,"Alert","OK"))) | AM18: Mechanical | AO18: Piping (acid / slurry / process) | AP18: 5 | AS18: 300000 | AT18: Default: criticality factors (safety and environment 5, production 4) | AU18: 2011 | AV18: 15
A19: 100115 | B19: AP-AR-01 | C19: Instrument air receiver | D19: Acid plant | E19: Utilities air | F19: Pressure vessel | J19: Duty | K19: Active | L19: 4 | M19: 2 | N19: 3 | O19: 2 | P19: 1 | Q19: =IF(COUNT($L19:$P19)<5,"",ROUND(($L19*Lists!$M$2+$M19*Lists!$M$3+$N19*Lists!$M$4+$O19*Lists!$M$5+$P19*Lists!$M$6)/5*100,0)) -> 53 | R19: =IF($Q19="","",IF($Q19>=Lists!$M$20,"A",IF($Q19>=Lists!$M$21,"B","C"))) -> B | S19: =IF($A19="","",IF(COUNTIF(Records!$C$5:$C$3000,$A19)=0,"No data",CHOOSE(_xlfn.MAXIFS(Records!$R$5:$R$3000,Records!$C$5:$C$3000,$A19,Records!$Y$5:$Y$3000,"<>Closed")+1,"OK","Alert","Danger"))) -> OK | T19: =IF($A19="","",COUNTIFS(Records!$C$5:$C$3000,$A19,Records!$R$5:$R$3000,">0",Records!$Y$5:$Y$3000,"<>Closed")) -> 0 | W19: Y | Z19: Y | AA19: Y | AB19: Y | AI19: Y | AJ19: 46458 | AK19: =IF($AJ19="","",$AJ19-TODAY()) -> 158 | AL19: =IF($AJ19="","",IF($AK19<0,"Danger",IF($AK19<=Lists!$M$24,"Alert","OK"))) -> OK | AM19: Mechanical | AO19: Pressure vessel / boiler | AP19: 4 | AS19: 80000 | AT19: Default: criticality factors (safety and environment 4, production 2) | AU19: 2008 | AV19: 30
A20: 100201 | B20: CK-1080 | C20: Calciner kiln 1080 | D20: Calciner | E20: Calcining | F20: Rotary kiln | J20: Duty | K20: Active | L20: 4 | M20: 5 | N20: 5 | O20: 5 | P20: 3 | Q20: =IF(COUNT($L20:$P20)<5,"",ROUND(($L20*Lists!$M$2+$M20*Lists!$M$3+$N20*Lists!$M$4+$O20*Lists!$M$5+$P20*Lists!$M$6)/5*100,0)) -> 90 | R20: =IF($Q20="","",IF($Q20>=Lists!$M$20,"A",IF($Q20>=Lists!$M$21,"B","C"))) -> A | S20: =IF($A20="","",IF(COUNTIF(Records!$C$5:$C$3000,$A20)=0,"No data",CHOOSE(_xlfn.MAXIFS(Records!$R$5:$R$3000,Records!$C$5:$C$3000,$A20,Records!$Y$5:$Y$3000,"<>Closed")+1,"OK","Alert","Danger"))) -> Alert | T20: =IF($A20="","",COUNTIFS(Records!$C$5:$C$3000,$A20,Records!$R$5:$R$3000,">0",Records!$Y$5:$Y$3000,"<>Closed")) -> 2 | U20: Y | V20: Y | Y20: Y | Z20: Y | AD20: Y | AI20: N | AK20: =IF($AJ20="","",$AJ20-TODAY()) | AL20: =IF($AJ20="","",IF($AK20<0,"Danger",IF($AK20<=Lists!$M$24,"Alert","OK"))) | AM20: Mechanical | AO20: Rotary dryer / kiln / calciner | AP20: 5 | AS20: 12000000 | AT20: Default: criticality factors (safety and environment 4, production 5) | AU20: 2009 | AV20: 30
A21: 100301 | B21: SS-TX-01 | C21: Transformer TX-01 | D21: Substation | E21: Main substation | F21: Electrical - transformer | J21: Duty | K21: Active | L21: 4 | M21: 5 | N21: 5 | O21: 5 | P21: 1 | Q21: =IF(COUNT($L21:$P21)<5,"",ROUND(($L21*Lists!$M$2+$M21*Lists!$M$3+$N21*Lists!$M$4+$O21*Lists!$M$5+$P21*Lists!$M$6)/5*100,0)) -> 86 | R21: =IF($Q21="","",IF($Q21>=Lists!$M$20,"A",IF($Q21>=Lists!$M$21,"B","C"))) -> A | S21: =IF($A21="","",IF(COUNTIF(Records!$C$5:$C$3000,$A21)=0,"No data",CHOOSE(_xlfn.MAXIFS(Records!$R$5:$R$3000,Records!$C$5:$C$3000,$A21,Records!$Y$5:$Y$3000,"<>Closed")+1,"OK","Alert","Danger"))) -> Alert | T21: =IF($A21="","",COUNTIFS(Records!$C$5:$C$3000,$A21,Records!$R$5:$R$3000,">0",Records!$Y$5:$Y$3000,"<>Closed")) -> 4 | V21: Y | W21: Y | Y21: Y | Z21: Y | AE21: Y | AI21: N | AK21: =IF($AJ21="","",$AJ21-TODAY()) | AL21: =IF($AJ21="","",IF($AK21<0,"Danger",IF($AK21<=Lists!$M$24,"Alert","OK"))) | AM21: Electrical | AO21: Switchgear / MCC / transformer | AP21: 5 | AS21: 1500000 | AT21: Default: criticality factors (safety and environment 4, production 5) | AU21: 2008 | AV21: 35
A22: 100302 | B22: SS-MCC-01 | C22: Acid plant MCC | D22: Substation | E22: Main substation | F22: Electrical - switchgear / MCC | J22: Duty | K22: Active | L22: 4 | M22: 5 | N22: 5 | O22: 3 | P22: 2 | Q22: =IF(COUNT($L22:$P22)<5,"",ROUND(($L22*Lists!$M$2+$M22*Lists!$M$3+$N22*Lists!$M$4+$O22*Lists!$M$5+$P22*Lists!$M$6)/5*100,0)) -> 82 | R22: =IF($Q22="","",IF($Q22>=Lists!$M$20,"A",IF($Q22>=Lists!$M$21,"B","C"))) -> A | S22: =IF($A22="","",IF(COUNTIF(Records!$C$5:$C$3000,$A22)=0,"No data",CHOOSE(_xlfn.MAXIFS(Records!$R$5:$R$3000,Records!$C$5:$C$3000,$A22,Records!$Y$5:$Y$3000,"<>Closed")+1,"OK","Alert","Danger"))) -> Danger | T22: =IF($A22="","",COUNTIFS(Records!$C$5:$C$3000,$A22,Records!$R$5:$R$3000,">0",Records!$Y$5:$Y$3000,"<>Closed")) -> 2 | W22: Y | Y22: Y | Z22: Y | AE22: Y | AI22: N | AK22: =IF($AJ22="","",$AJ22-TODAY()) | AL22: =IF($AJ22="","",IF($AK22<0,"Danger",IF($AK22<=Lists!$M$24,"Alert","OK"))) | AM22: Electrical | AO22: Switchgear / MCC / transformer | AP22: 5 | AS22: 600000 | AT22: Default: criticality factors (safety and environment 4, production 5) | AU22: 2008 | AV22: 25
A23: 100401 | B23: PP-GEN-01 | C23: Diesel generator Gen 1 | D23: Power plant | E23: Power station | F23: Diesel generator | G23: Hyundai | J23: Duty | K23: Active | L23: 4 | M23: 5 | N23: 3 | O23: 4 | P23: 4 | Q23: =IF(COUNT($L23:$P23)<5,"",ROUND(($L23*Lists!$M$2+$M23*Lists!$M$3+$N23*Lists!$M$4+$O23*Lists!$M$5+$P23*Lists!$M$6)/5*100,0)) -> 83 | R23: =IF($Q23="","",IF($Q23>=Lists!$M$20,"A",IF($Q23>=Lists!$M$21,"B","C"))) -> A | S23: =IF($A23="","",IF(COUNTIF(Records!$C$5:$C$3000,$A23)=0,"No data",CHOOSE(_xlfn.MAXIFS(Records!$R$5:$R$3000,Records!$C$5:$C$3000,$A23,Records!$Y$5:$Y$3000,"<>Closed")+1,"OK","Alert","Danger"))) -> Alert | T23: =IF($A23="","",COUNTIFS(Records!$C$5:$C$3000,$A23,Records!$R$5:$R$3000,">0",Records!$Y$5:$Y$3000,"<>Closed")) -> 1 | U23: Y | V23: Y | Y23: Y | Z23: Y | AE23: Y | AF23: Y | AI23: N | AK23: =IF($AJ23="","",$AJ23-TODAY()) | AL23: =IF($AJ23="","",IF($AK23<0,"Danger",IF($AK23<=Lists!$M$24,"Alert","OK"))) | AM23: Power plant | AO23: Diesel generator | AP23: 5 | AS23: 1800000 | AT23: Default: criticality factors (safety and environment 4, production 5) | AU23: 2010 | AV23: 20
A24: 100402 | B24: PP-GEN-02 | C24: Diesel generator Gen 2 | D24: Power plant | E24: Power station | F24: Diesel generator | G24: Hyundai | J24: Duty | K24: Active | L24: 4 | M24: 5 | N24: 3 | O24: 4 | P24: 2 | Q24: =IF(COUNT($L24:$P24)<5,"",ROUND(($L24*Lists!$M$2+$M24*Lists!$M$3+$N24*Lists!$M$4+$O24*Lists!$M$5+$P24*Lists!$M$6)/5*100,0)) -> 79 | R24: =IF($Q24="","",IF($Q24>=Lists!$M$20,"A",IF($Q24>=Lists!$M$21,"B","C"))) -> A | S24: =IF($A24="","",IF(COUNTIF(Records!$C$5:$C$3000,$A24)=0,"No data",CHOOSE(_xlfn.MAXIFS(Records!$R$5:$R$3000,Records!$C$5:$C$3000,$A24,Records!$Y$5:$Y$3000,"<>Closed")+1,"OK","Alert","Danger"))) -> OK | T24: =IF($A24="","",COUNTIFS(Records!$C$5:$C$3000,$A24,Records!$R$5:$R$3000,">0",Records!$Y$5:$Y$3000,"<>Closed")) -> 0 | U24: Y | V24: Y | Y24: Y | Z24: Y | AE24: Y | AF24: Y | AI24: N | AK24: =IF($AJ24="","",$AJ24-TODAY()) | AL24: =IF($AJ24="","",IF($AK24<0,"Danger",IF($AK24<=Lists!$M$24,"Alert","OK"))) | AM24: Power plant | AO24: Diesel generator | AP24: 5 | AS24: 1800000 | AT24: Default: criticality factors (safety and environment 4, production 5) | AU24: 2010 | AV24: 20
A25: 100403 | B25: PP-GEN-03 | C25: Diesel generator Gen 3 | D25: Power plant | E25: Power station | F25: Diesel generator | G25: Hyundai | J25: Standby | K25: Active | L25: 4 | M25: 5 | N25: 3 | O25: 4 | P25: 2 | Q25: =IF(COUNT($L25:$P25)<5,"",ROUND(($L25*Lists!$M$2+$M25*Lists!$M$3+$N25*Lists!$M$4+$O25*Lists!$M$5+$P25*Lists!$M$6)/5*100,0)) -> 79 | R25: =IF($Q25="","",IF($Q25>=Lists!$M$20,"A",IF($Q25>=Lists!$M$21,"B","C"))) -> A | S25: =IF($A25="","",IF(COUNTIF(Records!$C$5:$C$3000,$A25)=0,"No data",CHOOSE(_xlfn.MAXIFS(Records!$R$5:$R$3000,Records!$C$5:$C$3000,$A25,Records!$Y$5:$Y$3000,"<>Closed")+1,"OK","Alert","Danger"))) -> OK | T25: =IF($A25="","",COUNTIFS(Records!$C$5:$C$3000,$A25,Records!$R$5:$R$3000,">0",Records!$Y$5:$Y$3000,"<>Closed")) -> 0 | U25: Y | V25: Y | Y25: Y | Z25: Y | AE25: Y | AF25: Y | AI25: N | AK25: =IF($AJ25="","",$AJ25-TODAY()) | AL25: =IF($AJ25="","",IF($AK25<0,"Danger",IF($AK25<=Lists!$M$24,"Alert","OK"))) | AM25: Power plant | AO25: Diesel generator | AP25: 5 | AS25: 1800000 | AT25: Default: criticality factors (safety and environment 4, production 5) | AU25: 2010 | AV25: 20
A26: 100404 | B26: PP-GEN-04 | C26: Diesel generator Gen 4 | D26: Power plant | E26: Power station | F26: Diesel generator | G26: Hyundai | J26: Duty | K26: Active | L26: 5 | M26: 5 | N26: 3 | O26: 5 | P26: 4 | Q26: =IF(COUNT($L26:$P26)<5,"",ROUND(($L26*Lists!$M$2+$M26*Lists!$M$3+$N26*Lists!$M$4+$O26*Lists!$M$5+$P26*Lists!$M$6)/5*100,0)) -> 92 | R26: =IF($Q26="","",IF($Q26>=Lists!$M$20,"A",IF($Q26>=Lists!$M$21,"B","C"))) -> A | S26: =IF($A26="","",IF(COUNTIF(Records!$C$5:$C$3000,$A26)=0,"No data",CHOOSE(_xlfn.MAXIFS(Records!$R$5:$R$3000,Records!$C$5:$C$3000,$A26,Records!$Y$5:$Y$3000,"<>Closed")+1,"OK","Alert","Danger"))) -> Alert | T26: =IF($A26="","",COUNTIFS(Records!$C$5:$C$3000,$A26,Records!$R$5:$R$3000,">0",Records!$Y$5:$Y$3000,"<>Closed")) -> 1 | U26: Y | V26: Y | Y26: Y | Z26: Y | AE26: Y | AF26: Y | AI26: N | AK26: =IF($AJ26="","",$AJ26-TODAY()) | AL26: =IF($AJ26="","",IF($AK26<0,"Danger",IF($AK26<=Lists!$M$24,"Alert","OK"))) | AM26: Power plant | AO26: Diesel generator | AP26: 5 | AS26: 1800000 | AT26: Default: criticality factors (safety and environment 5, production 5) | AU26: 2010 | AV26: 20
A27: 100501 | B27: LV-01 | C27: Light vehicle LV-01 (pickup) | D27: Mobile fleet | E27: Light vehicles | F27: Light vehicle | J27: Mobile | K27: Active | L27: 3 | M27: 2 | N27: 2 | O27: 1 | P27: 2 | Q27: =IF(COUNT($L27:$P27)<5,"",ROUND(($L27*Lists!$M$2+$M27*Lists!$M$3+$N27*Lists!$M$4+$O27*Lists!$M$5+$P27*Lists!$M$6)/5*100,0)) -> 43 | R27: =IF($Q27="","",IF($Q27>=Lists!$M$20,"A",IF($Q27>=Lists!$M$21,"B","C"))) -> C | S27: =IF($A27="","",IF(COUNTIF(Records!$C$5:$C$3000,$A27)=0,"No data",CHOOSE(_xlfn.MAXIFS(Records!$R$5:$R$3000,Records!$C$5:$C$3000,$A27,Records!$Y$5:$Y$3000,"<>Closed")+1,"OK","Alert","Danger"))) -> Alert | T27: =IF($A27="","",COUNTIFS(Records!$C$5:$C$3000,$A27,Records!$R$5:$R$3000,">0",Records!$Y$5:$Y$3000,"<>Closed")) -> 1 | V27: Y | Z27: Y | AG27: Y | AH27: Y | AI27: N | AK27: =IF($AJ27="","",$AJ27-TODAY()) | AL27: =IF($AJ27="","",IF($AK27<0,"Danger",IF($AK27<=Lists!$M$24,"Alert","OK"))) | AM27: Fleet workshop | AP27: 3 | AS27: 60000 | AT27: Default: criticality factors (safety and environment 3, production 2) | AU27: 2021 | AV27: 6
A28: 100502 | B28: LV-02 | C28: Light vehicle LV-02 (pickup) | D28: Mobile fleet | E28: Light vehicles | F28: Light vehicle | J28: Mobile | K28: Active | L28: 3 | M28: 2 | N28: 2 | O28: 1 | P28: 1 | Q28: =IF(COUNT($L28:$P28)<5,"",ROUND(($L28*Lists!$M$2+$M28*Lists!$M$3+$N28*Lists!$M$4+$O28*Lists!$M$5+$P28*Lists!$M$6)/5*100,0)) -> 41 | R28: =IF($Q28="","",IF($Q28>=Lists!$M$20,"A",IF($Q28>=Lists!$M$21,"B","C"))) -> C | S28: =IF($A28="","",IF(COUNTIF(Records!$C$5:$C$3000,$A28)=0,"No data",CHOOSE(_xlfn.MAXIFS(Records!$R$5:$R$3000,Records!$C$5:$C$3000,$A28,Records!$Y$5:$Y$3000,"<>Closed")+1,"OK","Alert","Danger"))) -> OK | T28: =IF($A28="","",COUNTIFS(Records!$C$5:$C$3000,$A28,Records!$R$5:$R$3000,">0",Records!$Y$5:$Y$3000,"<>Closed")) -> 0 | V28: Y | Z28: Y | AG28: Y | AH28: Y | AI28: N | AK28: =IF($AJ28="","",$AJ28-TODAY()) | AL28: =IF($AJ28="","",IF($AK28<0,"Danger",IF($AK28<=Lists!$M$24,"Alert","OK"))) | AM28: Fleet workshop | AP28: 3 | AS28: 60000 | AT28: Default: criticality factors (safety and environment 3, production 2) | AU28: 2022 | AV28: 6
A29: 100601 | B29: HV-01 | C29: Dozer HV-01 | D29: Mobile fleet | E29: Heavy equipment | F29: Heavy equipment | J29: Mobile | K29: Active | L29: 4 | M29: 3 | N29: 3 | O29: 4 | P29: 3 | Q29: =IF(COUNT($L29:$P29)<5,"",ROUND(($L29*Lists!$M$2+$M29*Lists!$M$3+$N29*Lists!$M$4+$O29*Lists!$M$5+$P29*Lists!$M$6)/5*100,0)) -> 69 | R29: =IF($Q29="","",IF($Q29>=Lists!$M$20,"A",IF($Q29>=Lists!$M$21,"B","C"))) -> B | S29: =IF($A29="","",IF(COUNTIF(Records!$C$5:$C$3000,$A29)=0,"No data",CHOOSE(_xlfn.MAXIFS(Records!$R$5:$R$3000,Records!$C$5:$C$3000,$A29,Records!$Y$5:$Y$3000,"<>Closed")+1,"OK","Alert","Danger"))) -> Alert | T29: =IF($A29="","",COUNTIFS(Records!$C$5:$C$3000,$A29,Records!$R$5:$R$3000,">0",Records!$Y$5:$Y$3000,"<>Closed")) -> 1 | V29: Y | Z29: Y | AG29: Y | AH29: Y | AI29: N | AK29: =IF($AJ29="","",$AJ29-TODAY()) | AL29: =IF($AJ29="","",IF($AK29<0,"Danger",IF($AK29<=Lists!$M$24,"Alert","OK"))) | AM29: Fleet workshop | AP29: 4 | AS29: 900000 | AT29: Default: criticality factors (safety and environment 4, production 3) | AU29: 2015 | AV29: 12
A30: 100602 | B30: HV-02 | C30: Compactor HV-02 | D30: Mobile fleet | E30: Heavy equipment | F30: Heavy equipment | J30: Mobile | K30: Active | L30: 4 | M30: 2 | N30: 3 | O30: 3 | P30: 2 | Q30: =IF(COUNT($L30:$P30)<5,"",ROUND(($L30*Lists!$M$2+$M30*Lists!$M$3+$N30*Lists!$M$4+$O30*Lists!$M$5+$P30*Lists!$M$6)/5*100,0)) -> 58 | R30: =IF($Q30="","",IF($Q30>=Lists!$M$20,"A",IF($Q30>=Lists!$M$21,"B","C"))) -> B | S30: =IF($A30="","",IF(COUNTIF(Records!$C$5:$C$3000,$A30)=0,"No data",CHOOSE(_xlfn.MAXIFS(Records!$R$5:$R$3000,Records!$C$5:$C$3000,$A30,Records!$Y$5:$Y$3000,"<>Closed")+1,"OK","Alert","Danger"))) -> Danger | T30: =IF($A30="","",COUNTIFS(Records!$C$5:$C$3000,$A30,Records!$R$5:$R$3000,">0",Records!$Y$5:$Y$3000,"<>Closed")) -> 1 | V30: Y | Z30: Y | AG30: Y | AH30: Y | AI30: N | AK30: =IF($AJ30="","",$AJ30-TODAY()) | AL30: =IF($AJ30="","",IF($AK30<0,"Danger",IF($AK30<=Lists!$M$24,"Alert","OK"))) | AM30: Fleet workshop | AP30: 4 | AS30: 450000 | AT30: Default: criticality factors (safety and environment 4, production 2) | AU30: 2016 | AV30: 12
A31: 100603 | B31: HV-03 | C31: Front-end loader HV-03 | D31: Mobile fleet | E31: Heavy equipment | F31: Heavy equipment | J31: Mobile | K31: Active | L31: 4 | M31: 3 | N31: 3 | O31: 4 | P31: 2 | Q31: =IF(COUNT($L31:$P31)<5,"",ROUND(($L31*Lists!$M$2+$M31*Lists!$M$3+$N31*Lists!$M$4+$O31*Lists!$M$5+$P31*Lists!$M$6)/5*100,0)) -> 67 | R31: =IF($Q31="","",IF($Q31>=Lists!$M$20,"A",IF($Q31>=Lists!$M$21,"B","C"))) -> B | S31: =IF($A31="","",IF(COUNTIF(Records!$C$5:$C$3000,$A31)=0,"No data",CHOOSE(_xlfn.MAXIFS(Records!$R$5:$R$3000,Records!$C$5:$C$3000,$A31,Records!$Y$5:$Y$3000,"<>Closed")+1,"OK","Alert","Danger"))) -> Alert | T31: =IF($A31="","",COUNTIFS(Records!$C$5:$C$3000,$A31,Records!$R$5:$R$3000,">0",Records!$Y$5:$Y$3000,"<>Closed")) -> 1 | V31: Y | Z31: Y | AG31: Y | AH31: Y | AI31: N | AK31: =IF($AJ31="","",$AJ31-TODAY()) | AL31: =IF($AJ31="","",IF($AK31<0,"Danger",IF($AK31<=Lists!$M$24,"Alert","OK"))) | AM31: Fleet workshop | AP31: 4 | AS31: 700000 | AT31: Default: criticality factors (safety and environment 4, production 3) | AU31: 2017 | AV31: 12
Q32: =IF(COUNT($L32:$P32)<5,"",ROUND(($L32*Lists!$M$2+$M32*Lists!$M$3+$N32*Lists!$M$4+$O32*Lists!$M$5+$P32*Lists!$M$6)/5*100,0)) | R32: =IF($Q32="","",IF($Q32>=Lists!$M$20,"A",IF($Q32>=Lists!$M$21,"B","C"))) | S32: =IF($A32="","",IF(COUNTIF(Records!$C$5:$C$3000,$A32)=0,"No data",CHOOSE(_xlfn.MAXIFS(Records!$R$5:$R$3000,Records!$C$5:$C$3000,$A32,Records!$Y$5:$Y$3000,"<>Closed")+1,"OK","Alert","Danger"))) | T32: =IF($A32="","",COUNTIFS(Records!$C$5:$C$3000,$A32,Records!$R$5:$R$3000,">0",Records!$Y$5:$Y$3000,"<>Closed")) | AK32: =IF($AJ32="","",$AJ32-TODAY()) | AL32: =IF($AJ32="","",IF($AK32<0,"Danger",IF($AK32<=Lists!$M$24,"Alert","OK")))
Q33: =IF(COUNT($L33:$P33)<5,"",ROUND(($L33*Lists!$M$2+$M33*Lists!$M$3+$N33*Lists!$M$4+$O33*Lists!$M$5+$P33*Lists!$M$6)/5*100,0)) | R33: =IF($Q33="","",IF($Q33>=Lists!$M$20,"A",IF($Q33>=Lists!$M$21,"B","C"))) | S33: =IF($A33="","",IF(COUNTIF(Records!$C$5:$C$3000,$A33)=0,"No data",CHOOSE(_xlfn.MAXIFS(Records!$R$5:$R$3000,Records!$C$5:$C$3000,$A33,Records!$Y$5:$Y$3000,"<>Closed")+1,"OK","Alert","Danger"))) | T33: =IF($A33="","",COUNTIFS(Records!$C$5:$C$3000,$A33,Records!$R$5:$R$3000,">0",Records!$Y$5:$Y$3000,"<>Closed")) | AK33: =IF($AJ33="","",$AJ33-TODAY()) | AL33: =IF($AJ33="","",IF($AK33<0,"Danger",IF($AK33<=Lists!$M$24,"Alert","OK")))
Q34: =IF(COUNT($L34:$P34)<5,"",ROUND(($L34*Lists!$M$2+$M34*Lists!$M$3+$N34*Lists!$M$4+$O34*Lists!$M$5+$P34*Lists!$M$6)/5*100,0)) | R34: =IF($Q34="","",IF($Q34>=Lists!$M$20,"A",IF($Q34>=Lists!$M$21,"B","C"))) | S34: =IF($A34="","",IF(COUNTIF(Records!$C$5:$C$3000,$A34)=0,"No data",CHOOSE(_xlfn.MAXIFS(Records!$R$5:$R$3000,Records!$C$5:$C$3000,$A34,Records!$Y$5:$Y$3000,"<>Closed")+1,"OK","Alert","Danger"))) | T34: =IF($A34="","",COUNTIFS(Records!$C$5:$C$3000,$A34,Records!$R$5:$R$3000,">0",Records!$Y$5:$Y$3000,"<>Closed")) | AK34: =IF($AJ34="","",$AJ34-TODAY()) | AL34: =IF($AJ34="","",IF($AK34<0,"Danger",IF($AK34<=Lists!$M$24,"Alert","OK")))
Q35: =IF(COUNT($L35:$P35)<5,"",ROUND(($L35*Lists!$M$2+$M35*Lists!$M$3+$N35*Lists!$M$4+$O35*Lists!$M$5+$P35*Lists!$M$6)/5*100,0)) | R35: =IF($Q35="","",IF($Q35>=Lists!$M$20,"A",IF($Q35>=Lists!$M$21,"B","C"))) | S35: =IF($A35="","",IF(COUNTIF(Records!$C$5:$C$3000,$A35)=0,"No data",CHOOSE(_xlfn.MAXIFS(Records!$R$5:$R$3000,Records!$C$5:$C$3000,$A35,Records!$Y$5:$Y$3000,"<>Closed")+1,"OK","Alert","Danger"))) | T35: =IF($A35="","",COUNTIFS(Records!$C$5:$C$3000,$A35,Records!$R$5:$R$3000,">0",Records!$Y$5:$Y$3000,"<>Closed")) | AK35: =IF($AJ35="","",$AJ35-TODAY()) | AL35: =IF($AJ35="","",IF($AK35<0,"Danger",IF($AK35<=Lists!$M$24,"Alert","OK")))
Q36: =IF(COUNT($L36:$P36)<5,"",ROUND(($L36*Lists!$M$2+$M36*Lists!$M$3+$N36*Lists!$M$4+$O36*Lists!$M$5+$P36*Lists!$M$6)/5*100,0)) | R36: =IF($Q36="","",IF($Q36>=Lists!$M$20,"A",IF($Q36>=Lists!$M$21,"B","C"))) | S36: =IF($A36="","",IF(COUNTIF(Records!$C$5:$C$3000,$A36)=0,"No data",CHOOSE(_xlfn.MAXIFS(Records!$R$5:$R$3000,Records!$C$5:$C$3000,$A36,Records!$Y$5:$Y$3000,"<>Closed")+1,"OK","Alert","Danger"))) | T36: =IF($A36="","",COUNTIFS(Records!$C$5:$C$3000,$A36,Records!$R$5:$R$3000,">0",Records!$Y$5:$Y$3000,"<>Closed")) | AK36: =IF($AJ36="","",$AJ36-TODAY()) | AL36: =IF($AJ36="","",IF($AK36<0,"Danger",IF($AK36<=Lists!$M$24,"Alert","OK")))
Q37: =IF(COUNT($L37:$P37)<5,"",ROUND(($L37*Lists!$M$2+$M37*Lists!$M$3+$N37*Lists!$M$4+$O37*Lists!$M$5+$P37*Lists!$M$6)/5*100,0)) | R37: =IF($Q37="","",IF($Q37>=Lists!$M$20,"A",IF($Q37>=Lists!$M$21,"B","C"))) | S37: =IF($A37="","",IF(COUNTIF(Records!$C$5:$C$3000,$A37)=0,"No data",CHOOSE(_xlfn.MAXIFS(Records!$R$5:$R$3000,Records!$C$5:$C$3000,$A37,Records!$Y$5:$Y$3000,"<>Closed")+1,"OK","Alert","Danger"))) | T37: =IF($A37="","",COUNTIFS(Records!$C$5:$C$3000,$A37,Records!$R$5:$R$3000,">0",Records!$Y$5:$Y$3000,"<>Closed")) | AK37: =IF($AJ37="","",$AJ37-TODAY()) | AL37: =IF($AJ37="","",IF($AK37<0,"Danger",IF($AK37<=Lists!$M$24,"Alert","OK")))
Q38: =IF(COUNT($L38:$P38)<5,"",ROUND(($L38*Lists!$M$2+$M38*Lists!$M$3+$N38*Lists!$M$4+$O38*Lists!$M$5+$P38*Lists!$M$6)/5*100,0)) | R38: =IF($Q38="","",IF($Q38>=Lists!$M$20,"A",IF($Q38>=Lists!$M$21,"B","C"))) | S38: =IF($A38="","",IF(COUNTIF(Records!$C$5:$C$3000,$A38)=0,"No data",CHOOSE(_xlfn.MAXIFS(Records!$R$5:$R$3000,Records!$C$5:$C$3000,$A38,Records!$Y$5:$Y$3000,"<>Closed")+1,"OK","Alert","Danger"))) | T38: =IF($A38="","",COUNTIFS(Records!$C$5:$C$3000,$A38,Records!$R$5:$R$3000,">0",Records!$Y$5:$Y$3000,"<>Closed")) | AK38: =IF($AJ38="","",$AJ38-TODAY()) | AL38: =IF($AJ38="","",IF($AK38<0,"Danger",IF($AK38<=Lists!$M$24,"Alert","OK")))
Q39: =IF(COUNT($L39:$P39)<5,"",ROUND(($L39*Lists!$M$2+$M39*Lists!$M$3+$N39*Lists!$M$4+$O39*Lists!$M$5+$P39*Lists!$M$6)/5*100,0)) | R39: =IF($Q39="","",IF($Q39>=Lists!$M$20,"A",IF($Q39>=Lists!$M$21,"B","C"))) | S39: =IF($A39="","",IF(COUNTIF(Records!$C$5:$C$3000,$A39)=0,"No data",CHOOSE(_xlfn.MAXIFS(Records!$R$5:$R$3000,Records!$C$5:$C$3000,$A39,Records!$Y$5:$Y$3000,"<>Closed")+1,"OK","Alert","Danger"))) | T39: =IF($A39="","",COUNTIFS(Records!$C$5:$C$3000,$A39,Records!$R$5:$R$3000,">0",Records!$Y$5:$Y$3000,"<>Closed")) | AK39: =IF($AJ39="","",$AJ39-TODAY()) | AL39: =IF($AJ39="","",IF($AK39<0,"Danger",IF($AK39<=Lists!$M$24,"Alert","OK")))
Q40: =IF(COUNT($L40:$P40)<5,"",ROUND(($L40*Lists!$M$2+$M40*Lists!$M$3+$N40*Lists!$M$4+$O40*Lists!$M$5+$P40*Lists!$M$6)/5*100,0)) | R40: =IF($Q40="","",IF($Q40>=Lists!$M$20,"A",IF($Q40>=Lists!$M$21,"B","C"))) | S40: =IF($A40="","",IF(COUNTIF(Records!$C$5:$C$3000,$A40)=0,"No data",CHOOSE(_xlfn.MAXIFS(Records!$R$5:$R$3000,Records!$C$5:$C$3000,$A40,Records!$Y$5:$Y$3000,"<>Closed")+1,"OK","Alert","Danger"))) | T40: =IF($A40="","",COUNTIFS(Records!$C$5:$C$3000,$A40,Records!$R$5:$R$3000,">0",Records!$Y$5:$Y$3000,"<>Closed")) | AK40: =IF($AJ40="","",$AJ40-TODAY()) | AL40: =IF($AJ40="","",IF($AK40<0,"Danger",IF($AK40<=Lists!$M$24,"Alert","OK")))
Q41: =IF(COUNT($L41:$P41)<5,"",ROUND(($L41*Lists!$M$2+$M41*Lists!$M$3+$N41*Lists!$M$4+$O41*Lists!$M$5+$P41*Lists!$M$6)/5*100,0)) | R41: =IF($Q41="","",IF($Q41>=Lists!$M$20,"A",IF($Q41>=Lists!$M$21,"B","C"))) | S41: =IF($A41="","",IF(COUNTIF(Records!$C$5:$C$3000,$A41)=0,"No data",CHOOSE(_xlfn.MAXIFS(Records!$R$5:$R$3000,Records!$C$5:$C$3000,$A41,Records!$Y$5:$Y$3000,"<>Closed")+1,"OK","Alert","Danger"))) | T41: =IF($A41="","",COUNTIFS(Records!$C$5:$C$3000,$A41,Records!$R$5:$R$3000,">0",Records!$Y$5:$Y$3000,"<>Closed")) | AK41: =IF($AJ41="","",$AJ41-TODAY()) | AL41: =IF($AJ41="","",IF($AK41<0,"Danger",IF($AK41<=Lists!$M$24,"Alert","OK")))
Q42: =IF(COUNT($L42:$P42)<5,"",ROUND(($L42*Lists!$M$2+$M42*Lists!$M$3+$N42*Lists!$M$4+$O42*Lists!$M$5+$P42*Lists!$M$6)/5*100,0)) | R42: =IF($Q42="","",IF($Q42>=Lists!$M$20,"A",IF($Q42>=Lists!$M$21,"B","C"))) | S42: =IF($A42="","",IF(COUNTIF(Records!$C$5:$C$3000,$A42)=0,"No data",CHOOSE(_xlfn.MAXIFS(Records!$R$5:$R$3000,Records!$C$5:$C$3000,$A42,Records!$Y$5:$Y$3000,"<>Closed")+1,"OK","Alert","Danger"))) | T42: =IF($A42="","",COUNTIFS(Records!$C$5:$C$3000,$A42,Records!$R$5:$R$3000,">0",Records!$Y$5:$Y$3000,"<>Closed")) | AK42: =IF($AJ42="","",$AJ42-TODAY()) | AL42: =IF($AJ42="","",IF($AK42<0,"Danger",IF($AK42<=Lists!$M$24,"Alert","OK")))
Q43: =IF(COUNT($L43:$P43)<5,"",ROUND(($L43*Lists!$M$2+$M43*Lists!$M$3+$N43*Lists!$M$4+$O43*Lists!$M$5+$P43*Lists!$M$6)/5*100,0)) | R43: =IF($Q43="","",IF($Q43>=Lists!$M$20,"A",IF($Q43>=Lists!$M$21,"B","C"))) | S43: =IF($A43="","",IF(COUNTIF(Records!$C$5:$C$3000,$A43)=0,"No data",CHOOSE(_xlfn.MAXIFS(Records!$R$5:$R$3000,Records!$C$5:$C$3000,$A43,Records!$Y$5:$Y$3000,"<>Closed")+1,"OK","Alert","Danger"))) | T43: =IF($A43="","",COUNTIFS(Records!$C$5:$C$3000,$A43,Records!$R$5:$R$3000,">0",Records!$Y$5:$Y$3000,"<>Closed")) | AK43: =IF($AJ43="","",$AJ43-TODAY()) | AL43: =IF($AJ43="","",IF($AK43<0,"Danger",IF($AK43<=Lists!$M$24,"Alert","OK")))
... Q1000: =IF(COUNT($L1000:$P1000)<5,"",ROUND(($L1000*Lists!$M$2+$M1000*Lists!$M$3+$N1000*Lists!$M$4+$O1000*Lists!$M$5+$P1000*Lists!$M$6)/5*100,0)) | R1000: =IF($Q1000="","",IF($Q1000>=Lists!$M$20,"A",IF($Q1000>=Lists!$M$21,"B","C"))) | S1000: =IF($A1000="","",IF(COUNTIF(Records!$C$5:$C$3000,$A1000)=0,"No data",CHOOSE(_xlfn.MAXIFS(Records!$R$5:$R$3000,Records!$C$5:$C$3000,$A1000,Records!$Y$5:$Y$3000,"<>Closed")+1,"OK","Alert","Danger"))) | T1000: =IF($A1000="","",COUNTIFS(Records!$C$5:$C$3000,$A1000,Records!$R$5:$R$3000,">0",Records!$Y$5:$Y$3000,"<>Closed")) | AK1000: =IF($AJ1000="","",$AJ1000-TODAY()) | AL1000: =IF($AJ1000="","",IF($AK1000<0,"Danger",IF($AK1000<=Lists!$M$24,"Alert","OK")))

Sheet Records
A1: AHIM Common Record
A2: One row per reading, checklist defect or certificate check, from ANY source. Dark headers = enter. Grey = automatic. Blue italic rows are SAMPLES showing each source: delete them before go-live.
A4: Record ID | B4: Date | C4: Pronto asset no. | D4: Description | E4: Area | F4: Class | G4: ACI | H4: Source (input) | I4: Technique | J4: Component / parameter / checklist item | K4: Value | L4: Unit | M4: Alert limit | N4: Danger limit | O4: Limit direction | P4: Inspector status | Q4: Status | R4: Severity | S4: Finding | T4: Recommendation | U4: Priority score | V4: Priority | W4: Due date | X4: Pronto WO no. | Y4: Record stage | Z4: Inspector | AA4: Date closed | AB4: Verified by | AC4: Days open | AD4: Due status | AE4: Remarks | AF4: Failure mode (ISO 14224) | AG4: Failure mechanism (ISO 14224) | AH4: Damage mechanism (API 571) | AI4: Execution window | AJ4: Likelihood override (1-5)
A5: =IF($C5="","","R"&TEXT(ROW()-4,"00000")) -> R00001 | B5: 45931 | C5: 100110 | D5: =IF($C5="","",IFERROR(INDEX(Asset_Register!$C$5:$C$1000,MATCH($C5,Asset_Register!$A$5:$A$1000,0)),"Not in register")) -> Molten sulphur pump | E5: =IF($C5="","",IFERROR(INDEX(Asset_Register!$D$5:$D$1000,MATCH($C5,Asset_Register!$A$5:$A$1000,0)),"Not in register")) -> Acid plant | F5: =IF($C5="","",IFERROR(INDEX(Asset_Register!$R$5:$R$1000,MATCH($C5,Asset_Register!$A$5:$A$1000,0)),"Not in register")) -> B | G5: =IF($C5="","",IFERROR(INDEX(Asset_Register!$Q$5:$Q$1000,MATCH($C5,Asset_Register!$A$5:$A$1000,0)),"Not in register")) -> 61 | H5: Vibration & visual route | I5: Vibration | J5: Overall velocity (max point) | K5: 2.4 | L5: mm/s | M5: 4.5 | N5: 7.1 | O5: Higher is worse | Q5: =IF($C5="","",IF($P5<>"",$P5,IF(AND(ISNUMBER($K5),ISNUMBER($M5),ISNUMBER($N5)),IF($O5="Lower is worse",IF($K5<=$N5,"Danger",IF($K5<=$M5,"Alert","OK")),IF($K5>=$N5,"Danger",IF($K5>=$M5,"Alert","OK"))),"Not set"))) -> OK | R5: =IF(OR($Q5="",$Q5="Not set"),"",MATCH($Q5,Lists!$F$2:$F$4,0)-1) -> 0 | U5: =IF(OR($Q5="",$Q5="OK",$Q5="Not set",NOT(ISNUMBER($G5))),"",ROUND($G5*IF($Q5="Danger",Lists!$M$15,Lists!$M$16),0)) | V5: =IF($U5="","",IF(OR($Q5="Danger",$U5>=Lists!$M$10),"P1",IF($U5>=Lists!$M$11,"P2","P3"))) | W5: =IF(OR($V5="",$B5=""),"",$B5+INDEX(Lists!$N$10:$N$12,MATCH($V5,Lists!$L$10:$L$12,0))) | Y5: No action | Z5: RCM Specialist | AC5: =IF(OR($U5="",$B5=""),"",IF($AA5<>"",$AA5-$B5,TODAY()-$B5)) | AD5: =IF($W5="","",IF($Y5="Closed",IF($AA5="","Closed",IF($AA5<=$W5,"Closed on time","Closed late")),IF(TODAY()>$W5,"Overdue","Within time")))
A6: =IF($C6="","","R"&TEXT(ROW()-4,"00000")) -> R00002 | B6: 45931 | C6: 100115 | D6: =IF($C6="","",IFERROR(INDEX(Asset_Register!$C$5:$C$1000,MATCH($C6,Asset_Register!$A$5:$A$1000,0)),"Not in register")) -> Instrument air receiver | E6: =IF($C6="","",IFERROR(INDEX(Asset_Register!$D$5:$D$1000,MATCH($C6,Asset_Register!$A$5:$A$1000,0)),"Not in register")) -> Acid plant | F6: =IF($C6="","",IFERROR(INDEX(Asset_Register!$R$5:$R$1000,MATCH($C6,Asset_Register!$A$5:$A$1000,0)),"Not in register")) -> B | G6: =IF($C6="","",IFERROR(INDEX(Asset_Register!$Q$5:$Q$1000,MATCH($C6,Asset_Register!$A$5:$A$1000,0)),"Not in register")) -> 53 | H6: Ultrasonic report | I6: Ultrasonics (airborne) | J6: Leak survey level | K6: 12 | L6: dBµV | M6: 30 | N6: 40 | O6: Higher is worse | Q6: =IF($C6="","",IF($P6<>"",$P6,IF(AND(ISNUMBER($K6),ISNUMBER($M6),ISNUMBER($N6)),IF($O6="Lower is worse",IF($K6<=$N6,"Danger",IF($K6<=$M6,"Alert","OK")),IF($K6>=$N6,"Danger",IF($K6>=$M6,"Alert","OK"))),"Not set"))) -> OK | R6: =IF(OR($Q6="",$Q6="Not set"),"",MATCH($Q6,Lists!$F$2:$F$4,0)-1) -> 0 | U6: =IF(OR($Q6="",$Q6="OK",$Q6="Not set",NOT(ISNUMBER($G6))),"",ROUND($G6*IF($Q6="Danger",Lists!$M$15,Lists!$M$16),0)) | V6: =IF($U6="","",IF(OR($Q6="Danger",$U6>=Lists!$M$10),"P1",IF($U6>=Lists!$M$11,"P2","P3"))) | W6: =IF(OR($V6="",$B6=""),"",$B6+INDEX(Lists!$N$10:$N$12,MATCH($V6,Lists!$L$10:$L$12,0))) | Y6: No action | Z6: RCM Specialist | AC6: =IF(OR($U6="",$B6=""),"",IF($AA6<>"",$AA6-$B6,TODAY()-$B6)) | AD6: =IF($W6="","",IF($Y6="Closed",IF($AA6="","Closed",IF($AA6<=$W6,"Closed on time","Closed late")),IF(TODAY()>$W6,"Overdue","Within time")))
A7: =IF($C7="","","R"&TEXT(ROW()-4,"00000")) -> R00003 | B7: 45932 | C7: 100108 | D7: =IF($C7="","",IFERROR(INDEX(Asset_Register!$C$5:$C$1000,MATCH($C7,Asset_Register!$A$5:$A$1000,0)),"Not in register")) -> Boiler feed water pump A | E7: =IF($C7="","",IFERROR(INDEX(Asset_Register!$D$5:$D$1000,MATCH($C7,Asset_Register!$A$5:$A$1000,0)),"Not in register")) -> Acid plant | F7: =IF($C7="","",IFERROR(INDEX(Asset_Register!$R$5:$R$1000,MATCH($C7,Asset_Register!$A$5:$A$1000,0)),"Not in register")) -> A | G7: =IF($C7="","",IFERROR(INDEX(Asset_Register!$Q$5:$Q$1000,MATCH($C7,Asset_Register!$A$5:$A$1000,0)),"Not in register")) -> 75 | H7: Vibration & visual route | I7: Vibration | J7: Overall velocity (max point) | K7: 2.5 | L7: mm/s | M7: 4.5 | N7: 7.1 | O7: Higher is worse | Q7: =IF($C7="","",IF($P7<>"",$P7,IF(AND(ISNUMBER($K7),ISNUMBER($M7),ISNUMBER($N7)),IF($O7="Lower is worse",IF($K7<=$N7,"Danger",IF($K7<=$M7,"Alert","OK")),IF($K7>=$N7,"Danger",IF($K7>=$M7,"Alert","OK"))),"Not set"))) -> OK | R7: =IF(OR($Q7="",$Q7="Not set"),"",MATCH($Q7,Lists!$F$2:$F$4,0)-1) -> 0 | U7: =IF(OR($Q7="",$Q7="OK",$Q7="Not set",NOT(ISNUMBER($G7))),"",ROUND($G7*IF($Q7="Danger",Lists!$M$15,Lists!$M$16),0)) | V7: =IF($U7="","",IF(OR($Q7="Danger",$U7>=Lists!$M$10),"P1",IF($U7>=Lists!$M$11,"P2","P3"))) | W7: =IF(OR($V7="",$B7=""),"",$B7+INDEX(Lists!$N$10:$N$12,MATCH($V7,Lists!$L$10:$L$12,0))) | Y7: No action | Z7: RCM Specialist | AC7: =IF(OR($U7="",$B7=""),"",IF($AA7<>"",$AA7-$B7,TODAY()-$B7)) | AD7: =IF($W7="","",IF($Y7="Closed",IF($AA7="","Closed",IF($AA7<=$W7,"Closed on time","Closed late")),IF(TODAY()>$W7,"Overdue","Within time")))
A8: =IF($C8="","","R"&TEXT(ROW()-4,"00000")) -> R00004 | B8: 45932 | C8: 100111 | D8: =IF($C8="","",IFERROR(INDEX(Asset_Register!$C$5:$C$1000,MATCH($C8,Asset_Register!$A$5:$A$1000,0)),"Not in register")) -> Sulphur melter agitator | E8: =IF($C8="","",IFERROR(INDEX(Asset_Register!$D$5:$D$1000,MATCH($C8,Asset_Register!$A$5:$A$1000,0)),"Not in register")) -> Acid plant | F8: =IF($C8="","",IFERROR(INDEX(Asset_Register!$R$5:$R$1000,MATCH($C8,Asset_Register!$A$5:$A$1000,0)),"Not in register")) -> C | G8: =IF($C8="","",IFERROR(INDEX(Asset_Register!$Q$5:$Q$1000,MATCH($C8,Asset_Register!$A$5:$A$1000,0)),"Not in register")) -> 43 | H8: Vibration & visual route | I8: Vibration | J8: Overall velocity (max point) | K8: 1.4 | L8: mm/s | M8: 4.5 | N8: 7.1 | O8: Higher is worse | Q8: =IF($C8="","",IF($P8<>"",$P8,IF(AND(ISNUMBER($K8),ISNUMBER($M8),ISNUMBER($N8)),IF($O8="Lower is worse",IF($K8<=$N8,"Danger",IF($K8<=$M8,"Alert","OK")),IF($K8>=$N8,"Danger",IF($K8>=$M8,"Alert","OK"))),"Not set"))) -> OK | R8: =IF(OR($Q8="",$Q8="Not set"),"",MATCH($Q8,Lists!$F$2:$F$4,0)-1) -> 0 | U8: =IF(OR($Q8="",$Q8="OK",$Q8="Not set",NOT(ISNUMBER($G8))),"",ROUND($G8*IF($Q8="Danger",Lists!$M$15,Lists!$M$16),0)) | V8: =IF($U8="","",IF(OR($Q8="Danger",$U8>=Lists!$M$10),"P1",IF($U8>=Lists!$M$11,"P2","P3"))) | W8: =IF(OR($V8="",$B8=""),"",$B8+INDEX(Lists!$N$10:$N$12,MATCH($V8,Lists!$L$10:$L$12,0))) | Y8: No action | Z8: RCM Specialist | AC8: =IF(OR($U8="",$B8=""),"",IF($AA8<>"",$AA8-$B8,TODAY()-$B8)) | AD8: =IF($W8="","",IF($Y8="Closed",IF($AA8="","Closed",IF($AA8<=$W8,"Closed on time","Closed late")),IF(TODAY()>$W8,"Overdue","Within time")))
A9: =IF($C9="","","R"&TEXT(ROW()-4,"00000")) -> R00005 | B9: 45935 | C9: 100109 | D9: =IF($C9="","",IFERROR(INDEX(Asset_Register!$C$5:$C$1000,MATCH($C9,Asset_Register!$A$5:$A$1000,0)),"Not in register")) -> Boiler feed water pump B | E9: =IF($C9="","",IFERROR(INDEX(Asset_Register!$D$5:$D$1000,MATCH($C9,Asset_Register!$A$5:$A$1000,0)),"Not in register")) -> Acid plant | F9: =IF($C9="","",IFERROR(INDEX(Asset_Register!$R$5:$R$1000,MATCH($C9,Asset_Register!$A$5:$A$1000,0)),"Not in register")) -> A | G9: =IF($C9="","",IFERROR(INDEX(Asset_Register!$Q$5:$Q$1000,MATCH($C9,Asset_Register!$A$5:$A$1000,0)),"Not in register")) -> 71 | H9: Vibration & visual route | I9: Vibration | J9: Overall velocity (max point) | K9: 1.8 | L9: mm/s | M9: 4.5 | N9: 7.1 | O9: Higher is worse | Q9: =IF($C9="","",IF($P9<>"",$P9,IF(AND(ISNUMBER($K9),ISNUMBER($M9),ISNUMBER($N9)),IF($O9="Lower is worse",IF($K9<=$N9,"Danger",IF($K9<=$M9,"Alert","OK")),IF($K9>=$N9,"Danger",IF($K9>=$M9,"Alert","OK"))),"Not set"))) -> OK | R9: =IF(OR($Q9="",$Q9="Not set"),"",MATCH($Q9,Lists!$F$2:$F$4,0)-1) -> 0 | U9: =IF(OR($Q9="",$Q9="OK",$Q9="Not set",NOT(ISNUMBER($G9))),"",ROUND($G9*IF($Q9="Danger",Lists!$M$15,Lists!$M$16),0)) | V9: =IF($U9="","",IF(OR($Q9="Danger",$U9>=Lists!$M$10),"P1",IF($U9>=Lists!$M$11,"P2","P3"))) | W9: =IF(OR($V9="",$B9=""),"",$B9+INDEX(Lists!$N$10:$N$12,MATCH($V9,Lists!$L$10:$L$12,0))) | Y9: No action | Z9: RCM Specialist | AC9: =IF(OR($U9="",$B9=""),"",IF($AA9<>"",$AA9-$B9,TODAY()-$B9)) | AD9: =IF($W9="","",IF($Y9="Closed",IF($AA9="","Closed",IF($AA9<=$W9,"Closed on time","Closed late")),IF(TODAY()>$W9,"Overdue","Within time")))
A10: =IF($C10="","","R"&TEXT(ROW()-4,"00000")) -> R00006 | B10: 45935 | C10: 100108 | D10: =IF($C10="","",IFERROR(INDEX(Asset_Register!$C$5:$C$1000,MATCH($C10,Asset_Register!$A$5:$A$1000,0)),"Not in register")) -> Boiler feed water pump A | E10: =IF($C10="","",IFERROR(INDEX(Asset_Register!$D$5:$D$1000,MATCH($C10,Asset_Register!$A$5:$A$1000,0)),"Not in register")) -> Acid plant | F10: =IF($C10="","",IFERROR(INDEX(Asset_Register!$R$5:$R$1000,MATCH($C10,Asset_Register!$A$5:$A$1000,0)),"Not in register")) -> A | G10: =IF($C10="","",IFERROR(INDEX(Asset_Register!$Q$5:$Q$1000,MATCH($C10,Asset_Register!$A$5:$A$1000,0)),"Not in register")) -> 75 | H10: Oil analysis | I10: Lubrication / oil | J10: Water in bearing oil | K10: 150 | L10: ppm | M10: 1000 | N10: 2000 | O10: Higher is worse | Q10: =IF($C10="","",IF($P10<>"",$P10,IF(AND(ISNUMBER($K10),ISNUMBER($M10),ISNUMBER($N10)),IF($O10="Lower is worse",IF($K10<=$N10,"Danger",IF($K10<=$M10,"Alert","OK")),IF($K10>=$N10,"Danger",IF($K10>=$M10,"Alert","OK"))),"Not set"))) -> OK | R10: =IF(OR($Q10="",$Q10="Not set"),"",MATCH($Q10,Lists!$F$2:$F$4,0)-1) -> 0 | U10: =IF(OR($Q10="",$Q10="OK",$Q10="Not set",NOT(ISNUMBER($G10))),"",ROUND($G10*IF($Q10="Danger",Lists!$M$15,Lists!$M$16),0)) | V10: =IF($U10="","",IF(OR($Q10="Danger",$U10>=Lists!$M$10),"P1",IF($U10>=Lists!$M$11,"P2","P3"))) | W10: =IF(OR($V10="",$B10=""),"",$B10+INDEX(Lists!$N$10:$N$12,MATCH($V10,Lists!$L$10:$L$12,0))) | Y10: No action | Z10: RCM Specialist | AC10: =IF(OR($U10="",$B10=""),"",IF($AA10<>"",$AA10-$B10,TODAY()-$B10)) | AD10: =IF($W10="","",IF($Y10="Closed",IF($AA10="","Closed",IF($AA10<=$W10,"Closed on time","Closed late")),IF(TODAY()>$W10,"Overdue","Within time")))
A11: =IF($C11="","","R"&TEXT(ROW()-4,"00000")) -> R00007 | B11: 45938 | C11: 100101 | D11: =IF($C11="","",IFERROR(INDEX(Asset_Register!$C$5:$C$1000,MATCH($C11,Asset_Register!$A$5:$A$1000,0)),"Not in register")) -> Sulphur furnace | E11: =IF($C11="","",IFERROR(INDEX(Asset_Register!$D$5:$D$1000,MATCH($C11,Asset_Register!$A$5:$A$1000,0)),"Not in register")) -> Acid plant | F11: =IF($C11="","",IFERROR(INDEX(Asset_Register!$R$5:$R$1000,MATCH($C11,Asset_Register!$A$5:$A$1000,0)),"Not in register")) -> A | G11: =IF($C11="","",IFERROR(INDEX(Asset_Register!$Q$5:$Q$1000,MATCH($C11,Asset_Register!$A$5:$A$1000,0)),"Not in register")) -> 94 | H11: IR survey | I11: Infrared | J11: Burner-end shell temperature | K11: 210 | L11: °C | M11: 280 | N11: 320 | O11: Higher is worse | Q11: =IF($C11="","",IF($P11<>"",$P11,IF(AND(ISNUMBER($K11),ISNUMBER($M11),ISNUMBER($N11)),IF($O11="Lower is worse",IF($K11<=$N11,"Danger",IF($K11<=$M11,"Alert","OK")),IF($K11>=$N11,"Danger",IF($K11>=$M11,"Alert","OK"))),"Not set"))) -> OK | R11: =IF(OR($Q11="",$Q11="Not set"),"",MATCH($Q11,Lists!$F$2:$F$4,0)-1) -> 0 | U11: =IF(OR($Q11="",$Q11="OK",$Q11="Not set",NOT(ISNUMBER($G11))),"",ROUND($G11*IF($Q11="Danger",Lists!$M$15,Lists!$M$16),0)) | V11: =IF($U11="","",IF(OR($Q11="Danger",$U11>=Lists!$M$10),"P1",IF($U11>=Lists!$M$11,"P2","P3"))) | W11: =IF(OR($V11="",$B11=""),"",$B11+INDEX(Lists!$N$10:$N$12,MATCH($V11,Lists!$L$10:$L$12,0))) | Y11: No action | Z11: RCM Specialist | AC11: =IF(OR($U11="",$B11=""),"",IF($AA11<>"",$AA11-$B11,TODAY()-$B11)) | AD11: =IF($W11="","",IF($Y11="Closed",IF($AA11="","Closed",IF($AA11<=$W11,"Closed on time","Closed late")),IF(TODAY()>$W11,"Overdue","Within time")))
A12: =IF($C12="","","R"&TEXT(ROW()-4,"00000")) -> R00008 | B12: 45940 | C12: 100112 | D12: =IF($C12="","",IFERROR(INDEX(Asset_Register!$C$5:$C$1000,MATCH($C12,Asset_Register!$A$5:$A$1000,0)),"Not in register")) -> Cooling tower fan 1 | E12: =IF($C12="","",IFERROR(INDEX(Asset_Register!$D$5:$D$1000,MATCH($C12,Asset_Register!$A$5:$A$1000,0)),"Not in register")) -> Acid plant | F12: =IF($C12="","",IFERROR(INDEX(Asset_Register!$R$5:$R$1000,MATCH($C12,Asset_Register!$A$5:$A$1000,0)),"Not in register")) -> B | G12: =IF($C12="","",IFERROR(INDEX(Asset_Register!$Q$5:$Q$1000,MATCH($C12,Asset_Register!$A$5:$A$1000,0)),"Not in register")) -> 50 | H12: Vibration & visual route | I12: Vibration | J12: Gearbox overall velocity | K12: 3.2 | L12: mm/s | M12: 4.5 | N12: 7.1 | O12: Higher is worse | Q12: =IF($C12="","",IF($P12<>"",$P12,IF(AND(ISNUMBER($K12),ISNUMBER($M12),ISNUMBER($N12)),IF($O12="Lower is worse",IF($K12<=$N12,"Danger",IF($K12<=$M12,"Alert","OK")),IF($K12>=$N12,"Danger",IF($K12>=$M12,"Alert","OK"))),"Not set"))) -> OK | R12: =IF(OR($Q12="",$Q12="Not set"),"",MATCH($Q12,Lists!$F$2:$F$4,0)-1) -> 0 | U12: =IF(OR($Q12="",$Q12="OK",$Q12="Not set",NOT(ISNUMBER($G12))),"",ROUND($G12*IF($Q12="Danger",Lists!$M$15,Lists!$M$16),0)) | V12: =IF($U12="","",IF(OR($Q12="Danger",$U12>=Lists!$M$10),"P1",IF($U12>=Lists!$M$11,"P2","P3"))) | W12: =IF(OR($V12="",$B12=""),"",$B12+INDEX(Lists!$N$10:$N$12,MATCH($V12,Lists!$L$10:$L$12,0))) | Y12: No action | Z12: RCM Specialist | AC12: =IF(OR($U12="",$B12=""),"",IF($AA12<>"",$AA12-$B12,TODAY()-$B12)) | AD12: =IF($W12="","",IF($Y12="Closed",IF($AA12="","Closed",IF($AA12<=$W12,"Closed on time","Closed late")),IF(TODAY()>$W12,"Overdue","Within time")))
A13: =IF($C13="","","R"&TEXT(ROW()-4,"00000")) -> R00009 | B13: 45940 | C13: 100201 | D13: =IF($C13="","",IFERROR(INDEX(Asset_Register!$C$5:$C$1000,MATCH($C13,Asset_Register!$A$5:$A$1000,0)),"Not in register")) -> Calciner kiln 1080 | E13: =IF($C13="","",IFERROR(INDEX(Asset_Register!$D$5:$D$1000,MATCH($C13,Asset_Register!$A$5:$A$1000,0)),"Not in register")) -> Calciner | F13: =IF($C13="","",IFERROR(INDEX(Asset_Register!$R$5:$R$1000,MATCH($C13,Asset_Register!$A$5:$A$1000,0)),"Not in register")) -> A | G13: =IF($C13="","",IFERROR(INDEX(Asset_Register!$Q$5:$Q$1000,MATCH($C13,Asset_Register!$A$5:$A$1000,0)),"Not in register")) -> 90 | H13: IR survey | I13: Infrared | J13: Zone 4 shell temperature | K13: 240 | L13: °C | M13: 280 | N13: 350 | O13: Higher is worse | Q13: =IF($C13="","",IF($P13<>"",$P13,IF(AND(ISNUMBER($K13),ISNUMBER($M13),ISNUMBER($N13)),IF($O13="Lower is worse",IF($K13<=$N13,"Danger",IF($K13<=$M13,"Alert","OK")),IF($K13>=$N13,"Danger",IF($K13>=$M13,"Alert","OK"))),"Not set"))) -> OK | R13: =IF(OR($Q13="",$Q13="Not set"),"",MATCH($Q13,Lists!$F$2:$F$4,0)-1) -> 0 | U13: =IF(OR($Q13="",$Q13="OK",$Q13="Not set",NOT(ISNUMBER($G13))),"",ROUND($G13*IF($Q13="Danger",Lists!$M$15,Lists!$M$16),0)) | V13: =IF($U13="","",IF(OR($Q13="Danger",$U13>=Lists!$M$10),"P1",IF($U13>=Lists!$M$11,"P2","P3"))) | W13: =IF(OR($V13="",$B13=""),"",$B13+INDEX(Lists!$N$10:$N$12,MATCH($V13,Lists!$L$10:$L$12,0))) | Y13: No action | Z13: RCM Specialist | AC13: =IF(OR($U13="",$B13=""),"",IF($AA13<>"",$AA13-$B13,TODAY()-$B13)) | AD13: =IF($W13="","",IF($Y13="Closed",IF($AA13="","Closed",IF($AA13<=$W13,"Closed on time","Closed late")),IF(TODAY()>$W13,"Overdue","Within time")))
A14: =IF($C14="","","R"&TEXT(ROW()-4,"00000")) -> R00010 | B14: 45940 | C14: 100112 | D14: =IF($C14="","",IFERROR(INDEX(Asset_Register!$C$5:$C$1000,MATCH($C14,Asset_Register!$A$5:$A$1000,0)),"Not in register")) -> Cooling tower fan 1 | E14: =IF($C14="","",IFERROR(INDEX(Asset_Register!$D$5:$D$1000,MATCH($C14,Asset_Register!$A$5:$A$1000,0)),"Not in register")) -> Acid plant | F14: =IF($C14="","",IFERROR(INDEX(Asset_Register!$R$5:$R$1000,MATCH($C14,Asset_Register!$A$5:$A$1000,0)),"Not in register")) -> B | G14: =IF($C14="","",IFERROR(INDEX(Asset_Register!$Q$5:$Q$1000,MATCH($C14,Asset_Register!$A$5:$A$1000,0)),"Not in register")) -> 50 | H14: Oil analysis | I14: Lubrication / oil | J14: Copper (Cu) in gearbox oil | K14: 10 | L14: ppm | M14: 30 | N14: 60 | O14: Higher is worse | Q14: =IF($C14="","",IF($P14<>"",$P14,IF(AND(ISNUMBER($K14),ISNUMBER($M14),ISNUMBER($N14)),IF($O14="Lower is worse",IF($K14<=$N14,"Danger",IF($K14<=$M14,"Alert","OK")),IF($K14>=$N14,"Danger",IF($K14>=$M14,"Alert","OK"))),"Not set"))) -> OK | R14: =IF(OR($Q14="",$Q14="Not set"),"",MATCH($Q14,Lists!$F$2:$F$4,0)-1) -> 0 | U14: =IF(OR($Q14="",$Q14="OK",$Q14="Not set",NOT(ISNUMBER($G14))),"",ROUND($G14*IF($Q14="Danger",Lists!$M$15,Lists!$M$16),0)) | V14: =IF($U14="","",IF(OR($Q14="Danger",$U14>=Lists!$M$10),"P1",IF($U14>=Lists!$M$11,"P2","P3"))) | W14: =IF(OR($V14="",$B14=""),"",$B14+INDEX(Lists!$N$10:$N$12,MATCH($V14,Lists!$L$10:$L$12,0))) | Y14: No action | Z14: RCM Specialist | AC14: =IF(OR($U14="",$B14=""),"",IF($AA14<>"",$AA14-$B14,TODAY()-$B14)) | AD14: =IF($W14="","",IF($Y14="Closed",IF($AA14="","Closed",IF($AA14<=$W14,"Closed on time","Closed late")),IF(TODAY()>$W14,"Overdue","Within time")))
A15: =IF($C15="","","R"&TEXT(ROW()-4,"00000")) -> R00011 | B15: 45940 | C15: 100603 | D15: =IF($C15="","",IFERROR(INDEX(Asset_Register!$C$5:$C$1000,MATCH($C15,Asset_Register!$A$5:$A$1000,0)),"Not in register")) -> Front-end loader HV-03 | E15: =IF($C15="","",IFERROR(INDEX(Asset_Register!$D$5:$D$1000,MATCH($C15,Asset_Register!$A$5:$A$1000,0)),"Not in register")) -> Mobile fleet | F15: =IF($C15="","",IFERROR(INDEX(Asset_Register!$R$5:$R$1000,MATCH($C15,Asset_Register!$A$5:$A$1000,0)),"Not in register")) -> B | G15: =IF($C15="","",IFERROR(INDEX(Asset_Register!$Q$5:$Q$1000,MATCH($C15,Asset_Register!$A$5:$A$1000,0)),"Not in register")) -> 67 | H15: Oil analysis | I15: Lubrication / oil | J15: Engine oil silicon (Si) | K15: 8 | L15: ppm | M15: 20 | N15: 30 | O15: Higher is worse | Q15: =IF($C15="","",IF($P15<>"",$P15,IF(AND(ISNUMBER($K15),ISNUMBER($M15),ISNUMBER($N15)),IF($O15="Lower is worse",IF($K15<=$N15,"Danger",IF($K15<=$M15,"Alert","OK")),IF($K15>=$N15,"Danger",IF($K15>=$M15,"Alert","OK"))),"Not set"))) -> OK | R15: =IF(OR($Q15="",$Q15="Not set"),"",MATCH($Q15,Lists!$F$2:$F$4,0)-1) -> 0 | U15: =IF(OR($Q15="",$Q15="OK",$Q15="Not set",NOT(ISNUMBER($G15))),"",ROUND($G15*IF($Q15="Danger",Lists!$M$15,Lists!$M$16),0)) | V15: =IF($U15="","",IF(OR($Q15="Danger",$U15>=Lists!$M$10),"P1",IF($U15>=Lists!$M$11,"P2","P3"))) | W15: =IF(OR($V15="",$B15=""),"",$B15+INDEX(Lists!$N$10:$N$12,MATCH($V15,Lists!$L$10:$L$12,0))) | Y15: No action | Z15: RCM Specialist | AC15: =IF(OR($U15="",$B15=""),"",IF($AA15<>"",$AA15-$B15,TODAY()-$B15)) | AD15: =IF($W15="","",IF($Y15="Closed",IF($AA15="","Closed",IF($AA15<=$W15,"Closed on time","Closed late")),IF(TODAY()>$W15,"Overdue","Within time")))
A16: =IF($C16="","","R"&TEXT(ROW()-4,"00000")) -> R00012 | B16: 45940 | C16: 100601 | D16: =IF($C16="","",IFERROR(INDEX(Asset_Register!$C$5:$C$1000,MATCH($C16,Asset_Register!$A$5:$A$1000,0)),"Not in register")) -> Dozer HV-01 | E16: =IF($C16="","",IFERROR(INDEX(Asset_Register!$D$5:$D$1000,MATCH($C16,Asset_Register!$A$5:$A$1000,0)),"Not in register")) -> Mobile fleet | F16: =IF($C16="","",IFERROR(INDEX(Asset_Register!$R$5:$R$1000,MATCH($C16,Asset_Register!$A$5:$A$1000,0)),"Not in register")) -> B | G16: =IF($C16="","",IFERROR(INDEX(Asset_Register!$Q$5:$Q$1000,MATCH($C16,Asset_Register!$A$5:$A$1000,0)),"Not in register")) -> 69 | H16: Oil analysis | I16: Lubrication / oil | J16: Engine oil iron (Fe) | K16: 20 | L16: ppm | M16: 60 | N16: 100 | O16: Higher is worse | Q16: =IF($C16="","",IF($P16<>"",$P16,IF(AND(ISNUMBER($K16),ISNUMBER($M16),ISNUMBER($N16)),IF($O16="Lower is worse",IF($K16<=$N16,"Danger",IF($K16<=$M16,"Alert","OK")),IF($K16>=$N16,"Danger",IF($K16>=$M16,"Alert","OK"))),"Not set"))) -> OK | R16: =IF(OR($Q16="",$Q16="Not set"),"",MATCH($Q16,Lists!$F$2:$F$4,0)-1) -> 0 | U16: =IF(OR($Q16="",$Q16="OK",$Q16="Not set",NOT(ISNUMBER($G16))),"",ROUND($G16*IF($Q16="Danger",Lists!$M$15,Lists!$M$16),0)) | V16: =IF($U16="","",IF(OR($Q16="Danger",$U16>=Lists!$M$10),"P1",IF($U16>=Lists!$M$11,"P2","P3"))) | W16: =IF(OR($V16="",$B16=""),"",$B16+INDEX(Lists!$N$10:$N$12,MATCH($V16,Lists!$L$10:$L$12,0))) | Y16: No action | Z16: RCM Specialist | AC16: =IF(OR($U16="",$B16=""),"",IF($AA16<>"",$AA16-$B16,TODAY()-$B16)) | AD16: =IF($W16="","",IF($Y16="Closed",IF($AA16="","Closed",IF($AA16<=$W16,"Closed on time","Closed late")),IF(TODAY()>$W16,"Overdue","Within time")))
... A95: =IF($C95="","","R"&TEXT(ROW()-4,"00000")) -> R00091 | B95: 46032 | C95: 100602 | D95: =IF($C95="","",IFERROR(INDEX(Asset_Register!$C$5:$C$1000,MATCH($C95,Asset_Register!$A$5:$A$1000,0)),"Not in register")) -> Compactor HV-02 | E95: =IF($C95="","",IFERROR(INDEX(Asset_Register!$D$5:$D$1000,MATCH($C95,Asset_Register!$A$5:$A$1000,0)),"Not in register")) -> Mobile fleet | F95: =IF($C95="","",IFERROR(INDEX(Asset_Register!$R$5:$R$1000,MATCH($C95,Asset_Register!$A$5:$A$1000,0)),"Not in register")) -> B | G95: =IF($C95="","",IFERROR(INDEX(Asset_Register!$Q$5:$Q$1000,MATCH($C95,Asset_Register!$A$5:$A$1000,0)),"Not in register")) -> 58 | H95: Oil analysis | I95: Lubrication / oil | J95: Engine oil iron (Fe) | K95: 19 | L95: ppm | M95: 60 | N95: 100 | O95: Higher is worse | Q95: =IF($C95="","",IF($P95<>"",$P95,IF(AND(ISNUMBER($K95),ISNUMBER($M95),ISNUMBER($N95)),IF($O95="Lower is worse",IF($K95<=$N95,"Danger",IF($K95<=$M95,"Alert","OK")),IF($K95>=$N95,"Danger",IF($K95>=$M95,"Alert","OK"))),"Not set"))) -> OK | R95: =IF(OR($Q95="",$Q95="Not set"),"",MATCH($Q95,Lists!$F$2:$F$4,0)-1) -> 0 | U95: =IF(OR($Q95="",$Q95="OK",$Q95="Not set",NOT(ISNUMBER($G95))),"",ROUND($G95*IF($Q95="Danger",Lists!$M$15,Lists!$M$16),0)) | V95: =IF($U95="","",IF(OR($Q95="Danger",$U95>=Lists!$M$10),"P1",IF($U95>=Lists!$M$11,"P2","P3"))) | W95: =IF(OR($V95="",$B95=""),"",$B95+INDEX(Lists!$N$10:$N$12,MATCH($V95,Lists!$L$10:$L$12,0))) | Y95: No action | Z95: RCM Specialist | AC95: =IF(OR($U95="",$B95=""),"",IF($AA95<>"",$AA95-$B95,TODAY()-$B95)) | AD95: =IF($W95="","",IF($Y95="Closed",IF($AA95="","Closed",IF($AA95<=$W95,"Closed on time","Closed late")),IF(TODAY()>$W95,"Overdue","Within time")))
A96: =IF($C96="","","R"&TEXT(ROW()-4,"00000")) -> R00092 | B96: 46032 | C96: 100106 | D96: =IF($C96="","",IFERROR(INDEX(Asset_Register!$C$5:$C$1000,MATCH($C96,Asset_Register!$A$5:$A$1000,0)),"Not in register")) -> Interpass tower acid pump | E96: =IF($C96="","",IFERROR(INDEX(Asset_Register!$D$5:$D$1000,MATCH($C96,Asset_Register!$A$5:$A$1000,0)),"Not in register")) -> Acid plant | F96: =IF($C96="","",IFERROR(INDEX(Asset_Register!$R$5:$R$1000,MATCH($C96,Asset_Register!$A$5:$A$1000,0)),"Not in register")) -> A | G96: =IF($C96="","",IFERROR(INDEX(Asset_Register!$Q$5:$Q$1000,MATCH($C96,Asset_Register!$A$5:$A$1000,0)),"Not in register")) -> 76 | H96: Vibration & visual route | I96: Vibration | J96: Alignment condition | P96: Alert | Q96: =IF($C96="","",IF($P96<>"",$P96,IF(AND(ISNUMBER($K96),ISNUMBER($M96),ISNUMBER($N96)),IF($O96="Lower is worse",IF($K96<=$N96,"Danger",IF($K96<=$M96,"Alert","OK")),IF($K96>=$N96,"Danger",IF($K96>=$M96,"Alert","OK"))),"Not set"))) -> Alert | R96: =IF(OR($Q96="",$Q96="Not set"),"",MATCH($Q96,Lists!$F$2:$F$4,0)-1) -> 1 | S96: Misalignment signature (2x) at coupling | T96: Laser align pump and motor | U96: =IF(OR($Q96="",$Q96="OK",$Q96="Not set",NOT(ISNUMBER($G96))),"",ROUND($G96*IF($Q96="Danger",Lists!$M$15,Lists!$M$16),0)) -> 46 | V96: =IF($U96="","",IF(OR($Q96="Danger",$U96>=Lists!$M$10),"P1",IF($U96>=Lists!$M$11,"P2","P3"))) -> P2 | W96: =IF(OR($V96="",$B96=""),"",$B96+INDEX(Lists!$N$10:$N$12,MATCH($V96,Lists!$L$10:$L$12,0))) -> 46062 | X96: 242210 | Y96: Closed | Z96: RCM Specialist | AA96: 46052 | AB96: Mechanical Supervisor | AC96: =IF(OR($U96="",$B96=""),"",IF($AA96<>"",$AA96-$B96,TODAY()-$B96)) -> 20 | AD96: =IF($W96="","",IF($Y96="Closed",IF($AA96="","Closed",IF($AA96<=$W96,"Closed on time","Closed late")),IF(TODAY()>$W96,"Overdue","Within time"))) -> Closed on time
A97: =IF($C97="","","R"&TEXT(ROW()-4,"00000")) -> R00093 | B97: 46034 | C97: 100103 | D97: =IF($C97="","",IFERROR(INDEX(Asset_Register!$C$5:$C$1000,MATCH($C97,Asset_Register!$A$5:$A$1000,0)),"Not in register")) -> Main air blower | E97: =IF($C97="","",IFERROR(INDEX(Asset_Register!$D$5:$D$1000,MATCH($C97,Asset_Register!$A$5:$A$1000,0)),"Not in register")) -> Acid plant | F97: =IF($C97="","",IFERROR(INDEX(Asset_Register!$R$5:$R$1000,MATCH($C97,Asset_Register!$A$5:$A$1000,0)),"Not in register")) -> A | G97: =IF($C97="","",IFERROR(INDEX(Asset_Register!$Q$5:$Q$1000,MATCH($C97,Asset_Register!$A$5:$A$1000,0)),"Not in register")) -> 87 | H97: Vibration & visual route | I97: Vibration | J97: Overall velocity (max point) | K97: 2.3 | L97: mm/s | M97: 4.5 | N97: 7.1 | O97: Higher is worse | Q97: =IF($C97="","",IF($P97<>"",$P97,IF(AND(ISNUMBER($K97),ISNUMBER($M97),ISNUMBER($N97)),IF($O97="Lower is worse",IF($K97<=$N97,"Danger",IF($K97<=$M97,"Alert","OK")),IF($K97>=$N97,"Danger",IF($K97>=$M97,"Alert","OK"))),"Not set"))) -> OK | R97: =IF(OR($Q97="",$Q97="Not set"),"",MATCH($Q97,Lists!$F$2:$F$4,0)-1) -> 0 | U97: =IF(OR($Q97="",$Q97="OK",$Q97="Not set",NOT(ISNUMBER($G97))),"",ROUND($G97*IF($Q97="Danger",Lists!$M$15,Lists!$M$16),0)) | V97: =IF($U97="","",IF(OR($Q97="Danger",$U97>=Lists!$M$10),"P1",IF($U97>=Lists!$M$11,"P2","P3"))) | W97: =IF(OR($V97="",$B97=""),"",$B97+INDEX(Lists!$N$10:$N$12,MATCH($V97,Lists!$L$10:$L$12,0))) | Y97: No action | Z97: RCM Specialist | AC97: =IF(OR($U97="",$B97=""),"",IF($AA97<>"",$AA97-$B97,TODAY()-$B97)) | AD97: =IF($W97="","",IF($Y97="Closed",IF($AA97="","Closed",IF($AA97<=$W97,"Closed on time","Closed late")),IF(TODAY()>$W97,"Overdue","Within time")))
A98: =IF($C98="","","R"&TEXT(ROW()-4,"00000")) -> R00094 | B98: 46037 | C98: 100107 | D98: =IF($C98="","",IFERROR(INDEX(Asset_Register!$C$5:$C$1000,MATCH($C98,Asset_Register!$A$5:$A$1000,0)),"Not in register")) -> Final tower acid pump | E98: =IF($C98="","",IFERROR(INDEX(Asset_Register!$D$5:$D$1000,MATCH($C98,Asset_Register!$A$5:$A$1000,0)),"Not in register")) -> Acid plant | F98: =IF($C98="","",IFERROR(INDEX(Asset_Register!$R$5:$R$1000,MATCH($C98,Asset_Register!$A$5:$A$1000,0)),"Not in register")) -> B | G98: =IF($C98="","",IFERROR(INDEX(Asset_Register!$Q$5:$Q$1000,MATCH($C98,Asset_Register!$A$5:$A$1000,0)),"Not in register")) -> 66 | H98: Vibration & visual route | I98: Vibration | J98: Overall velocity (max point) | K98: 3.4 | L98: mm/s | M98: 4.5 | N98: 7.1 | O98: Higher is worse | Q98: =IF($C98="","",IF($P98<>"",$P98,IF(AND(ISNUMBER($K98),ISNUMBER($M98),ISNUMBER($N98)),IF($O98="Lower is worse",IF($K98<=$N98,"Danger",IF($K98<=$M98,"Alert","OK")),IF($K98>=$N98,"Danger",IF($K98>=$M98,"Alert","OK"))),"Not set"))) -> OK | R98: =IF(OR($Q98="",$Q98="Not set"),"",MATCH($Q98,Lists!$F$2:$F$4,0)-1) -> 0 | U98: =IF(OR($Q98="",$Q98="OK",$Q98="Not set",NOT(ISNUMBER($G98))),"",ROUND($G98*IF($Q98="Danger",Lists!$M$15,Lists!$M$16),0)) | V98: =IF($U98="","",IF(OR($Q98="Danger",$U98>=Lists!$M$10),"P1",IF($U98>=Lists!$M$11,"P2","P3"))) | W98: =IF(OR($V98="",$B98=""),"",$B98+INDEX(Lists!$N$10:$N$12,MATCH($V98,Lists!$L$10:$L$12,0))) | Y98: No action | Z98: RCM Specialist | AC98: =IF(OR($U98="",$B98=""),"",IF($AA98<>"",$AA98-$B98,TODAY()-$B98)) | AD98: =IF($W98="","",IF($Y98="Closed",IF($AA98="","Closed",IF($AA98<=$W98,"Closed on time","Closed late")),IF(TODAY()>$W98,"Overdue","Within time")))
A99: =IF($C99="","","R"&TEXT(ROW()-4,"00000")) -> R00095 | B99: 46040 | C99: 100114 | D99: =IF($C99="","",IFERROR(INDEX(Asset_Register!$C$5:$C$1000,MATCH($C99,Asset_Register!$A$5:$A$1000,0)),"Not in register")) -> Acid transfer line | E99: =IF($C99="","",IFERROR(INDEX(Asset_Register!$D$5:$D$1000,MATCH($C99,Asset_Register!$A$5:$A$1000,0)),"Not in register")) -> Acid plant | F99: =IF($C99="","",IFERROR(INDEX(Asset_Register!$R$5:$R$1000,MATCH($C99,Asset_Register!$A$5:$A$1000,0)),"Not in register")) -> A | G99: =IF($C99="","",IFERROR(INDEX(Asset_Register!$Q$5:$Q$1000,MATCH($C99,Asset_Register!$A$5:$A$1000,0)),"Not in register")) -> 81 | H99: Ultrasonic report | I99: Ultrasonic thickness | J99: Elbow E-07 wall | K99: 5.4 | L99: mm | M99: 4.5 | N99: 4 | O99: Lower is worse | Q99: =IF($C99="","",IF($P99<>"",$P99,IF(AND(ISNUMBER($K99),ISNUMBER($M99),ISNUMBER($N99)),IF($O99="Lower is worse",IF($K99<=$N99,"Danger",IF($K99<=$M99,"Alert","OK")),IF($K99>=$N99,"Danger",IF($K99>=$M99,"Alert","OK"))),"Not set"))) -> OK | R99: =IF(OR($Q99="",$Q99="Not set"),"",MATCH($Q99,Lists!$F$2:$F$4,0)-1) -> 0 | U99: =IF(OR($Q99="",$Q99="OK",$Q99="Not set",NOT(ISNUMBER($G99))),"",ROUND($G99*IF($Q99="Danger",Lists!$M$15,Lists!$M$16),0)) | V99: =IF($U99="","",IF(OR($Q99="Danger",$U99>=Lists!$M$10),"P1",IF($U99>=Lists!$M$11,"P2","P3"))) | W99: =IF(OR($V99="",$B99=""),"",$B99+INDEX(Lists!$N$10:$N$12,MATCH($V99,Lists!$L$10:$L$12,0))) | Y99: No action | Z99: UT contractor | AC99: =IF(OR($U99="",$B99=""),"",IF($AA99<>"",$AA99-$B99,TODAY()-$B99)) | AD99: =IF($W99="","",IF($Y99="Closed",IF($AA99="","Closed",IF($AA99<=$W99,"Closed on time","Closed late")),IF(TODAY()>$W99,"Overdue","Within time")))
A100: =IF($C100="","","R"&TEXT(ROW()-4,"00000")) -> R00096 | B100: 46042 | C100: 100104 | D100: =IF($C100="","",IFERROR(INDEX(Asset_Register!$C$5:$C$1000,MATCH($C100,Asset_Register!$A$5:$A$1000,0)),"Not in register")) -> SO2 converter | E100: =IF($C100="","",IFERROR(INDEX(Asset_Register!$D$5:$D$1000,MATCH($C100,Asset_Register!$A$5:$A$1000,0)),"Not in register")) -> Acid plant | F100: =IF($C100="","",IFERROR(INDEX(Asset_Register!$R$5:$R$1000,MATCH($C100,Asset_Register!$A$5:$A$1000,0)),"Not in register")) -> A | G100: =IF($C100="","",IFERROR(INDEX(Asset_Register!$Q$5:$Q$1000,MATCH($C100,Asset_Register!$A$5:$A$1000,0)),"Not in register")) -> 86 | H100: IR survey | I100: Infrared | J100: Bed 3 outlet flange dT above baseline | K100: 7 | L100: °C | M100: 30 | N100: 60 | O100: Higher is worse | Q100: =IF($C100="","",IF($P100<>"",$P100,IF(AND(ISNUMBER($K100),ISNUMBER($M100),ISNUMBER($N100)),IF($O100="Lower is worse",IF($K100<=$N100,"Danger",IF($K100<=$M100,"Alert","OK")),IF($K100>=$N100,"Danger",IF($K100>=$M100,"Alert","OK"))),"Not set"))) -> OK | R100: =IF(OR($Q100="",$Q100="Not set"),"",MATCH($Q100,Lists!$F$2:$F$4,0)-1) -> 0 | U100: =IF(OR($Q100="",$Q100="OK",$Q100="Not set",NOT(ISNUMBER($G100))),"",ROUND($G100*IF($Q100="Danger",Lists!$M$15,Lists!$M$16),0)) | V100: =IF($U100="","",IF(OR($Q100="Danger",$U100>=Lists!$M$10),"P1",IF($U100>=Lists!$M$11,"P2","P3"))) | W100: =IF(OR($V100="",$B100=""),"",$B100+INDEX(Lists!$N$10:$N$12,MATCH($V100,Lists!$L$10:$L$12,0))) | Y100: No action | Z100: RCM Specialist | AC100: =IF(OR($U100="",$B100=""),"",IF($AA100<>"",$AA100-$B100,TODAY()-$B100)) | AD100: =IF($W100="","",IF($Y100="Closed",IF($AA100="","Closed",IF($AA100<=$W100,"Closed on time","Closed late")),IF(TODAY()>$W100,"Overdue","Within time")))
A101: =IF($C101="","","R"&TEXT(ROW()-4,"00000")) -> R00097 | B101: 46044 | C101: 100105 | D101: =IF($C101="","",IFERROR(INDEX(Asset_Register!$C$5:$C$1000,MATCH($C101,Asset_Register!$A$5:$A$1000,0)),"Not in register")) -> Drying tower acid pump | E101: =IF($C101="","",IFERROR(INDEX(Asset_Register!$D$5:$D$1000,MATCH($C101,Asset_Register!$A$5:$A$1000,0)),"Not in register")) -> Acid plant | F101: =IF($C101="","",IFERROR(INDEX(Asset_Register!$R$5:$R$1000,MATCH($C101,Asset_Register!$A$5:$A$1000,0)),"Not in register")) -> A | G101: =IF($C101="","",IFERROR(INDEX(Asset_Register!$Q$5:$Q$1000,MATCH($C101,Asset_Register!$A$5:$A$1000,0)),"Not in register")) -> 74 | H101: Vibration & visual route | I101: Vibration | J101: Overall velocity (max point) | K101: 3.3 | L101: mm/s | M101: 4.5 | N101: 7.1 | O101: Higher is worse | Q101: =IF($C101="","",IF($P101<>"",$P101,IF(AND(ISNUMBER($K101),ISNUMBER($M101),ISNUMBER($N101)),IF($O101="Lower is worse",IF($K101<=$N101,"Danger",IF($K101<=$M101,"Alert","OK")),IF($K101>=$N101,"Danger",IF($K101>=$M101,"Alert","OK"))),"Not set"))) -> OK | R101: =IF(OR($Q101="",$Q101="Not set"),"",MATCH($Q101,Lists!$F$2:$F$4,0)-1) -> 0 | U101: =IF(OR($Q101="",$Q101="OK",$Q101="Not set",NOT(ISNUMBER($G101))),"",ROUND($G101*IF($Q101="Danger",Lists!$M$15,Lists!$M$16),0)) | V101: =IF($U101="","",IF(OR($Q101="Danger",$U101>=Lists!$M$10),"P1",IF($U101>=Lists!$M$11,"P2","P3"))) | W101: =IF(OR($V101="",$B101=""),"",$B101+INDEX(Lists!$N$10:$N$12,MATCH($V101,Lists!$L$10:$L$12,0))) | Y101: No action | Z101: RCM Specialist | AC101: =IF(OR($U101="",$B101=""),"",IF($AA101<>"",$AA101-$B101,TODAY()-$B101)) | AD101: =IF($W101="","",IF($Y101="Closed",IF($AA101="","Closed",IF($AA101<=$W101,"Closed on time","Closed late")),IF(TODAY()>$W101,"Overdue","Within time")))
A102: =IF($C102="","","R"&TEXT(ROW()-4,"00000")) -> R00098 | B102: 46044 | C102: 100106 | D102: =IF($C102="","",IFERROR(INDEX(Asset_Register!$C$5:$C$1000,MATCH($C102,Asset_Register!$A$5:$A$1000,0)),"Not in register")) -> Interpass tower acid pump | E102: =IF($C102="","",IFERROR(INDEX(Asset_Register!$D$5:$D$1000,MATCH($C102,Asset_Register!$A$5:$A$1000,0)),"Not in register")) -> Acid plant | F102: =IF($C102="","",IFERROR(INDEX(Asset_Register!$R$5:$R$1000,MATCH($C102,Asset_Register!$A$5:$A$1000,0)),"Not in register")) -> A | G102: =IF($C102="","",IFERROR(INDEX(Asset_Register!$Q$5:$Q$1000,MATCH($C102,Asset_Register!$A$5:$A$1000,0)),"Not in register")) -> 76 | H102: Vibration & visual route | I102: Vibration | J102: Overall velocity (max point) | K102: 2.2 | L102: mm/s | M102: 4.5 | N102: 7.1 | O102: Higher is worse | Q102: =IF($C102="","",IF($P102<>"",$P102,IF(AND(ISNUMBER($K102),ISNUMBER($M102),ISNUMBER($N102)),IF($O102="Lower is worse",IF($K102<=$N102,"Danger",IF($K102<=$M102,"Alert","OK")),IF($K102>=$N102,"Danger",IF($K102>=$M102,"Alert","OK"))),"Not set"))) -> OK | R102: =IF(OR($Q102="",$Q102="Not set"),"",MATCH($Q102,Lists!$F$2:$F$4,0)-1) -> 0 | U102: =IF(OR($Q102="",$Q102="OK",$Q102="Not set",NOT(ISNUMBER($G102))),"",ROUND($G102*IF($Q102="Danger",Lists!$M$15,Lists!$M$16),0)) | V102: =IF($U102="","",IF(OR($Q102="Danger",$U102>=Lists!$M$10),"P1",IF($U102>=Lists!$M$11,"P2","P3"))) | W102: =IF(OR($V102="",$B102=""),"",$B102+INDEX(Lists!$N$10:$N$12,MATCH($V102,Lists!$L$10:$L$12,0))) | Y102: No action | Z102: RCM Specialist | AC102: =IF(OR($U102="",$B102=""),"",IF($AA102<>"",$AA102-$B102,TODAY()-$B102)) | AD102: =IF($W102="","",IF($Y102="Closed",IF($AA102="","Closed",IF($AA102<=$W102,"Closed on time","Closed late")),IF(TODAY()>$W102,"Overdue","Within time")))
A103: =IF($C103="","","R"&TEXT(ROW()-4,"00000")) -> R00099 | B103: 46044 | C103: 100105 | D103: =IF($C103="","",IFERROR(INDEX(Asset_Register!$C$5:$C$1000,MATCH($C103,Asset_Register!$A$5:$A$1000,0)),"Not in register")) -> Drying tower acid pump | E103: =IF($C103="","",IFERROR(INDEX(Asset_Register!$D$5:$D$1000,MATCH($C103,Asset_Register!$A$5:$A$1000,0)),"Not in register")) -> Acid plant | F103: =IF($C103="","",IFERROR(INDEX(Asset_Register!$R$5:$R$1000,MATCH($C103,Asset_Register!$A$5:$A$1000,0)),"Not in register")) -> A | G103: =IF($C103="","",IFERROR(INDEX(Asset_Register!$Q$5:$Q$1000,MATCH($C103,Asset_Register!$A$5:$A$1000,0)),"Not in register")) -> 74 | H103: Oil analysis | I103: Lubrication / oil | J103: Iron (Fe) | K103: 18 | L103: ppm | M103: 50 | N103: 100 | O103: Higher is worse | Q103: =IF($C103="","",IF($P103<>"",$P103,IF(AND(ISNUMBER($K103),ISNUMBER($M103),ISNUMBER($N103)),IF($O103="Lower is worse",IF($K103<=$N103,"Danger",IF($K103<=$M103,"Alert","OK")),IF($K103>=$N103,"Danger",IF($K103>=$M103,"Alert","OK"))),"Not set"))) -> OK | R103: =IF(OR($Q103="",$Q103="Not set"),"",MATCH($Q103,Lists!$F$2:$F$4,0)-1) -> 0 | U103: =IF(OR($Q103="",$Q103="OK",$Q103="Not set",NOT(ISNUMBER($G103))),"",ROUND($G103*IF($Q103="Danger",Lists!$M$15,Lists!$M$16),0)) | V103: =IF($U103="","",IF(OR($Q103="Danger",$U103>=Lists!$M$10),"P1",IF($U103>=Lists!$M$11,"P2","P3"))) | W103: =IF(OR($V103="",$B103=""),"",$B103+INDEX(Lists!$N$10:$N$12,MATCH($V103,Lists!$L$10:$L$12,0))) | Y103: No action | Z103: RCM Specialist | AC103: =IF(OR($U103="",$B103=""),"",IF($AA103<>"",$AA103-$B103,TODAY()-$B103)) | AD103: =IF($W103="","",IF($Y103="Closed",IF($AA103="","Closed",IF($AA103<=$W103,"Closed on time","Closed late")),IF(TODAY()>$W103,"Overdue","Within time")))
A104: =IF($C104="","","R"&TEXT(ROW()-4,"00000")) -> R00100 | B104: 46046 | C104: 100301 | D104: =IF($C104="","",IFERROR(INDEX(Asset_Register!$C$5:$C$1000,MATCH($C104,Asset_Register!$A$5:$A$1000,0)),"Not in register")) -> Transformer TX-01 | E104: =IF($C104="","",IFERROR(INDEX(Asset_Register!$D$5:$D$1000,MATCH($C104,Asset_Register!$A$5:$A$1000,0)),"Not in register")) -> Substation | F104: =IF($C104="","",IFERROR(INDEX(Asset_Register!$R$5:$R$1000,MATCH($C104,Asset_Register!$A$5:$A$1000,0)),"Not in register")) -> A | G104: =IF($C104="","",IFERROR(INDEX(Asset_Register!$Q$5:$Q$1000,MATCH($C104,Asset_Register!$A$5:$A$1000,0)),"Not in register")) -> 86 | H104: Substation inspection | I104: Infrared | J104: LV bushing connection dT | K104: 3 | L104: °C | M104: 4 | N104: 15 | O104: Higher is worse | Q104: =IF($C104="","",IF($P104<>"",$P104,IF(AND(ISNUMBER($K104),ISNUMBER($M104),ISNUMBER($N104)),IF($O104="Lower is worse",IF($K104<=$N104,"Danger",IF($K104<=$M104,"Alert","OK")),IF($K104>=$N104,"Danger",IF($K104>=$M104,"Alert","OK"))),"Not set"))) -> OK | R104: =IF(OR($Q104="",$Q104="Not set"),"",MATCH($Q104,Lists!$F$2:$F$4,0)-1) -> 0 | U104: =IF(OR($Q104="",$Q104="OK",$Q104="Not set",NOT(ISNUMBER($G104))),"",ROUND($G104*IF($Q104="Danger",Lists!$M$15,Lists!$M$16),0)) | V104: =IF($U104="","",IF(OR($Q104="Danger",$U104>=Lists!$M$10),"P1",IF($U104>=Lists!$M$11,"P2","P3"))) | W104: =IF(OR($V104="",$B104=""),"",$B104+INDEX(Lists!$N$10:$N$12,MATCH($V104,Lists!$L$10:$L$12,0))) | Y104: No action | Z104: Electrician | AC104: =IF(OR($U104="",$B104=""),"",IF($AA104<>"",$AA104-$B104,TODAY()-$B104)) | AD104: =IF($W104="","",IF($Y104="Closed",IF($AA104="","Closed",IF($AA104<=$W104,"Closed on time","Closed late")),IF(TODAY()>$W104,"Overdue","Within time")))
A105: =IF($C105="","","R"&TEXT(ROW()-4,"00000")) -> R00101 | B105: 46046 | C105: 100302 | D105: =IF($C105="","",IFERROR(INDEX(Asset_Register!$C$5:$C$1000,MATCH($C105,Asset_Register!$A$5:$A$1000,0)),"Not in register")) -> Acid plant MCC | E105: =IF($C105="","",IFERROR(INDEX(Asset_Register!$D$5:$D$1000,MATCH($C105,Asset_Register!$A$5:$A$1000,0)),"Not in register")) -> Substation | F105: =IF($C105="","",IFERROR(INDEX(Asset_Register!$R$5:$R$1000,MATCH($C105,Asset_Register!$A$5:$A$1000,0)),"Not in register")) -> A | G105: =IF($C105="","",IFERROR(INDEX(Asset_Register!$Q$5:$Q$1000,MATCH($C105,Asset_Register!$A$5:$A$1000,0)),"Not in register")) -> 82 | H105: IR survey | I105: Infrared | J105: Hottest termination dT | K105: 2 | L105: °C | M105: 4 | N105: 15 | O105: Higher is worse | Q105: =IF($C105="","",IF($P105<>"",$P105,IF(AND(ISNUMBER($K105),ISNUMBER($M105),ISNUMBER($N105)),IF($O105="Lower is worse",IF($K105<=$N105,"Danger",IF($K105<=$M105,"Alert","OK")),IF($K105>=$N105,"Danger",IF($K105>=$M105,"Alert","OK"))),"Not set"))) -> OK | R105: =IF(OR($Q105="",$Q105="Not set"),"",MATCH($Q105,Lists!$F$2:$F$4,0)-1) -> 0 | U105: =IF(OR($Q105="",$Q105="OK",$Q105="Not set",NOT(ISNUMBER($G105))),"",ROUND($G105*IF($Q105="Danger",Lists!$M$15,Lists!$M$16),0)) | V105: =IF($U105="","",IF(OR($Q105="Danger",$U105>=Lists!$M$10),"P1",IF($U105>=Lists!$M$11,"P2","P3"))) | W105: =IF(OR($V105="",$B105=""),"",$B105+INDEX(Lists!$N$10:$N$12,MATCH($V105,Lists!$L$10:$L$12,0))) | Y105: No action | Z105: RCM Specialist | AC105: =IF(OR($U105="",$B105=""),"",IF($AA105<>"",$AA105-$B105,TODAY()-$B105)) | AD105: =IF($W105="","",IF($Y105="Closed",IF($AA105="","Closed",IF($AA105<=$W105,"Closed on time","Closed late")),IF(TODAY()>$W105,"Overdue","Within time")))
A106: =IF($C106="","","R"&TEXT(ROW()-4,"00000")) -> R00102 | B106: 46050 | C106: 100401 | D106: =IF($C106="","",IFERROR(INDEX(Asset_Register!$C$5:$C$1000,MATCH($C106,Asset_Register!$A$5:$A$1000,0)),"Not in register")) -> Diesel generator Gen 1 | E106: =IF($C106="","",IFERROR(INDEX(Asset_Register!$D$5:$D$1000,MATCH($C106,Asset_Register!$A$5:$A$1000,0)),"Not in register")) -> Power plant | F106: =IF($C106="","",IFERROR(INDEX(Asset_Register!$R$5:$R$1000,MATCH($C106,Asset_Register!$A$5:$A$1000,0)),"Not in register")) -> A | G106: =IF($C106="","",IFERROR(INDEX(Asset_Register!$Q$5:$Q$1000,MATCH($C106,Asset_Register!$A$5:$A$1000,0)),"Not in register")) -> 83 | H106: DG checklist | I106: DG checks | J106: Turbo outlet exhaust temperature | K106: 478 | L106: °C | M106: 520 | N106: 580 | O106: Higher is worse | Q106: =IF($C106="","",IF($P106<>"",$P106,IF(AND(ISNUMBER($K106),ISNUMBER($M106),ISNUMBER($N106)),IF($O106="Lower is worse",IF($K106<=$N106,"Danger",IF($K106<=$M106,"Alert","OK")),IF($K106>=$N106,"Danger",IF($K106>=$M106,"Alert","OK"))),"Not set"))) -> OK | R106: =IF(OR($Q106="",$Q106="Not set"),"",MATCH($Q106,Lists!$F$2:$F$4,0)-1) -> 0 | U106: =IF(OR($Q106="",$Q106="OK",$Q106="Not set",NOT(ISNUMBER($G106))),"",ROUND($G106*IF($Q106="Danger",Lists!$M$15,Lists!$M$16),0)) | V106: =IF($U106="","",IF(OR($Q106="Danger",$U106>=Lists!$M$10),"P1",IF($U106>=Lists!$M$11,"P2","P3"))) | W106: =IF(OR($V106="",$B106=""),"",$B106+INDEX(Lists!$N$10:$N$12,MATCH($V106,Lists!$L$10:$L$12,0))) | Y106: No action | Z106: DG operator | AC106: =IF(OR($U106="",$B106=""),"",IF($AA106<>"",$AA106-$B106,TODAY()-$B106)) | AD106: =IF($W106="","",IF($Y106="Closed",IF($AA106="","Closed",IF($AA106<=$W106,"Closed on time","Closed late")),IF(TODAY()>$W106,"Overdue","Within time")))
A107: =IF($C107="","","R"&TEXT(ROW()-4,"00000")) -> R00103 | B107: 46050 | C107: 100402 | D107: =IF($C107="","",IFERROR(INDEX(Asset_Register!$C$5:$C$1000,MATCH($C107,Asset_Register!$A$5:$A$1000,0)),"Not in register")) -> Diesel generator Gen 2 | E107: =IF($C107="","",IFERROR(INDEX(Asset_Register!$D$5:$D$1000,MATCH($C107,Asset_Register!$A$5:$A$1000,0)),"Not in register")) -> Power plant | F107: =IF($C107="","",IFERROR(INDEX(Asset_Register!$R$5:$R$1000,MATCH($C107,Asset_Register!$A$5:$A$1000,0)),"Not in register")) -> A | G107: =IF($C107="","",IFERROR(INDEX(Asset_Register!$Q$5:$Q$1000,MATCH($C107,Asset_Register!$A$5:$A$1000,0)),"Not in register")) -> 79 | H107: DG checklist | I107: DG checks | J107: Exhaust temperature spread between cylinders | K107: 25 | L107: °C | M107: 50 | N107: 80 | O107: Higher is worse | Q107: =IF($C107="","",IF($P107<>"",$P107,IF(AND(ISNUMBER($K107),ISNUMBER($M107),ISNUMBER($N107)),IF($O107="Lower is worse",IF($K107<=$N107,"Danger",IF($K107<=$M107,"Alert","OK")),IF($K107>=$N107,"Danger",IF($K107>=$M107,"Alert","OK"))),"Not set"))) -> OK | R107: =IF(OR($Q107="",$Q107="Not set"),"",MATCH($Q107,Lists!$F$2:$F$4,0)-1) -> 0 | U107: =IF(OR($Q107="",$Q107="OK",$Q107="Not set",NOT(ISNUMBER($G107))),"",ROUND($G107*IF($Q107="Danger",Lists!$M$15,Lists!$M$16),0)) | V107: =IF($U107="","",IF(OR($Q107="Danger",$U107>=Lists!$M$10),"P1",IF($U107>=Lists!$M$11,"P2","P3"))) | W107: =IF(OR($V107="",$B107=""),"",$B107+INDEX(Lists!$N$10:$N$12,MATCH($V107,Lists!$L$10:$L$12,0))) | Y107: No action | Z107: DG operator | AC107: =IF(OR($U107="",$B107=""),"",IF($AA107<>"",$AA107-$B107,TODAY()-$B107)) | AD107: =IF($W107="","",IF($Y107="Closed",IF($AA107="","Closed",IF($AA107<=$W107,"Closed on time","Closed late")),IF(TODAY()>$W107,"Overdue","Within time")))
A108: =IF($C108="","","R"&TEXT(ROW()-4,"00000")) -> R00104 | B108: 46050 | C108: 100403 | D108: =IF($C108="","",IFERROR(INDEX(Asset_Register!$C$5:$C$1000,MATCH($C108,Asset_Register!$A$5:$A$1000,0)),"Not in register")) -> Diesel generator Gen 3 | E108: =IF($C108="","",IFERROR(INDEX(Asset_Register!$D$5:$D$1000,MATCH($C108,Asset_Register!$A$5:$A$1000,0)),"Not in register")) -> Power plant | F108: =IF($C108="","",IFERROR(INDEX(Asset_Register!$R$5:$R$1000,MATCH($C108,Asset_Register!$A$5:$A$1000,0)),"Not in register")) -> A | G108: =IF($C108="","",IFERROR(INDEX(Asset_Register!$Q$5:$Q$1000,MATCH($C108,Asset_Register!$A$5:$A$1000,0)),"Not in register")) -> 79 | H108: DG checklist | I108: DG checks | J108: Turbo outlet exhaust temperature | K108: 460 | L108: °C | M108: 520 | N108: 580 | O108: Higher is worse | Q108: =IF($C108="","",IF($P108<>"",$P108,IF(AND(ISNUMBER($K108),ISNUMBER($M108),ISNUMBER($N108)),IF($O108="Lower is worse",IF($K108<=$N108,"Danger",IF($K108<=$M108,"Alert","OK")),IF($K108>=$N108,"Danger",IF($K108>=$M108,"Alert","OK"))),"Not set"))) -> OK | R108: =IF(OR($Q108="",$Q108="Not set"),"",MATCH($Q108,Lists!$F$2:$F$4,0)-1) -> 0 | U108: =IF(OR($Q108="",$Q108="OK",$Q108="Not set",NOT(ISNUMBER($G108))),"",ROUND($G108*IF($Q108="Danger",Lists!$M$15,Lists!$M$16),0)) | V108: =IF($U108="","",IF(OR($Q108="Danger",$U108>=Lists!$M$10),"P1",IF($U108>=Lists!$M$11,"P2","P3"))) | W108: =IF(OR($V108="",$B108=""),"",$B108+INDEX(Lists!$N$10:$N$12,MATCH($V108,Lists!$L$10:$L$12,0))) | Y108: No action | Z108: DG operator | AC108: =IF(OR($U108="",$B108=""),"",IF($AA108<>"",$AA108-$B108,TODAY()-$B108)) | AD108: =IF($W108="","",IF($Y108="Closed",IF($AA108="","Closed",IF($AA108<=$W108,"Closed on time","Closed late")),IF(TODAY()>$W108,"Overdue","Within time")))
... A114: =IF($C114="","","R"&TEXT(ROW()-4,"00000")) -> R00110 | B114: 46055 | C114: 100111 | D114: =IF($C114="","",IFERROR(INDEX(Asset_Register!$C$5:$C$1000,MATCH($C114,Asset_Register!$A$5:$A$1000,0)),"Not in register")) -> Sulphur melter agitator | E114: =IF($C114="","",IFERROR(INDEX(Asset_Register!$D$5:$D$1000,MATCH($C114,Asset_Register!$A$5:$A$1000,0)),"Not in register")) -> Acid plant | F114: =IF($C114="","",IFERROR(INDEX(Asset_Register!$R$5:$R$1000,MATCH($C114,Asset_Register!$A$5:$A$1000,0)),"Not in register")) -> C | G114: =IF($C114="","",IFERROR(INDEX(Asset_Register!$Q$5:$Q$1000,MATCH($C114,Asset_Register!$A$5:$A$1000,0)),"Not in register")) -> 43 | H114: Vibration & visual route | I114: Vibration | J114: Overall velocity (max point) | K114: 1.5 | L114: mm/s | M114: 4.5 | N114: 7.1 | O114: Higher is worse | Q114: =IF($C114="","",IF($P114<>"",$P114,IF(AND(ISNUMBER($K114),ISNUMBER($M114),ISNUMBER($N114)),IF($O114="Lower is worse",IF($K114<=$N114,"Danger",IF($K114<=$M114,"Alert","OK")),IF($K114>=$N114,"Danger",IF($K114>=$M114,"Alert","OK"))),"Not set"))) -> OK | R114: =IF(OR($Q114="",$Q114="Not set"),"",MATCH($Q114,Lists!$F$2:$F$4,0)-1) -> 0 | U114: =IF(OR($Q114="",$Q114="OK",$Q114="Not set",NOT(ISNUMBER($G114))),"",ROUND($G114*IF($Q114="Danger",Lists!$M$15,Lists!$M$16),0)) | V114: =IF($U114="","",IF(OR($Q114="Danger",$U114>=Lists!$M$10),"P1",IF($U114>=Lists!$M$11,"P2","P3"))) | W114: =IF(OR($V114="",$B114=""),"",$B114+INDEX(Lists!$N$10:$N$12,MATCH($V114,Lists!$L$10:$L$12,0))) | Y114: No action | Z114: RCM Specialist | AC114: =IF(OR($U114="",$B114=""),"",IF($AA114<>"",$AA114-$B114,TODAY()-$B114)) | AD114: =IF($W114="","",IF($Y114="Closed",IF($AA114="","Closed",IF($AA114<=$W114,"Closed on time","Closed late")),IF(TODAY()>$W114,"Overdue","Within time")))
A115: =IF($C115="","","R"&TEXT(ROW()-4,"00000")) -> R00111 | B115: 46056 | C115: 100103 | D115: =IF($C115="","",IFERROR(INDEX(Asset_Register!$C$5:$C$1000,MATCH($C115,Asset_Register!$A$5:$A$1000,0)),"Not in register")) -> Main air blower | E115: =IF($C115="","",IFERROR(INDEX(Asset_Register!$D$5:$D$1000,MATCH($C115,Asset_Register!$A$5:$A$1000,0)),"Not in register")) -> Acid plant | F115: =IF($C115="","",IFERROR(INDEX(Asset_Register!$R$5:$R$1000,MATCH($C115,Asset_Register!$A$5:$A$1000,0)),"Not in register")) -> A | G115: =IF($C115="","",IFERROR(INDEX(Asset_Register!$Q$5:$Q$1000,MATCH($C115,Asset_Register!$A$5:$A$1000,0)),"Not in register")) -> 87 | H115: Oil analysis | I115: Lubrication / oil | J115: Oil contamination | P115: Alert | Q115: =IF($C115="","",IF($P115<>"",$P115,IF(AND(ISNUMBER($K115),ISNUMBER($M115),ISNUMBER($N115)),IF($O115="Lower is worse",IF($K115<=$N115,"Danger",IF($K115<=$M115,"Alert","OK")),IF($K115>=$N115,"Danger",IF($K115>=$M115,"Alert","OK"))),"Not set"))) -> Alert | R115: =IF(OR($Q115="",$Q115="Not set"),"",MATCH($Q115,Lists!$F$2:$F$4,0)-1) -> 1 | S115: Particle count ISO 21/19/16, above target | T115: Change oil and filters | U115: =IF(OR($Q115="",$Q115="OK",$Q115="Not set",NOT(ISNUMBER($G115))),"",ROUND($G115*IF($Q115="Danger",Lists!$M$15,Lists!$M$16),0)) -> 52 | V115: =IF($U115="","",IF(OR($Q115="Danger",$U115>=Lists!$M$10),"P1",IF($U115>=Lists!$M$11,"P2","P3"))) -> P2 | W115: =IF(OR($V115="",$B115=""),"",$B115+INDEX(Lists!$N$10:$N$12,MATCH($V115,Lists!$L$10:$L$12,0))) -> 46086 | X115: 242530 | Y115: Closed | Z115: RCM Specialist | AA115: 46078 | AB115: Mechanical Supervisor | AC115: =IF(OR($U115="",$B115=""),"",IF($AA115<>"",$AA115-$B115,TODAY()-$B115)) -> 22 | AD115: =IF($W115="","",IF($Y115="Closed",IF($AA115="","Closed",IF($AA115<=$W115,"Closed on time","Closed late")),IF(TODAY()>$W115,"Overdue","Within time"))) -> Closed on time
A116: =IF($C116="","","R"&TEXT(ROW()-4,"00000")) -> R00112 | B116: 46058 | C116: 100109 | D116: =IF($C116="","",IFERROR(INDEX(Asset_Register!$C$5:$C$1000,MATCH($C116,Asset_Register!$A$5:$A$1000,0)),"Not in register")) -> Boiler feed water pump B | E116: =IF($C116="","",IFERROR(INDEX(Asset_Register!$D$5:$D$1000,MATCH($C116,Asset_Register!$A$5:$A$1000,0)),"Not in register")) -> Acid plant | F116: =IF($C116="","",IFERROR(INDEX(Asset_Register!$R$5:$R$1000,MATCH($C116,Asset_Register!$A$5:$A$1000,0)),"Not in register")) -> A | G116: =IF($C116="","",IFERROR(INDEX(Asset_Register!$Q$5:$Q$1000,MATCH($C116,Asset_Register!$A$5:$A$1000,0)),"Not in register")) -> 71 | H116: Vibration & visual route | I116: Vibration | J116: Overall velocity (max point) | K116: 1.9 | L116: mm/s | M116: 4.5 | N116: 7.1 | O116: Higher is worse | Q116: =IF($C116="","",IF($P116<>"",$P116,IF(AND(ISNUMBER($K116),ISNUMBER($M116),ISNUMBER($N116)),IF($O116="Lower is worse",IF($K116<=$N116,"Danger",IF($K116<=$M116,"Alert","OK")),IF($K116>=$N116,"Danger",IF($K116>=$M116,"Alert","OK"))),"Not set"))) -> OK | R116: =IF(OR($Q116="",$Q116="Not set"),"",MATCH($Q116,Lists!$F$2:$F$4,0)-1) -> 0 | U116: =IF(OR($Q116="",$Q116="OK",$Q116="Not set",NOT(ISNUMBER($G116))),"",ROUND($G116*IF($Q116="Danger",Lists!$M$15,Lists!$M$16),0)) | V116: =IF($U116="","",IF(OR($Q116="Danger",$U116>=Lists!$M$10),"P1",IF($U116>=Lists!$M$11,"P2","P3"))) | W116: =IF(OR($V116="",$B116=""),"",$B116+INDEX(Lists!$N$10:$N$12,MATCH($V116,Lists!$L$10:$L$12,0))) | Y116: No action | Z116: RCM Specialist | AC116: =IF(OR($U116="",$B116=""),"",IF($AA116<>"",$AA116-$B116,TODAY()-$B116)) | AD116: =IF($W116="","",IF($Y116="Closed",IF($AA116="","Closed",IF($AA116<=$W116,"Closed on time","Closed late")),IF(TODAY()>$W116,"Overdue","Within time")))
A117: =IF($C117="","","R"&TEXT(ROW()-4,"00000")) -> R00113 | B117: 46058 | C117: 100108 | D117: =IF($C117="","",IFERROR(INDEX(Asset_Register!$C$5:$C$1000,MATCH($C117,Asset_Register!$A$5:$A$1000,0)),"Not in register")) -> Boiler feed water pump A | E117: =IF($C117="","",IFERROR(INDEX(Asset_Register!$D$5:$D$1000,MATCH($C117,Asset_Register!$A$5:$A$1000,0)),"Not in register")) -> Acid plant | F117: =IF($C117="","",IFERROR(INDEX(Asset_Register!$R$5:$R$1000,MATCH($C117,Asset_Register!$A$5:$A$1000,0)),"Not in register")) -> A | G117: =IF($C117="","",IFERROR(INDEX(Asset_Register!$Q$5:$Q$1000,MATCH($C117,Asset_Register!$A$5:$A$1000,0)),"Not in register")) -> 75 | H117: Oil analysis | I117: Lubrication / oil | J117: Water in bearing oil | K117: 240 | L117: ppm | M117: 1000 | N117: 2000 | O117: Higher is worse | Q117: =IF($C117="","",IF($P117<>"",$P117,IF(AND(ISNUMBER($K117),ISNUMBER($M117),ISNUMBER($N117)),IF($O117="Lower is worse",IF($K117<=$N117,"Danger",IF($K117<=$M117,"Alert","OK")),IF($K117>=$N117,"Danger",IF($K117>=$M117,"Alert","OK"))),"Not set"))) -> OK | R117: =IF(OR($Q117="",$Q117="Not set"),"",MATCH($Q117,Lists!$F$2:$F$4,0)-1) -> 0 | U117: =IF(OR($Q117="",$Q117="OK",$Q117="Not set",NOT(ISNUMBER($G117))),"",ROUND($G117*IF($Q117="Danger",Lists!$M$15,Lists!$M$16),0)) | V117: =IF($U117="","",IF(OR($Q117="Danger",$U117>=Lists!$M$10),"P1",IF($U117>=Lists!$M$11,"P2","P3"))) | W117: =IF(OR($V117="",$B117=""),"",$B117+INDEX(Lists!$N$10:$N$12,MATCH($V117,Lists!$L$10:$L$12,0))) | Y117: No action | Z117: RCM Specialist | AC117: =IF(OR($U117="",$B117=""),"",IF($AA117<>"",$AA117-$B117,TODAY()-$B117)) | AD117: =IF($W117="","",IF($Y117="Closed",IF($AA117="","Closed",IF($AA117<=$W117,"Closed on time","Closed late")),IF(TODAY()>$W117,"Overdue","Within time")))
A118: =IF($C118="","","R"&TEXT(ROW()-4,"00000")) -> R00114 | B118: 46061 | C118: 100101 | D118: =IF($C118="","",IFERROR(INDEX(Asset_Register!$C$5:$C$1000,MATCH($C118,Asset_Register!$A$5:$A$1000,0)),"Not in register")) -> Sulphur furnace | E118: =IF($C118="","",IFERROR(INDEX(Asset_Register!$D$5:$D$1000,MATCH($C118,Asset_Register!$A$5:$A$1000,0)),"Not in register")) -> Acid plant | F118: =IF($C118="","",IFERROR(INDEX(Asset_Register!$R$5:$R$1000,MATCH($C118,Asset_Register!$A$5:$A$1000,0)),"Not in register")) -> A | G118: =IF($C118="","",IFERROR(INDEX(Asset_Register!$Q$5:$Q$1000,MATCH($C118,Asset_Register!$A$5:$A$1000,0)),"Not in register")) -> 94 | H118: IR survey | I118: Infrared | J118: Burner-end shell temperature | K118: 230 | L118: °C | M118: 280 | N118: 320 | O118: Higher is worse | Q118: =IF($C118="","",IF($P118<>"",$P118,IF(AND(ISNUMBER($K118),ISNUMBER($M118),ISNUMBER($N118)),IF($O118="Lower is worse",IF($K118<=$N118,"Danger",IF($K118<=$M118,"Alert","OK")),IF($K118>=$N118,"Danger",IF($K118>=$M118,"Alert","OK"))),"Not set"))) -> OK | R118: =IF(OR($Q118="",$Q118="Not set"),"",MATCH($Q118,Lists!$F$2:$F$4,0)-1) -> 0 | U118: =IF(OR($Q118="",$Q118="OK",$Q118="Not set",NOT(ISNUMBER($G118))),"",ROUND($G118*IF($Q118="Danger",Lists!$M$15,Lists!$M$16),0)) | V118: =IF($U118="","",IF(OR($Q118="Danger",$U118>=Lists!$M$10),"P1",IF($U118>=Lists!$M$11,"P2","P3"))) | W118: =IF(OR($V118="",$B118=""),"",$B118+INDEX(Lists!$N$10:$N$12,MATCH($V118,Lists!$L$10:$L$12,0))) | Y118: No action | Z118: RCM Specialist | AC118: =IF(OR($U118="",$B118=""),"",IF($AA118<>"",$AA118-$B118,TODAY()-$B118)) | AD118: =IF($W118="","",IF($Y118="Closed",IF($AA118="","Closed",IF($AA118<=$W118,"Closed on time","Closed late")),IF(TODAY()>$W118,"Overdue","Within time")))
A119: =IF($C119="","","R"&TEXT(ROW()-4,"00000")) -> R00115 | B119: 46063 | C119: 100112 | D119: =IF($C119="","",IFERROR(INDEX(Asset_Register!$C$5:$C$1000,MATCH($C119,Asset_Register!$A$5:$A$1000,0)),"Not in register")) -> Cooling tower fan 1 | E119: =IF($C119="","",IFERROR(INDEX(Asset_Register!$D$5:$D$1000,MATCH($C119,Asset_Register!$A$5:$A$1000,0)),"Not in register")) -> Acid plant | F119: =IF($C119="","",IFERROR(INDEX(Asset_Register!$R$5:$R$1000,MATCH($C119,Asset_Register!$A$5:$A$1000,0)),"Not in register")) -> B | G119: =IF($C119="","",IFERROR(INDEX(Asset_Register!$Q$5:$Q$1000,MATCH($C119,Asset_Register!$A$5:$A$1000,0)),"Not in register")) -> 50 | H119: Vibration & visual route | I119: Vibration | J119: Gearbox overall velocity | K119: 4 | L119: mm/s | M119: 4.5 | N119: 7.1 | O119: Higher is worse | Q119: =IF($C119="","",IF($P119<>"",$P119,IF(AND(ISNUMBER($K119),ISNUMBER($M119),ISNUMBER($N119)),IF($O119="Lower is worse",IF($K119<=$N119,"Danger",IF($K119<=$M119,"Alert","OK")),IF($K119>=$N119,"Danger",IF($K119>=$M119,"Alert","OK"))),"Not set"))) -> OK | R119: =IF(OR($Q119="",$Q119="Not set"),"",MATCH($Q119,Lists!$F$2:$F$4,0)-1) -> 0 | U119: =IF(OR($Q119="",$Q119="OK",$Q119="Not set",NOT(ISNUMBER($G119))),"",ROUND($G119*IF($Q119="Danger",Lists!$M$15,Lists!$M$16),0)) | V119: =IF($U119="","",IF(OR($Q119="Danger",$U119>=Lists!$M$10),"P1",IF($U119>=Lists!$M$11,"P2","P3"))) | W119: =IF(OR($V119="",$B119=""),"",$B119+INDEX(Lists!$N$10:$N$12,MATCH($V119,Lists!$L$10:$L$12,0))) | Y119: No action | Z119: RCM Specialist | AC119: =IF(OR($U119="",$B119=""),"",IF($AA119<>"",$AA119-$B119,TODAY()-$B119)) | AD119: =IF($W119="","",IF($Y119="Closed",IF($AA119="","Closed",IF($AA119<=$W119,"Closed on time","Closed late")),IF(TODAY()>$W119,"Overdue","Within time")))
A120: =IF($C120="","","R"&TEXT(ROW()-4,"00000")) -> R00116 | B120: 46063 | C120: 100201 | D120: =IF($C120="","",IFERROR(INDEX(Asset_Register!$C$5:$C$1000,MATCH($C120,Asset_Register!$A$5:$A$1000,0)),"Not in register")) -> Calciner kiln 1080 | E120: =IF($C120="","",IFERROR(INDEX(Asset_Register!$D$5:$D$1000,MATCH($C120,Asset_Register!$A$5:$A$1000,0)),"Not in register")) -> Calciner | F120: =IF($C120="","",IFERROR(INDEX(Asset_Register!$R$5:$R$1000,MATCH($C120,Asset_Register!$A$5:$A$1000,0)),"Not in register")) -> A | G120: =IF($C120="","",IFERROR(INDEX(Asset_Register!$Q$5:$Q$1000,MATCH($C120,Asset_Register!$A$5:$A$1000,0)),"Not in register")) -> 90 | H120: IR survey | I120: Infrared | J120: Zone 4 shell temperature | K120: 255 | L120: °C | M120: 280 | N120: 350 | O120: Higher is worse | Q120: =IF($C120="","",IF($P120<>"",$P120,IF(AND(ISNUMBER($K120),ISNUMBER($M120),ISNUMBER($N120)),IF($O120="Lower is worse",IF($K120<=$N120,"Danger",IF($K120<=$M120,"Alert","OK")),IF($K120>=$N120,"Danger",IF($K120>=$M120,"Alert","OK"))),"Not set"))) -> OK | R120: =IF(OR($Q120="",$Q120="Not set"),"",MATCH($Q120,Lists!$F$2:$F$4,0)-1) -> 0 | U120: =IF(OR($Q120="",$Q120="OK",$Q120="Not set",NOT(ISNUMBER($G120))),"",ROUND($G120*IF($Q120="Danger",Lists!$M$15,Lists!$M$16),0)) | V120: =IF($U120="","",IF(OR($Q120="Danger",$U120>=Lists!$M$10),"P1",IF($U120>=Lists!$M$11,"P2","P3"))) | W120: =IF(OR($V120="",$B120=""),"",$B120+INDEX(Lists!$N$10:$N$12,MATCH($V120,Lists!$L$10:$L$12,0))) | Y120: No action | Z120: RCM Specialist | AC120: =IF(OR($U120="",$B120=""),"",IF($AA120<>"",$AA120-$B120,TODAY()-$B120)) | AD120: =IF($W120="","",IF($Y120="Closed",IF($AA120="","Closed",IF($AA120<=$W120,"Closed on time","Closed late")),IF(TODAY()>$W120,"Overdue","Within time")))
A121: =IF($C121="","","R"&TEXT(ROW()-4,"00000")) -> R00117 | B121: 46063 | C121: 100112 | D121: =IF($C121="","",IFERROR(INDEX(Asset_Register!$C$5:$C$1000,MATCH($C121,Asset_Register!$A$5:$A$1000,0)),"Not in register")) -> Cooling tower fan 1 | E121: =IF($C121="","",IFERROR(INDEX(Asset_Register!$D$5:$D$1000,MATCH($C121,Asset_Register!$A$5:$A$1000,0)),"Not in register")) -> Acid plant | F121: =IF($C121="","",IFERROR(INDEX(Asset_Register!$R$5:$R$1000,MATCH($C121,Asset_Register!$A$5:$A$1000,0)),"Not in register")) -> B | G121: =IF($C121="","",IFERROR(INDEX(Asset_Register!$Q$5:$Q$1000,MATCH($C121,Asset_Register!$A$5:$A$1000,0)),"Not in register")) -> 50 | H121: Oil analysis | I121: Lubrication / oil | J121: Copper (Cu) in gearbox oil | K121: 16 | L121: ppm | M121: 30 | N121: 60 | O121: Higher is worse | Q121: =IF($C121="","",IF($P121<>"",$P121,IF(AND(ISNUMBER($K121),ISNUMBER($M121),ISNUMBER($N121)),IF($O121="Lower is worse",IF($K121<=$N121,"Danger",IF($K121<=$M121,"Alert","OK")),IF($K121>=$N121,"Danger",IF($K121>=$M121,"Alert","OK"))),"Not set"))) -> OK | R121: =IF(OR($Q121="",$Q121="Not set"),"",MATCH($Q121,Lists!$F$2:$F$4,0)-1) -> 0 | U121: =IF(OR($Q121="",$Q121="OK",$Q121="Not set",NOT(ISNUMBER($G121))),"",ROUND($G121*IF($Q121="Danger",Lists!$M$15,Lists!$M$16),0)) | V121: =IF($U121="","",IF(OR($Q121="Danger",$U121>=Lists!$M$10),"P1",IF($U121>=Lists!$M$11,"P2","P3"))) | W121: =IF(OR($V121="",$B121=""),"",$B121+INDEX(Lists!$N$10:$N$12,MATCH($V121,Lists!$L$10:$L$12,0))) | Y121: No action | Z121: RCM Specialist | AC121: =IF(OR($U121="",$B121=""),"",IF($AA121<>"",$AA121-$B121,TODAY()-$B121)) | AD121: =IF($W121="","",IF($Y121="Closed",IF($AA121="","Closed",IF($AA121<=$W121,"Closed on time","Closed late")),IF(TODAY()>$W121,"Overdue","Within time")))
A122: =IF($C122="","","R"&TEXT(ROW()-4,"00000")) -> R00118 | B122: 46063 | C122: 100603 | D122: =IF($C122="","",IFERROR(INDEX(Asset_Register!$C$5:$C$1000,MATCH($C122,Asset_Register!$A$5:$A$1000,0)),"Not in register")) -> Front-end loader HV-03 | E122: =IF($C122="","",IFERROR(INDEX(Asset_Register!$D$5:$D$1000,MATCH($C122,Asset_Register!$A$5:$A$1000,0)),"Not in register")) -> Mobile fleet | F122: =IF($C122="","",IFERROR(INDEX(Asset_Register!$R$5:$R$1000,MATCH($C122,Asset_Register!$A$5:$A$1000,0)),"Not in register")) -> B | G122: =IF($C122="","",IFERROR(INDEX(Asset_Register!$Q$5:$Q$1000,MATCH($C122,Asset_Register!$A$5:$A$1000,0)),"Not in register")) -> 67 | H122: Oil analysis | I122: Lubrication / oil | J122: Engine oil silicon (Si) | K122: 9 | L122: ppm | M122: 20 | N122: 30 | O122: Higher is worse | Q122: =IF($C122="","",IF($P122<>"",$P122,IF(AND(ISNUMBER($K122),ISNUMBER($M122),ISNUMBER($N122)),IF($O122="Lower is worse",IF($K122<=$N122,"Danger",IF($K122<=$M122,"Alert","OK")),IF($K122>=$N122,"Danger",IF($K122>=$M122,"Alert","OK"))),"Not set"))) -> OK | R122: =IF(OR($Q122="",$Q122="Not set"),"",MATCH($Q122,Lists!$F$2:$F$4,0)-1) -> 0 | U122: =IF(OR($Q122="",$Q122="OK",$Q122="Not set",NOT(ISNUMBER($G122))),"",ROUND($G122*IF($Q122="Danger",Lists!$M$15,Lists!$M$16),0)) | V122: =IF($U122="","",IF(OR($Q122="Danger",$U122>=Lists!$M$10),"P1",IF($U122>=Lists!$M$11,"P2","P3"))) | W122: =IF(OR($V122="",$B122=""),"",$B122+INDEX(Lists!$N$10:$N$12,MATCH($V122,Lists!$L$10:$L$12,0))) | Y122: No action | Z122: RCM Specialist | AC122: =IF(OR($U122="",$B122=""),"",IF($AA122<>"",$AA122-$B122,TODAY()-$B122)) | AD122: =IF($W122="","",IF($Y122="Closed",IF($AA122="","Closed",IF($AA122<=$W122,"Closed on time","Closed late")),IF(TODAY()>$W122,"Overdue","Within time")))
A123: =IF($C123="","","R"&TEXT(ROW()-4,"00000")) -> R00119 | B123: 46063 | C123: 100601 | D123: =IF($C123="","",IFERROR(INDEX(Asset_Register!$C$5:$C$1000,MATCH($C123,Asset_Register!$A$5:$A$1000,0)),"Not in register")) -> Dozer HV-01 | E123: =IF($C123="","",IFERROR(INDEX(Asset_Register!$D$5:$D$1000,MATCH($C123,Asset_Register!$A$5:$A$1000,0)),"Not in register")) -> Mobile fleet | F123: =IF($C123="","",IFERROR(INDEX(Asset_Register!$R$5:$R$1000,MATCH($C123,Asset_Register!$A$5:$A$1000,0)),"Not in register")) -> B | G123: =IF($C123="","",IFERROR(INDEX(Asset_Register!$Q$5:$Q$1000,MATCH($C123,Asset_Register!$A$5:$A$1000,0)),"Not in register")) -> 69 | H123: Oil analysis | I123: Lubrication / oil | J123: Engine oil iron (Fe) | K123: 24 | L123: ppm | M123: 60 | N123: 100 | O123: Higher is worse | Q123: =IF($C123="","",IF($P123<>"",$P123,IF(AND(ISNUMBER($K123),ISNUMBER($M123),ISNUMBER($N123)),IF($O123="Lower is worse",IF($K123<=$N123,"Danger",IF($K123<=$M123,"Alert","OK")),IF($K123>=$N123,"Danger",IF($K123>=$M123,"Alert","OK"))),"Not set"))) -> OK | R123: =IF(OR($Q123="",$Q123="Not set"),"",MATCH($Q123,Lists!$F$2:$F$4,0)-1) -> 0 | U123: =IF(OR($Q123="",$Q123="OK",$Q123="Not set",NOT(ISNUMBER($G123))),"",ROUND($G123*IF($Q123="Danger",Lists!$M$15,Lists!$M$16),0)) | V123: =IF($U123="","",IF(OR($Q123="Danger",$U123>=Lists!$M$10),"P1",IF($U123>=Lists!$M$11,"P2","P3"))) | W123: =IF(OR($V123="",$B123=""),"",$B123+INDEX(Lists!$N$10:$N$12,MATCH($V123,Lists!$L$10:$L$12,0))) | Y123: No action | Z123: RCM Specialist | AC123: =IF(OR($U123="",$B123=""),"",IF($AA123<>"",$AA123-$B123,TODAY()-$B123)) | AD123: =IF($W123="","",IF($Y123="Closed",IF($AA123="","Closed",IF($AA123<=$W123,"Closed on time","Closed late")),IF(TODAY()>$W123,"Overdue","Within time")))
A124: =IF($C124="","","R"&TEXT(ROW()-4,"00000")) -> R00120 | B124: 46063 | C124: 100602 | D124: =IF($C124="","",IFERROR(INDEX(Asset_Register!$C$5:$C$1000,MATCH($C124,Asset_Register!$A$5:$A$1000,0)),"Not in register")) -> Compactor HV-02 | E124: =IF($C124="","",IFERROR(INDEX(Asset_Register!$D$5:$D$1000,MATCH($C124,Asset_Register!$A$5:$A$1000,0)),"Not in register")) -> Mobile fleet | F124: =IF($C124="","",IFERROR(INDEX(Asset_Register!$R$5:$R$1000,MATCH($C124,Asset_Register!$A$5:$A$1000,0)),"Not in register")) -> B | G124: =IF($C124="","",IFERROR(INDEX(Asset_Register!$Q$5:$Q$1000,MATCH($C124,Asset_Register!$A$5:$A$1000,0)),"Not in register")) -> 58 | H124: Oil analysis | I124: Lubrication / oil | J124: Engine oil iron (Fe) | K124: 22 | L124: ppm | M124: 60 | N124: 100 | O124: Higher is worse | Q124: =IF($C124="","",IF($P124<>"",$P124,IF(AND(ISNUMBER($K124),ISNUMBER($M124),ISNUMBER($N124)),IF($O124="Lower is worse",IF($K124<=$N124,"Danger",IF($K124<=$M124,"Alert","OK")),IF($K124>=$N124,"Danger",IF($K124>=$M124,"Alert","OK"))),"Not set"))) -> OK | R124: =IF(OR($Q124="",$Q124="Not set"),"",MATCH($Q124,Lists!$F$2:$F$4,0)-1) -> 0 | U124: =IF(OR($Q124="",$Q124="OK",$Q124="Not set",NOT(ISNUMBER($G124))),"",ROUND($G124*IF($Q124="Danger",Lists!$M$15,Lists!$M$16),0)) | V124: =IF($U124="","",IF(OR($Q124="Danger",$U124>=Lists!$M$10),"P1",IF($U124>=Lists!$M$11,"P2","P3"))) | W124: =IF(OR($V124="",$B124=""),"",$B124+INDEX(Lists!$N$10:$N$12,MATCH($V124,Lists!$L$10:$L$12,0))) | Y124: No action | Z124: RCM Specialist | AC124: =IF(OR($U124="",$B124=""),"",IF($AA124<>"",$AA124-$B124,TODAY()-$B124)) | AD124: =IF($W124="","",IF($Y124="Closed",IF($AA124="","Closed",IF($AA124<=$W124,"Closed on time","Closed late")),IF(TODAY()>$W124,"Overdue","Within time")))
A125: =IF($C125="","","R"&TEXT(ROW()-4,"00000")) -> R00121 | B125: 46065 | C125: 100103 | D125: =IF($C125="","",IFERROR(INDEX(Asset_Register!$C$5:$C$1000,MATCH($C125,Asset_Register!$A$5:$A$1000,0)),"Not in register")) -> Main air blower | E125: =IF($C125="","",IFERROR(INDEX(Asset_Register!$D$5:$D$1000,MATCH($C125,Asset_Register!$A$5:$A$1000,0)),"Not in register")) -> Acid plant | F125: =IF($C125="","",IFERROR(INDEX(Asset_Register!$R$5:$R$1000,MATCH($C125,Asset_Register!$A$5:$A$1000,0)),"Not in register")) -> A | G125: =IF($C125="","",IFERROR(INDEX(Asset_Register!$Q$5:$Q$1000,MATCH($C125,Asset_Register!$A$5:$A$1000,0)),"Not in register")) -> 87 | H125: Vibration & visual route | I125: Vibration | J125: Overall velocity (max point) | K125: 2.4 | L125: mm/s | M125: 4.5 | N125: 7.1 | O125: Higher is worse | Q125: =IF($C125="","",IF($P125<>"",$P125,IF(AND(ISNUMBER($K125),ISNUMBER($M125),ISNUMBER($N125)),IF($O125="Lower is worse",IF($K125<=$N125,"Danger",IF($K125<=$M125,"Alert","OK")),IF($K125>=$N125,"Danger",IF($K125>=$M125,"Alert","OK"))),"Not set"))) -> OK | R125: =IF(OR($Q125="",$Q125="Not set"),"",MATCH($Q125,Lists!$F$2:$F$4,0)-1) -> 0 | U125: =IF(OR($Q125="",$Q125="OK",$Q125="Not set",NOT(ISNUMBER($G125))),"",ROUND($G125*IF($Q125="Danger",Lists!$M$15,Lists!$M$16),0)) | V125: =IF($U125="","",IF(OR($Q125="Danger",$U125>=Lists!$M$10),"P1",IF($U125>=Lists!$M$11,"P2","P3"))) | W125: =IF(OR($V125="",$B125=""),"",$B125+INDEX(Lists!$N$10:$N$12,MATCH($V125,Lists!$L$10:$L$12,0))) | Y125: No action | Z125: RCM Specialist | AC125: =IF(OR($U125="",$B125=""),"",IF($AA125<>"",$AA125-$B125,TODAY()-$B125)) | AD125: =IF($W125="","",IF($Y125="Closed",IF($AA125="","Closed",IF($AA125<=$W125,"Closed on time","Closed late")),IF(TODAY()>$W125,"Overdue","Within time")))
A126: =IF($C126="","","R"&TEXT(ROW()-4,"00000")) -> R00122 | B126: 46068 | C126: 100107 | D126: =IF($C126="","",IFERROR(INDEX(Asset_Register!$C$5:$C$1000,MATCH($C126,Asset_Register!$A$5:$A$1000,0)),"Not in register")) -> Final tower acid pump | E126: =IF($C126="","",IFERROR(INDEX(Asset_Register!$D$5:$D$1000,MATCH($C126,Asset_Register!$A$5:$A$1000,0)),"Not in register")) -> Acid plant | F126: =IF($C126="","",IFERROR(INDEX(Asset_Register!$R$5:$R$1000,MATCH($C126,Asset_Register!$A$5:$A$1000,0)),"Not in register")) -> B | G126: =IF($C126="","",IFERROR(INDEX(Asset_Register!$Q$5:$Q$1000,MATCH($C126,Asset_Register!$A$5:$A$1000,0)),"Not in register")) -> 66 | H126: Vibration & visual route | I126: Vibration | J126: Overall velocity (max point) | K126: 3.3 | L126: mm/s | M126: 4.5 | N126: 7.1 | O126: Higher is worse | Q126: =IF($C126="","",IF($P126<>"",$P126,IF(AND(ISNUMBER($K126),ISNUMBER($M126),ISNUMBER($N126)),IF($O126="Lower is worse",IF($K126<=$N126,"Danger",IF($K126<=$M126,"Alert","OK")),IF($K126>=$N126,"Danger",IF($K126>=$M126,"Alert","OK"))),"Not set"))) -> OK | R126: =IF(OR($Q126="",$Q126="Not set"),"",MATCH($Q126,Lists!$F$2:$F$4,0)-1) -> 0 | U126: =IF(OR($Q126="",$Q126="OK",$Q126="Not set",NOT(ISNUMBER($G126))),"",ROUND($G126*IF($Q126="Danger",Lists!$M$15,Lists!$M$16),0)) | V126: =IF($U126="","",IF(OR($Q126="Danger",$U126>=Lists!$M$10),"P1",IF($U126>=Lists!$M$11,"P2","P3"))) | W126: =IF(OR($V126="",$B126=""),"",$B126+INDEX(Lists!$N$10:$N$12,MATCH($V126,Lists!$L$10:$L$12,0))) | Y126: No action | Z126: RCM Specialist | AC126: =IF(OR($U126="",$B126=""),"",IF($AA126<>"",$AA126-$B126,TODAY()-$B126)) | AD126: =IF($W126="","",IF($Y126="Closed",IF($AA126="","Closed",IF($AA126<=$W126,"Closed on time","Closed late")),IF(TODAY()>$W126,"Overdue","Within time")))
A127: =IF($C127="","","R"&TEXT(ROW()-4,"00000")) -> R00123 | B127: 46073 | C127: 100104 | D127: =IF($C127="","",IFERROR(INDEX(Asset_Register!$C$5:$C$1000,MATCH($C127,Asset_Register!$A$5:$A$1000,0)),"Not in register")) -> SO2 converter | E127: =IF($C127="","",IFERROR(INDEX(Asset_Register!$D$5:$D$1000,MATCH($C127,Asset_Register!$A$5:$A$1000,0)),"Not in register")) -> Acid plant | F127: =IF($C127="","",IFERROR(INDEX(Asset_Register!$R$5:$R$1000,MATCH($C127,Asset_Register!$A$5:$A$1000,0)),"Not in register")) -> A | G127: =IF($C127="","",IFERROR(INDEX(Asset_Register!$Q$5:$Q$1000,MATCH($C127,Asset_Register!$A$5:$A$1000,0)),"Not in register")) -> 86 | H127: IR survey | I127: Infrared | J127: Bed 3 outlet flange dT above baseline | K127: 8 | L127: °C | M127: 30 | N127: 60 | O127: Higher is worse | Q127: =IF($C127="","",IF($P127<>"",$P127,IF(AND(ISNUMBER($K127),ISNUMBER($M127),ISNUMBER($N127)),IF($O127="Lower is worse",IF($K127<=$N127,"Danger",IF($K127<=$M127,"Alert","OK")),IF($K127>=$N127,"Danger",IF($K127>=$M127,"Alert","OK"))),"Not set"))) -> OK | R127: =IF(OR($Q127="",$Q127="Not set"),"",MATCH($Q127,Lists!$F$2:$F$4,0)-1) -> 0 | U127: =IF(OR($Q127="",$Q127="OK",$Q127="Not set",NOT(ISNUMBER($G127))),"",ROUND($G127*IF($Q127="Danger",Lists!$M$15,Lists!$M$16),0)) | V127: =IF($U127="","",IF(OR($Q127="Danger",$U127>=Lists!$M$10),"P1",IF($U127>=Lists!$M$11,"P2","P3"))) | W127: =IF(OR($V127="",$B127=""),"",$B127+INDEX(Lists!$N$10:$N$12,MATCH($V127,Lists!$L$10:$L$12,0))) | Y127: No action | Z127: RCM Specialist | AC127: =IF(OR($U127="",$B127=""),"",IF($AA127<>"",$AA127-$B127,TODAY()-$B127)) | AD127: =IF($W127="","",IF($Y127="Closed",IF($AA127="","Closed",IF($AA127<=$W127,"Closed on time","Closed late")),IF(TODAY()>$W127,"Overdue","Within time")))
... A130: =IF($C130="","","R"&TEXT(ROW()-4,"00000")) -> R00126 | B130: 46075 | C130: 100105 | D130: =IF($C130="","",IFERROR(INDEX(Asset_Register!$C$5:$C$1000,MATCH($C130,Asset_Register!$A$5:$A$1000,0)),"Not in register")) -> Drying tower acid pump | E130: =IF($C130="","",IFERROR(INDEX(Asset_Register!$D$5:$D$1000,MATCH($C130,Asset_Register!$A$5:$A$1000,0)),"Not in register")) -> Acid plant | F130: =IF($C130="","",IFERROR(INDEX(Asset_Register!$R$5:$R$1000,MATCH($C130,Asset_Register!$A$5:$A$1000,0)),"Not in register")) -> A | G130: =IF($C130="","",IFERROR(INDEX(Asset_Register!$Q$5:$Q$1000,MATCH($C130,Asset_Register!$A$5:$A$1000,0)),"Not in register")) -> 74 | H130: Oil analysis | I130: Lubrication / oil | J130: Iron (Fe) | K130: 22 | L130: ppm | M130: 50 | N130: 100 | O130: Higher is worse | Q130: =IF($C130="","",IF($P130<>"",$P130,IF(AND(ISNUMBER($K130),ISNUMBER($M130),ISNUMBER($N130)),IF($O130="Lower is worse",IF($K130<=$N130,"Danger",IF($K130<=$M130,"Alert","OK")),IF($K130>=$N130,"Danger",IF($K130>=$M130,"Alert","OK"))),"Not set"))) -> OK | R130: =IF(OR($Q130="",$Q130="Not set"),"",MATCH($Q130,Lists!$F$2:$F$4,0)-1) -> 0 | U130: =IF(OR($Q130="",$Q130="OK",$Q130="Not set",NOT(ISNUMBER($G130))),"",ROUND($G130*IF($Q130="Danger",Lists!$M$15,Lists!$M$16),0)) | V130: =IF($U130="","",IF(OR($Q130="Danger",$U130>=Lists!$M$10),"P1",IF($U130>=Lists!$M$11,"P2","P3"))) | W130: =IF(OR($V130="",$B130=""),"",$B130+INDEX(Lists!$N$10:$N$12,MATCH($V130,Lists!$L$10:$L$12,0))) | Y130: No action | Z130: RCM Specialist | AC130: =IF(OR($U130="",$B130=""),"",IF($AA130<>"",$AA130-$B130,TODAY()-$B130)) | AD130: =IF($W130="","",IF($Y130="Closed",IF($AA130="","Closed",IF($AA130<=$W130,"Closed on time","Closed late")),IF(TODAY()>$W130,"Overdue","Within time")))
A131: =IF($C131="","","R"&TEXT(ROW()-4,"00000")) -> R00127 | B131: 46077 | C131: 100301 | D131: =IF($C131="","",IFERROR(INDEX(Asset_Register!$C$5:$C$1000,MATCH($C131,Asset_Register!$A$5:$A$1000,0)),"Not in register")) -> Transformer TX-01 | E131: =IF($C131="","",IFERROR(INDEX(Asset_Register!$D$5:$D$1000,MATCH($C131,Asset_Register!$A$5:$A$1000,0)),"Not in register")) -> Substation | F131: =IF($C131="","",IFERROR(INDEX(Asset_Register!$R$5:$R$1000,MATCH($C131,Asset_Register!$A$5:$A$1000,0)),"Not in register")) -> A | G131: =IF($C131="","",IFERROR(INDEX(Asset_Register!$Q$5:$Q$1000,MATCH($C131,Asset_Register!$A$5:$A$1000,0)),"Not in register")) -> 86 | H131: Substation inspection | I131: Infrared | J131: LV bushing connection dT | K131: 5 | L131: °C | M131: 4 | N131: 15 | O131: Higher is worse | Q131: =IF($C131="","",IF($P131<>"",$P131,IF(AND(ISNUMBER($K131),ISNUMBER($M131),ISNUMBER($N131)),IF($O131="Lower is worse",IF($K131<=$N131,"Danger",IF($K131<=$M131,"Alert","OK")),IF($K131>=$N131,"Danger",IF($K131>=$M131,"Alert","OK"))),"Not set"))) -> Alert | R131: =IF(OR($Q131="",$Q131="Not set"),"",MATCH($Q131,Lists!$F$2:$F$4,0)-1) -> 1 | S131: LV connection running warm | T131: Clean and retorque connection | U131: =IF(OR($Q131="",$Q131="OK",$Q131="Not set",NOT(ISNUMBER($G131))),"",ROUND($G131*IF($Q131="Danger",Lists!$M$15,Lists!$M$16),0)) -> 52 | V131: =IF($U131="","",IF(OR($Q131="Danger",$U131>=Lists!$M$10),"P1",IF($U131>=Lists!$M$11,"P2","P3"))) -> P2 | W131: =IF(OR($V131="",$B131=""),"",$B131+INDEX(Lists!$N$10:$N$12,MATCH($V131,Lists!$L$10:$L$12,0))) -> 46107 | X131: 243120 | Y131: Closed | Z131: Electrician | AA131: 46127 | AB131: Electrical Supervisor | AC131: =IF(OR($U131="",$B131=""),"",IF($AA131<>"",$AA131-$B131,TODAY()-$B131)) -> 50 | AD131: =IF($W131="","",IF($Y131="Closed",IF($AA131="","Closed",IF($AA131<=$W131,"Closed on time","Closed late")),IF(TODAY()>$W131,"Overdue","Within time"))) -> Closed late
A132: =IF($C132="","","R"&TEXT(ROW()-4,"00000")) -> R00128 | B132: 46077 | C132: 100302 | D132: =IF($C132="","",IFERROR(INDEX(Asset_Register!$C$5:$C$1000,MATCH($C132,Asset_Register!$A$5:$A$1000,0)),"Not in register")) -> Acid plant MCC | E132: =IF($C132="","",IFERROR(INDEX(Asset_Register!$D$5:$D$1000,MATCH($C132,Asset_Register!$A$5:$A$1000,0)),"Not in register")) -> Substation | F132: =IF($C132="","",IFERROR(INDEX(Asset_Register!$R$5:$R$1000,MATCH($C132,Asset_Register!$A$5:$A$1000,0)),"Not in register")) -> A | G132: =IF($C132="","",IFERROR(INDEX(Asset_Register!$Q$5:$Q$1000,MATCH($C132,Asset_Register!$A$5:$A$1000,0)),"Not in register")) -> 82 | H132: IR survey | I132: Infrared | J132: Hottest termination dT | K132: 3 | L132: °C | M132: 4 | N132: 15 | O132: Higher is worse | Q132: =IF($C132="","",IF($P132<>"",$P132,IF(AND(ISNUMBER($K132),ISNUMBER($M132),ISNUMBER($N132)),IF($O132="Lower is worse",IF($K132<=$N132,"Danger",IF($K132<=$M132,"Alert","OK")),IF($K132>=$N132,"Danger",IF($K132>=$M132,"Alert","OK"))),"Not set"))) -> OK | R132: =IF(OR($Q132="",$Q132="Not set"),"",MATCH($Q132,Lists!$F$2:$F$4,0)-1) -> 0 | U132: =IF(OR($Q132="",$Q132="OK",$Q132="Not set",NOT(ISNUMBER($G132))),"",ROUND($G132*IF($Q132="Danger",Lists!$M$15,Lists!$M$16),0)) | V132: =IF($U132="","",IF(OR($Q132="Danger",$U132>=Lists!$M$10),"P1",IF($U132>=Lists!$M$11,"P2","P3"))) | W132: =IF(OR($V132="",$B132=""),"",$B132+INDEX(Lists!$N$10:$N$12,MATCH($V132,Lists!$L$10:$L$12,0))) | Y132: No action | Z132: RCM Specialist | AC132: =IF(OR($U132="",$B132=""),"",IF($AA132<>"",$AA132-$B132,TODAY()-$B132)) | AD132: =IF($W132="","",IF($Y132="Closed",IF($AA132="","Closed",IF($AA132<=$W132,"Closed on time","Closed late")),IF(TODAY()>$W132,"Overdue","Within time")))
A133: =IF($C133="","","R"&TEXT(ROW()-4,"00000")) -> R00129 | B133: 46081 | C133: 100401 | D133: =IF($C133="","",IFERROR(INDEX(Asset_Register!$C$5:$C$1000,MATCH($C133,Asset_Register!$A$5:$A$1000,0)),"Not in register")) -> Diesel generator Gen 1 | E133: =IF($C133="","",IFERROR(INDEX(Asset_Register!$D$5:$D$1000,MATCH($C133,Asset_Register!$A$5:$A$1000,0)),"Not in register")) -> Power plant | F133: =IF($C133="","",IFERROR(INDEX(Asset_Register!$R$5:$R$1000,MATCH($C133,Asset_Register!$A$5:$A$1000,0)),"Not in register")) -> A | G133: =IF($C133="","",IFERROR(INDEX(Asset_Register!$Q$5:$Q$1000,MATCH($C133,Asset_Register!$A$5:$A$1000,0)),"Not in register")) -> 83 | H133: DG checklist | I133: DG checks | J133: Turbo outlet exhaust temperature | K133: 485 | L133: °C | M133: 520 | N133: 580 | O133: Higher is worse | Q133: =IF($C133="","",IF($P133<>"",$P133,IF(AND(ISNUMBER($K133),ISNUMBER($M133),ISNUMBER($N133)),IF($O133="Lower is worse",IF($K133<=$N133,"Danger",IF($K133<=$M133,"Alert","OK")),IF($K133>=$N133,"Danger",IF($K133>=$M133,"Alert","OK"))),"Not set"))) -> OK | R133: =IF(OR($Q133="",$Q133="Not set"),"",MATCH($Q133,Lists!$F$2:$F$4,0)-1) -> 0 | U133: =IF(OR($Q133="",$Q133="OK",$Q133="Not set",NOT(ISNUMBER($G133))),"",ROUND($G133*IF($Q133="Danger",Lists!$M$15,Lists!$M$16),0)) | V133: =IF($U133="","",IF(OR($Q133="Danger",$U133>=Lists!$M$10),"P1",IF($U133>=Lists!$M$11,"P2","P3"))) | W133: =IF(OR($V133="",$B133=""),"",$B133+INDEX(Lists!$N$10:$N$12,MATCH($V133,Lists!$L$10:$L$12,0))) | Y133: No action | Z133: DG operator | AC133: =IF(OR($U133="",$B133=""),"",IF($AA133<>"",$AA133-$B133,TODAY()-$B133)) | AD133: =IF($W133="","",IF($Y133="Closed",IF($AA133="","Closed",IF($AA133<=$W133,"Closed on time","Closed late")),IF(TODAY()>$W133,"Overdue","Within time")))
A134: =IF($C134="","","R"&TEXT(ROW()-4,"00000")) -> R00130 | B134: 46081 | C134: 100402 | D134: =IF($C134="","",IFERROR(INDEX(Asset_Register!$C$5:$C$1000,MATCH($C134,Asset_Register!$A$5:$A$1000,0)),"Not in register")) -> Diesel generator Gen 2 | E134: =IF($C134="","",IFERROR(INDEX(Asset_Register!$D$5:$D$1000,MATCH($C134,Asset_Register!$A$5:$A$1000,0)),"Not in register")) -> Power plant | F134: =IF($C134="","",IFERROR(INDEX(Asset_Register!$R$5:$R$1000,MATCH($C134,Asset_Register!$A$5:$A$1000,0)),"Not in register")) -> A | G134: =IF($C134="","",IFERROR(INDEX(Asset_Register!$Q$5:$Q$1000,MATCH($C134,Asset_Register!$A$5:$A$1000,0)),"Not in register")) -> 79 | H134: DG checklist | I134: DG checks | J134: Exhaust temperature spread between cylinders | K134: 24 | L134: °C | M134: 50 | N134: 80 | O134: Higher is worse | Q134: =IF($C134="","",IF($P134<>"",$P134,IF(AND(ISNUMBER($K134),ISNUMBER($M134),ISNUMBER($N134)),IF($O134="Lower is worse",IF($K134<=$N134,"Danger",IF($K134<=$M134,"Alert","OK")),IF($K134>=$N134,"Danger",IF($K134>=$M134,"Alert","OK"))),"Not set"))) -> OK | R134: =IF(OR($Q134="",$Q134="Not set"),"",MATCH($Q134,Lists!$F$2:$F$4,0)-1) -> 0 | U134: =IF(OR($Q134="",$Q134="OK",$Q134="Not set",NOT(ISNUMBER($G134))),"",ROUND($G134*IF($Q134="Danger",Lists!$M$15,Lists!$M$16),0)) | V134: =IF($U134="","",IF(OR($Q134="Danger",$U134>=Lists!$M$10),"P1",IF($U134>=Lists!$M$11,"P2","P3"))) | W134: =IF(OR($V134="",$B134=""),"",$B134+INDEX(Lists!$N$10:$N$12,MATCH($V134,Lists!$L$10:$L$12,0))) | Y134: No action | Z134: DG operator | AC134: =IF(OR($U134="",$B134=""),"",IF($AA134<>"",$AA134-$B134,TODAY()-$B134)) | AD134: =IF($W134="","",IF($Y134="Closed",IF($AA134="","Closed",IF($AA134<=$W134,"Closed on time","Closed late")),IF(TODAY()>$W134,"Overdue","Within time")))
A135: =IF($C135="","","R"&TEXT(ROW()-4,"00000")) -> R00131 | B135: 46081 | C135: 100403 | D135: =IF($C135="","",IFERROR(INDEX(Asset_Register!$C$5:$C$1000,MATCH($C135,Asset_Register!$A$5:$A$1000,0)),"Not in register")) -> Diesel generator Gen 3 | E135: =IF($C135="","",IFERROR(INDEX(Asset_Register!$D$5:$D$1000,MATCH($C135,Asset_Register!$A$5:$A$1000,0)),"Not in register")) -> Power plant | F135: =IF($C135="","",IFERROR(INDEX(Asset_Register!$R$5:$R$1000,MATCH($C135,Asset_Register!$A$5:$A$1000,0)),"Not in register")) -> A | G135: =IF($C135="","",IFERROR(INDEX(Asset_Register!$Q$5:$Q$1000,MATCH($C135,Asset_Register!$A$5:$A$1000,0)),"Not in register")) -> 79 | H135: DG checklist | I135: DG checks | J135: Turbo outlet exhaust temperature | K135: 462 | L135: °C | M135: 520 | N135: 580 | O135: Higher is worse | Q135: =IF($C135="","",IF($P135<>"",$P135,IF(AND(ISNUMBER($K135),ISNUMBER($M135),ISNUMBER($N135)),IF($O135="Lower is worse",IF($K135<=$N135,"Danger",IF($K135<=$M135,"Alert","OK")),IF($K135>=$N135,"Danger",IF($K135>=$M135,"Alert","OK"))),"Not set"))) -> OK | R135: =IF(OR($Q135="",$Q135="Not set"),"",MATCH($Q135,Lists!$F$2:$F$4,0)-1) -> 0 | U135: =IF(OR($Q135="",$Q135="OK",$Q135="Not set",NOT(ISNUMBER($G135))),"",ROUND($G135*IF($Q135="Danger",Lists!$M$15,Lists!$M$16),0)) | V135: =IF($U135="","",IF(OR($Q135="Danger",$U135>=Lists!$M$10),"P1",IF($U135>=Lists!$M$11,"P2","P3"))) | W135: =IF(OR($V135="",$B135=""),"",$B135+INDEX(Lists!$N$10:$N$12,MATCH($V135,Lists!$L$10:$L$12,0))) | Y135: No action | Z135: DG operator | AC135: =IF(OR($U135="",$B135=""),"",IF($AA135<>"",$AA135-$B135,TODAY()-$B135)) | AD135: =IF($W135="","",IF($Y135="Closed",IF($AA135="","Closed",IF($AA135<=$W135,"Closed on time","Closed late")),IF(TODAY()>$W135,"Overdue","Within time")))
A136: =IF($C136="","","R"&TEXT(ROW()-4,"00000")) -> R00132 | B136: 46081 | C136: 100404 | D136: =IF($C136="","",IFERROR(INDEX(Asset_Register!$C$5:$C$1000,MATCH($C136,Asset_Register!$A$5:$A$1000,0)),"Not in register")) -> Diesel generator Gen 4 | E136: =IF($C136="","",IFERROR(INDEX(Asset_Register!$D$5:$D$1000,MATCH($C136,Asset_Register!$A$5:$A$1000,0)),"Not in register")) -> Power plant | F136: =IF($C136="","",IFERROR(INDEX(Asset_Register!$R$5:$R$1000,MATCH($C136,Asset_Register!$A$5:$A$1000,0)),"Not in register")) -> A | G136: =IF($C136="","",IFERROR(INDEX(Asset_Register!$Q$5:$Q$1000,MATCH($C136,Asset_Register!$A$5:$A$1000,0)),"Not in register")) -> 92 | H136: DG checklist | I136: DG checks | J136: Lube oil pressure at rated load | K136: 4 | L136: bar | M136: 3.5 | N136: 2.5 | O136: Lower is worse | Q136: =IF($C136="","",IF($P136<>"",$P136,IF(AND(ISNUMBER($K136),ISNUMBER($M136),ISNUMBER($N136)),IF($O136="Lower is worse",IF($K136<=$N136,"Danger",IF($K136<=$M136,"Alert","OK")),IF($K136>=$N136,"Danger",IF($K136>=$M136,"Alert","OK"))),"Not set"))) -> OK | R136: =IF(OR($Q136="",$Q136="Not set"),"",MATCH($Q136,Lists!$F$2:$F$4,0)-1) -> 0 | U136: =IF(OR($Q136="",$Q136="OK",$Q136="Not set",NOT(ISNUMBER($G136))),"",ROUND($G136*IF($Q136="Danger",Lists!$M$15,Lists!$M$16),0)) | V136: =IF($U136="","",IF(OR($Q136="Danger",$U136>=Lists!$M$10),"P1",IF($U136>=Lists!$M$11,"P2","P3"))) | W136: =IF(OR($V136="",$B136=""),"",$B136+INDEX(Lists!$N$10:$N$12,MATCH($V136,Lists!$L$10:$L$12,0))) | Y136: No action | Z136: DG operator | AC136: =IF(OR($U136="",$B136=""),"",IF($AA136<>"",$AA136-$B136,TODAY()-$B136)) | AD136: =IF($W136="","",IF($Y136="Closed",IF($AA136="","Closed",IF($AA136<=$W136,"Closed on time","Closed late")),IF(TODAY()>$W136,"Overdue","Within time")))
A137: =IF($C137="","","R"&TEXT(ROW()-4,"00000")) -> R00133 | B137: 46082 | C137: 100110 | D137: =IF($C137="","",IFERROR(INDEX(Asset_Register!$C$5:$C$1000,MATCH($C137,Asset_Register!$A$5:$A$1000,0)),"Not in register")) -> Molten sulphur pump | E137: =IF($C137="","",IFERROR(INDEX(Asset_Register!$D$5:$D$1000,MATCH($C137,Asset_Register!$A$5:$A$1000,0)),"Not in register")) -> Acid plant | F137: =IF($C137="","",IFERROR(INDEX(Asset_Register!$R$5:$R$1000,MATCH($C137,Asset_Register!$A$5:$A$1000,0)),"Not in register")) -> B | G137: =IF($C137="","",IFERROR(INDEX(Asset_Register!$Q$5:$Q$1000,MATCH($C137,Asset_Register!$A$5:$A$1000,0)),"Not in register")) -> 61 | H137: Vibration & visual route | I137: Vibration | J137: Overall velocity (max point) | K137: 2.7 | L137: mm/s | M137: 4.5 | N137: 7.1 | O137: Higher is worse | Q137: =IF($C137="","",IF($P137<>"",$P137,IF(AND(ISNUMBER($K137),ISNUMBER($M137),ISNUMBER($N137)),IF($O137="Lower is worse",IF($K137<=$N137,"Danger",IF($K137<=$M137,"Alert","OK")),IF($K137>=$N137,"Danger",IF($K137>=$M137,"Alert","OK"))),"Not set"))) -> OK | R137: =IF(OR($Q137="",$Q137="Not set"),"",MATCH($Q137,Lists!$F$2:$F$4,0)-1) -> 0 | U137: =IF(OR($Q137="",$Q137="OK",$Q137="Not set",NOT(ISNUMBER($G137))),"",ROUND($G137*IF($Q137="Danger",Lists!$M$15,Lists!$M$16),0)) | V137: =IF($U137="","",IF(OR($Q137="Danger",$U137>=Lists!$M$10),"P1",IF($U137>=Lists!$M$11,"P2","P3"))) | W137: =IF(OR($V137="",$B137=""),"",$B137+INDEX(Lists!$N$10:$N$12,MATCH($V137,Lists!$L$10:$L$12,0))) | Y137: No action | Z137: RCM Specialist | AC137: =IF(OR($U137="",$B137=""),"",IF($AA137<>"",$AA137-$B137,TODAY()-$B137)) | AD137: =IF($W137="","",IF($Y137="Closed",IF($AA137="","Closed",IF($AA137<=$W137,"Closed on time","Closed late")),IF(TODAY()>$W137,"Overdue","Within time")))
A138: =IF($C138="","","R"&TEXT(ROW()-4,"00000")) -> R00134 | B138: 46082 | C138: 100115 | D138: =IF($C138="","",IFERROR(INDEX(Asset_Register!$C$5:$C$1000,MATCH($C138,Asset_Register!$A$5:$A$1000,0)),"Not in register")) -> Instrument air receiver | E138: =IF($C138="","",IFERROR(INDEX(Asset_Register!$D$5:$D$1000,MATCH($C138,Asset_Register!$A$5:$A$1000,0)),"Not in register")) -> Acid plant | F138: =IF($C138="","",IFERROR(INDEX(Asset_Register!$R$5:$R$1000,MATCH($C138,Asset_Register!$A$5:$A$1000,0)),"Not in register")) -> B | G138: =IF($C138="","",IFERROR(INDEX(Asset_Register!$Q$5:$Q$1000,MATCH($C138,Asset_Register!$A$5:$A$1000,0)),"Not in register")) -> 53 | H138: Ultrasonic report | I138: Ultrasonics (airborne) | J138: Leak survey level | K138: 14 | L138: dBµV | M138: 30 | N138: 40 | O138: Higher is worse | Q138: =IF($C138="","",IF($P138<>"",$P138,IF(AND(ISNUMBER($K138),ISNUMBER($M138),ISNUMBER($N138)),IF($O138="Lower is worse",IF($K138<=$N138,"Danger",IF($K138<=$M138,"Alert","OK")),IF($K138>=$N138,"Danger",IF($K138>=$M138,"Alert","OK"))),"Not set"))) -> OK | R138: =IF(OR($Q138="",$Q138="Not set"),"",MATCH($Q138,Lists!$F$2:$F$4,0)-1) -> 0 | U138: =IF(OR($Q138="",$Q138="OK",$Q138="Not set",NOT(ISNUMBER($G138))),"",ROUND($G138*IF($Q138="Danger",Lists!$M$15,Lists!$M$16),0)) | V138: =IF($U138="","",IF(OR($Q138="Danger",$U138>=Lists!$M$10),"P1",IF($U138>=Lists!$M$11,"P2","P3"))) | W138: =IF(OR($V138="",$B138=""),"",$B138+INDEX(Lists!$N$10:$N$12,MATCH($V138,Lists!$L$10:$L$12,0))) | Y138: No action | Z138: RCM Specialist | AC138: =IF(OR($U138="",$B138=""),"",IF($AA138<>"",$AA138-$B138,TODAY()-$B138)) | AD138: =IF($W138="","",IF($Y138="Closed",IF($AA138="","Closed",IF($AA138<=$W138,"Closed on time","Closed late")),IF(TODAY()>$W138,"Overdue","Within time")))
A139: =IF($C139="","","R"&TEXT(ROW()-4,"00000")) -> R00135 | B139: 46083 | C139: 100108 | D139: =IF($C139="","",IFERROR(INDEX(Asset_Register!$C$5:$C$1000,MATCH($C139,Asset_Register!$A$5:$A$1000,0)),"Not in register")) -> Boiler feed water pump A | E139: =IF($C139="","",IFERROR(INDEX(Asset_Register!$D$5:$D$1000,MATCH($C139,Asset_Register!$A$5:$A$1000,0)),"Not in register")) -> Acid plant | F139: =IF($C139="","",IFERROR(INDEX(Asset_Register!$R$5:$R$1000,MATCH($C139,Asset_Register!$A$5:$A$1000,0)),"Not in register")) -> A | G139: =IF($C139="","",IFERROR(INDEX(Asset_Register!$Q$5:$Q$1000,MATCH($C139,Asset_Register!$A$5:$A$1000,0)),"Not in register")) -> 75 | H139: Vibration & visual route | I139: Vibration | J139: Overall velocity (max point) | K139: 3.1 | L139: mm/s | M139: 4.5 | N139: 7.1 | O139: Higher is worse | Q139: =IF($C139="","",IF($P139<>"",$P139,IF(AND(ISNUMBER($K139),ISNUMBER($M139),ISNUMBER($N139)),IF($O139="Lower is worse",IF($K139<=$N139,"Danger",IF($K139<=$M139,"Alert","OK")),IF($K139>=$N139,"Danger",IF($K139>=$M139,"Alert","OK"))),"Not set"))) -> OK | R139: =IF(OR($Q139="",$Q139="Not set"),"",MATCH($Q139,Lists!$F$2:$F$4,0)-1) -> 0 | U139: =IF(OR($Q139="",$Q139="OK",$Q139="Not set",NOT(ISNUMBER($G139))),"",ROUND($G139*IF($Q139="Danger",Lists!$M$15,Lists!$M$16),0)) | V139: =IF($U139="","",IF(OR($Q139="Danger",$U139>=Lists!$M$10),"P1",IF($U139>=Lists!$M$11,"P2","P3"))) | W139: =IF(OR($V139="",$B139=""),"",$B139+INDEX(Lists!$N$10:$N$12,MATCH($V139,Lists!$L$10:$L$12,0))) | Y139: No action | Z139: RCM Specialist | AC139: =IF(OR($U139="",$B139=""),"",IF($AA139<>"",$AA139-$B139,TODAY()-$B139)) | AD139: =IF($W139="","",IF($Y139="Closed",IF($AA139="","Closed",IF($AA139<=$W139,"Closed on time","Closed late")),IF(TODAY()>$W139,"Overdue","Within time")))
A140: =IF($C140="","","R"&TEXT(ROW()-4,"00000")) -> R00136 | B140: 46083 | C140: 100111 | D140: =IF($C140="","",IFERROR(INDEX(Asset_Register!$C$5:$C$1000,MATCH($C140,Asset_Register!$A$5:$A$1000,0)),"Not in register")) -> Sulphur melter agitator | E140: =IF($C140="","",IFERROR(INDEX(Asset_Register!$D$5:$D$1000,MATCH($C140,Asset_Register!$A$5:$A$1000,0)),"Not in register")) -> Acid plant | F140: =IF($C140="","",IFERROR(INDEX(Asset_Register!$R$5:$R$1000,MATCH($C140,Asset_Register!$A$5:$A$1000,0)),"Not in register")) -> C | G140: =IF($C140="","",IFERROR(INDEX(Asset_Register!$Q$5:$Q$1000,MATCH($C140,Asset_Register!$A$5:$A$1000,0)),"Not in register")) -> 43 | H140: Vibration & visual route | I140: Vibration | J140: Overall velocity (max point) | K140: 1.6 | L140: mm/s | M140: 4.5 | N140: 7.1 | O140: Higher is worse | Q140: =IF($C140="","",IF($P140<>"",$P140,IF(AND(ISNUMBER($K140),ISNUMBER($M140),ISNUMBER($N140)),IF($O140="Lower is worse",IF($K140<=$N140,"Danger",IF($K140<=$M140,"Alert","OK")),IF($K140>=$N140,"Danger",IF($K140>=$M140,"Alert","OK"))),"Not set"))) -> OK | R140: =IF(OR($Q140="",$Q140="Not set"),"",MATCH($Q140,Lists!$F$2:$F$4,0)-1) -> 0 | U140: =IF(OR($Q140="",$Q140="OK",$Q140="Not set",NOT(ISNUMBER($G140))),"",ROUND($G140*IF($Q140="Danger",Lists!$M$15,Lists!$M$16),0)) | V140: =IF($U140="","",IF(OR($Q140="Danger",$U140>=Lists!$M$10),"P1",IF($U140>=Lists!$M$11,"P2","P3"))) | W140: =IF(OR($V140="",$B140=""),"",$B140+INDEX(Lists!$N$10:$N$12,MATCH($V140,Lists!$L$10:$L$12,0))) | Y140: No action | Z140: RCM Specialist | AC140: =IF(OR($U140="",$B140=""),"",IF($AA140<>"",$AA140-$B140,TODAY()-$B140)) | AD140: =IF($W140="","",IF($Y140="Closed",IF($AA140="","Closed",IF($AA140<=$W140,"Closed on time","Closed late")),IF(TODAY()>$W140,"Overdue","Within time")))
A141: =IF($C141="","","R"&TEXT(ROW()-4,"00000")) -> R00137 | B141: 46086 | C141: 100109 | D141: =IF($C141="","",IFERROR(INDEX(Asset_Register!$C$5:$C$1000,MATCH($C141,Asset_Register!$A$5:$A$1000,0)),"Not in register")) -> Boiler feed water pump B | E141: =IF($C141="","",IFERROR(INDEX(Asset_Register!$D$5:$D$1000,MATCH($C141,Asset_Register!$A$5:$A$1000,0)),"Not in register")) -> Acid plant | F141: =IF($C141="","",IFERROR(INDEX(Asset_Register!$R$5:$R$1000,MATCH($C141,Asset_Register!$A$5:$A$1000,0)),"Not in register")) -> A | G141: =IF($C141="","",IFERROR(INDEX(Asset_Register!$Q$5:$Q$1000,MATCH($C141,Asset_Register!$A$5:$A$1000,0)),"Not in register")) -> 71 | H141: Vibration & visual route | I141: Vibration | J141: Overall velocity (max point) | K141: 2 | L141: mm/s | M141: 4.5 | N141: 7.1 | O141: Higher is worse | Q141: =IF($C141="","",IF($P141<>"",$P141,IF(AND(ISNUMBER($K141),ISNUMBER($M141),ISNUMBER($N141)),IF($O141="Lower is worse",IF($K141<=$N141,"Danger",IF($K141<=$M141,"Alert","OK")),IF($K141>=$N141,"Danger",IF($K141>=$M141,"Alert","OK"))),"Not set"))) -> OK | R141: =IF(OR($Q141="",$Q141="Not set"),"",MATCH($Q141,Lists!$F$2:$F$4,0)-1) -> 0 | U141: =IF(OR($Q141="",$Q141="OK",$Q141="Not set",NOT(ISNUMBER($G141))),"",ROUND($G141*IF($Q141="Danger",Lists!$M$15,Lists!$M$16),0)) | V141: =IF($U141="","",IF(OR($Q141="Danger",$U141>=Lists!$M$10),"P1",IF($U141>=Lists!$M$11,"P2","P3"))) | W141: =IF(OR($V141="",$B141=""),"",$B141+INDEX(Lists!$N$10:$N$12,MATCH($V141,Lists!$L$10:$L$12,0))) | Y141: No action | Z141: RCM Specialist | AC141: =IF(OR($U141="",$B141=""),"",IF($AA141<>"",$AA141-$B141,TODAY()-$B141)) | AD141: =IF($W141="","",IF($Y141="Closed",IF($AA141="","Closed",IF($AA141<=$W141,"Closed on time","Closed late")),IF(TODAY()>$W141,"Overdue","Within time")))
A142: =IF($C142="","","R"&TEXT(ROW()-4,"00000")) -> R00138 | B142: 46086 | C142: 100108 | D142: =IF($C142="","",IFERROR(INDEX(Asset_Register!$C$5:$C$1000,MATCH($C142,Asset_Register!$A$5:$A$1000,0)),"Not in register")) -> Boiler feed water pump A | E142: =IF($C142="","",IFERROR(INDEX(Asset_Register!$D$5:$D$1000,MATCH($C142,Asset_Register!$A$5:$A$1000,0)),"Not in register")) -> Acid plant | F142: =IF($C142="","",IFERROR(INDEX(Asset_Register!$R$5:$R$1000,MATCH($C142,Asset_Register!$A$5:$A$1000,0)),"Not in register")) -> A | G142: =IF($C142="","",IFERROR(INDEX(Asset_Register!$Q$5:$Q$1000,MATCH($C142,Asset_Register!$A$5:$A$1000,0)),"Not in register")) -> 75 | H142: Oil analysis | I142: Lubrication / oil | J142: Water in bearing oil | K142: 300 | L142: ppm | M142: 1000 | N142: 2000 | O142: Higher is worse | Q142: =IF($C142="","",IF($P142<>"",$P142,IF(AND(ISNUMBER($K142),ISNUMBER($M142),ISNUMBER($N142)),IF($O142="Lower is worse",IF($K142<=$N142,"Danger",IF($K142<=$M142,"Alert","OK")),IF($K142>=$N142,"Danger",IF($K142>=$M142,"Alert","OK"))),"Not set"))) -> OK | R142: =IF(OR($Q142="",$Q142="Not set"),"",MATCH($Q142,Lists!$F$2:$F$4,0)-1) -> 0 | U142: =IF(OR($Q142="",$Q142="OK",$Q142="Not set",NOT(ISNUMBER($G142))),"",ROUND($G142*IF($Q142="Danger",Lists!$M$15,Lists!$M$16),0)) | V142: =IF($U142="","",IF(OR($Q142="Danger",$U142>=Lists!$M$10),"P1",IF($U142>=Lists!$M$11,"P2","P3"))) | W142: =IF(OR($V142="",$B142=""),"",$B142+INDEX(Lists!$N$10:$N$12,MATCH($V142,Lists!$L$10:$L$12,0))) | Y142: No action | Z142: RCM Specialist | AC142: =IF(OR($U142="",$B142=""),"",IF($AA142<>"",$AA142-$B142,TODAY()-$B142)) | AD142: =IF($W142="","",IF($Y142="Closed",IF($AA142="","Closed",IF($AA142<=$W142,"Closed on time","Closed late")),IF(TODAY()>$W142,"Overdue","Within time")))
A143: =IF($C143="","","R"&TEXT(ROW()-4,"00000")) -> R00139 | B143: 46089 | C143: 100101 | D143: =IF($C143="","",IFERROR(INDEX(Asset_Register!$C$5:$C$1000,MATCH($C143,Asset_Register!$A$5:$A$1000,0)),"Not in register")) -> Sulphur furnace | E143: =IF($C143="","",IFERROR(INDEX(Asset_Register!$D$5:$D$1000,MATCH($C143,Asset_Register!$A$5:$A$1000,0)),"Not in register")) -> Acid plant | F143: =IF($C143="","",IFERROR(INDEX(Asset_Register!$R$5:$R$1000,MATCH($C143,Asset_Register!$A$5:$A$1000,0)),"Not in register")) -> A | G143: =IF($C143="","",IFERROR(INDEX(Asset_Register!$Q$5:$Q$1000,MATCH($C143,Asset_Register!$A$5:$A$1000,0)),"Not in register")) -> 94 | H143: IR survey | I143: Infrared | J143: Burner-end shell temperature | K143: 238 | L143: °C | M143: 280 | N143: 320 | O143: Higher is worse | Q143: =IF($C143="","",IF($P143<>"",$P143,IF(AND(ISNUMBER($K143),ISNUMBER($M143),ISNUMBER($N143)),IF($O143="Lower is worse",IF($K143<=$N143,"Danger",IF($K143<=$M143,"Alert","OK")),IF($K143>=$N143,"Danger",IF($K143>=$M143,"Alert","OK"))),"Not set"))) -> OK | R143: =IF(OR($Q143="",$Q143="Not set"),"",MATCH($Q143,Lists!$F$2:$F$4,0)-1) -> 0 | U143: =IF(OR($Q143="",$Q143="OK",$Q143="Not set",NOT(ISNUMBER($G143))),"",ROUND($G143*IF($Q143="Danger",Lists!$M$15,Lists!$M$16),0)) | V143: =IF($U143="","",IF(OR($Q143="Danger",$U143>=Lists!$M$10),"P1",IF($U143>=Lists!$M$11,"P2","P3"))) | W143: =IF(OR($V143="",$B143=""),"",$B143+INDEX(Lists!$N$10:$N$12,MATCH($V143,Lists!$L$10:$L$12,0))) | Y143: No action | Z143: RCM Specialist | AC143: =IF(OR($U143="",$B143=""),"",IF($AA143<>"",$AA143-$B143,TODAY()-$B143)) | AD143: =IF($W143="","",IF($Y143="Closed",IF($AA143="","Closed",IF($AA143<=$W143,"Closed on time","Closed late")),IF(TODAY()>$W143,"Overdue","Within time")))
... A152: =IF($C152="","","R"&TEXT(ROW()-4,"00000")) -> R00148 | B152: 46101 | C152: 100104 | D152: =IF($C152="","",IFERROR(INDEX(Asset_Register!$C$5:$C$1000,MATCH($C152,Asset_Register!$A$5:$A$1000,0)),"Not in register")) -> SO2 converter | E152: =IF($C152="","",IFERROR(INDEX(Asset_Register!$D$5:$D$1000,MATCH($C152,Asset_Register!$A$5:$A$1000,0)),"Not in register")) -> Acid plant | F152: =IF($C152="","",IFERROR(INDEX(Asset_Register!$R$5:$R$1000,MATCH($C152,Asset_Register!$A$5:$A$1000,0)),"Not in register")) -> A | G152: =IF($C152="","",IFERROR(INDEX(Asset_Register!$Q$5:$Q$1000,MATCH($C152,Asset_Register!$A$5:$A$1000,0)),"Not in register")) -> 86 | H152: IR survey | I152: Infrared | J152: Bed 3 outlet flange dT above baseline | K152: 9 | L152: °C | M152: 30 | N152: 60 | O152: Higher is worse | Q152: =IF($C152="","",IF($P152<>"",$P152,IF(AND(ISNUMBER($K152),ISNUMBER($M152),ISNUMBER($N152)),IF($O152="Lower is worse",IF($K152<=$N152,"Danger",IF($K152<=$M152,"Alert","OK")),IF($K152>=$N152,"Danger",IF($K152>=$M152,"Alert","OK"))),"Not set"))) -> OK | R152: =IF(OR($Q152="",$Q152="Not set"),"",MATCH($Q152,Lists!$F$2:$F$4,0)-1) -> 0 | U152: =IF(OR($Q152="",$Q152="OK",$Q152="Not set",NOT(ISNUMBER($G152))),"",ROUND($G152*IF($Q152="Danger",Lists!$M$15,Lists!$M$16),0)) | V152: =IF($U152="","",IF(OR($Q152="Danger",$U152>=Lists!$M$10),"P1",IF($U152>=Lists!$M$11,"P2","P3"))) | W152: =IF(OR($V152="",$B152=""),"",$B152+INDEX(Lists!$N$10:$N$12,MATCH($V152,Lists!$L$10:$L$12,0))) | Y152: No action | Z152: RCM Specialist | AC152: =IF(OR($U152="",$B152=""),"",IF($AA152<>"",$AA152-$B152,TODAY()-$B152)) | AD152: =IF($W152="","",IF($Y152="Closed",IF($AA152="","Closed",IF($AA152<=$W152,"Closed on time","Closed late")),IF(TODAY()>$W152,"Overdue","Within time")))
A153: =IF($C153="","","R"&TEXT(ROW()-4,"00000")) -> R00149 | B153: 46101 | C153: 100110 | D153: =IF($C153="","",IFERROR(INDEX(Asset_Register!$C$5:$C$1000,MATCH($C153,Asset_Register!$A$5:$A$1000,0)),"Not in register")) -> Molten sulphur pump | E153: =IF($C153="","",IFERROR(INDEX(Asset_Register!$D$5:$D$1000,MATCH($C153,Asset_Register!$A$5:$A$1000,0)),"Not in register")) -> Acid plant | F153: =IF($C153="","",IFERROR(INDEX(Asset_Register!$R$5:$R$1000,MATCH($C153,Asset_Register!$A$5:$A$1000,0)),"Not in register")) -> B | G153: =IF($C153="","",IFERROR(INDEX(Asset_Register!$Q$5:$Q$1000,MATCH($C153,Asset_Register!$A$5:$A$1000,0)),"Not in register")) -> 61 | H153: IR survey | I153: Infrared | J153: Motor DE bearing temperature | P153: Alert | Q153: =IF($C153="","",IF($P153<>"",$P153,IF(AND(ISNUMBER($K153),ISNUMBER($M153),ISNUMBER($N153)),IF($O153="Lower is worse",IF($K153<=$N153,"Danger",IF($K153<=$M153,"Alert","OK")),IF($K153>=$N153,"Danger",IF($K153>=$M153,"Alert","OK"))),"Not set"))) -> Alert | R153: =IF(OR($Q153="",$Q153="Not set"),"",MATCH($Q153,Lists!$F$2:$F$4,0)-1) -> 1 | S153: Motor DE bearing 25 °C above NDE | T153: Replace motor bearing in planned window | U153: =IF(OR($Q153="",$Q153="OK",$Q153="Not set",NOT(ISNUMBER($G153))),"",ROUND($G153*IF($Q153="Danger",Lists!$M$15,Lists!$M$16),0)) -> 37 | V153: =IF($U153="","",IF(OR($Q153="Danger",$U153>=Lists!$M$10),"P1",IF($U153>=Lists!$M$11,"P2","P3"))) -> P3 | W153: =IF(OR($V153="",$B153=""),"",$B153+INDEX(Lists!$N$10:$N$12,MATCH($V153,Lists!$L$10:$L$12,0))) -> 46161 | X153: 242980 | Y153: Closed | Z153: RCM Specialist | AA153: 46122 | AB153: Electrical Supervisor | AC153: =IF(OR($U153="",$B153=""),"",IF($AA153<>"",$AA153-$B153,TODAY()-$B153)) -> 21 | AD153: =IF($W153="","",IF($Y153="Closed",IF($AA153="","Closed",IF($AA153<=$W153,"Closed on time","Closed late")),IF(TODAY()>$W153,"Overdue","Within time"))) -> Closed on time
A154: =IF($C154="","","R"&TEXT(ROW()-4,"00000")) -> R00150 | B154: 46103 | C154: 100105 | D154: =IF($C154="","",IFERROR(INDEX(Asset_Register!$C$5:$C$1000,MATCH($C154,Asset_Register!$A$5:$A$1000,0)),"Not in register")) -> Drying tower acid pump | E154: =IF($C154="","",IFERROR(INDEX(Asset_Register!$D$5:$D$1000,MATCH($C154,Asset_Register!$A$5:$A$1000,0)),"Not in register")) -> Acid plant | F154: =IF($C154="","",IFERROR(INDEX(Asset_Register!$R$5:$R$1000,MATCH($C154,Asset_Register!$A$5:$A$1000,0)),"Not in register")) -> A | G154: =IF($C154="","",IFERROR(INDEX(Asset_Register!$Q$5:$Q$1000,MATCH($C154,Asset_Register!$A$5:$A$1000,0)),"Not in register")) -> 74 | H154: Vibration & visual route | I154: Vibration | J154: Overall velocity (max point) | K154: 4.4 | L154: mm/s | M154: 4.5 | N154: 7.1 | O154: Higher is worse | Q154: =IF($C154="","",IF($P154<>"",$P154,IF(AND(ISNUMBER($K154),ISNUMBER($M154),ISNUMBER($N154)),IF($O154="Lower is worse",IF($K154<=$N154,"Danger",IF($K154<=$M154,"Alert","OK")),IF($K154>=$N154,"Danger",IF($K154>=$M154,"Alert","OK"))),"Not set"))) -> OK | R154: =IF(OR($Q154="",$Q154="Not set"),"",MATCH($Q154,Lists!$F$2:$F$4,0)-1) -> 0 | U154: =IF(OR($Q154="",$Q154="OK",$Q154="Not set",NOT(ISNUMBER($G154))),"",ROUND($G154*IF($Q154="Danger",Lists!$M$15,Lists!$M$16),0)) | V154: =IF($U154="","",IF(OR($Q154="Danger",$U154>=Lists!$M$10),"P1",IF($U154>=Lists!$M$11,"P2","P3"))) | W154: =IF(OR($V154="",$B154=""),"",$B154+INDEX(Lists!$N$10:$N$12,MATCH($V154,Lists!$L$10:$L$12,0))) | Y154: No action | Z154: RCM Specialist | AC154: =IF(OR($U154="",$B154=""),"",IF($AA154<>"",$AA154-$B154,TODAY()-$B154)) | AD154: =IF($W154="","",IF($Y154="Closed",IF($AA154="","Closed",IF($AA154<=$W154,"Closed on time","Closed late")),IF(TODAY()>$W154,"Overdue","Within time")))
A155: =IF($C155="","","R"&TEXT(ROW()-4,"00000")) -> R00151 | B155: 46103 | C155: 100106 | D155: =IF($C155="","",IFERROR(INDEX(Asset_Register!$C$5:$C$1000,MATCH($C155,Asset_Register!$A$5:$A$1000,0)),"Not in register")) -> Interpass tower acid pump | E155: =IF($C155="","",IFERROR(INDEX(Asset_Register!$D$5:$D$1000,MATCH($C155,Asset_Register!$A$5:$A$1000,0)),"Not in register")) -> Acid plant | F155: =IF($C155="","",IFERROR(INDEX(Asset_Register!$R$5:$R$1000,MATCH($C155,Asset_Register!$A$5:$A$1000,0)),"Not in register")) -> A | G155: =IF($C155="","",IFERROR(INDEX(Asset_Register!$Q$5:$Q$1000,MATCH($C155,Asset_Register!$A$5:$A$1000,0)),"Not in register")) -> 76 | H155: Vibration & visual route | I155: Vibration | J155: Overall velocity (max point) | K155: 2.1 | L155: mm/s | M155: 4.5 | N155: 7.1 | O155: Higher is worse | Q155: =IF($C155="","",IF($P155<>"",$P155,IF(AND(ISNUMBER($K155),ISNUMBER($M155),ISNUMBER($N155)),IF($O155="Lower is worse",IF($K155<=$N155,"Danger",IF($K155<=$M155,"Alert","OK")),IF($K155>=$N155,"Danger",IF($K155>=$M155,"Alert","OK"))),"Not set"))) -> OK | R155: =IF(OR($Q155="",$Q155="Not set"),"",MATCH($Q155,Lists!$F$2:$F$4,0)-1) -> 0 | U155: =IF(OR($Q155="",$Q155="OK",$Q155="Not set",NOT(ISNUMBER($G155))),"",ROUND($G155*IF($Q155="Danger",Lists!$M$15,Lists!$M$16),0)) | V155: =IF($U155="","",IF(OR($Q155="Danger",$U155>=Lists!$M$10),"P1",IF($U155>=Lists!$M$11,"P2","P3"))) | W155: =IF(OR($V155="",$B155=""),"",$B155+INDEX(Lists!$N$10:$N$12,MATCH($V155,Lists!$L$10:$L$12,0))) | Y155: No action | Z155: RCM Specialist | AC155: =IF(OR($U155="",$B155=""),"",IF($AA155<>"",$AA155-$B155,TODAY()-$B155)) | AD155: =IF($W155="","",IF($Y155="Closed",IF($AA155="","Closed",IF($AA155<=$W155,"Closed on time","Closed late")),IF(TODAY()>$W155,"Overdue","Within time")))
A156: =IF($C156="","","R"&TEXT(ROW()-4,"00000")) -> R00152 | B156: 46103 | C156: 100105 | D156: =IF($C156="","",IFERROR(INDEX(Asset_Register!$C$5:$C$1000,MATCH($C156,Asset_Register!$A$5:$A$1000,0)),"Not in register")) -> Drying tower acid pump | E156: =IF($C156="","",IFERROR(INDEX(Asset_Register!$D$5:$D$1000,MATCH($C156,Asset_Register!$A$5:$A$1000,0)),"Not in register")) -> Acid plant | F156: =IF($C156="","",IFERROR(INDEX(Asset_Register!$R$5:$R$1000,MATCH($C156,Asset_Register!$A$5:$A$1000,0)),"Not in register")) -> A | G156: =IF($C156="","",IFERROR(INDEX(Asset_Register!$Q$5:$Q$1000,MATCH($C156,Asset_Register!$A$5:$A$1000,0)),"Not in register")) -> 74 | H156: Oil analysis | I156: Lubrication / oil | J156: Iron (Fe) | K156: 30 | L156: ppm | M156: 50 | N156: 100 | O156: Higher is worse | Q156: =IF($C156="","",IF($P156<>"",$P156,IF(AND(ISNUMBER($K156),ISNUMBER($M156),ISNUMBER($N156)),IF($O156="Lower is worse",IF($K156<=$N156,"Danger",IF($K156<=$M156,"Alert","OK")),IF($K156>=$N156,"Danger",IF($K156>=$M156,"Alert","OK"))),"Not set"))) -> OK | R156: =IF(OR($Q156="",$Q156="Not set"),"",MATCH($Q156,Lists!$F$2:$F$4,0)-1) -> 0 | U156: =IF(OR($Q156="",$Q156="OK",$Q156="Not set",NOT(ISNUMBER($G156))),"",ROUND($G156*IF($Q156="Danger",Lists!$M$15,Lists!$M$16),0)) | V156: =IF($U156="","",IF(OR($Q156="Danger",$U156>=Lists!$M$10),"P1",IF($U156>=Lists!$M$11,"P2","P3"))) | W156: =IF(OR($V156="",$B156=""),"",$B156+INDEX(Lists!$N$10:$N$12,MATCH($V156,Lists!$L$10:$L$12,0))) | Y156: No action | Z156: RCM Specialist | AC156: =IF(OR($U156="",$B156=""),"",IF($AA156<>"",$AA156-$B156,TODAY()-$B156)) | AD156: =IF($W156="","",IF($Y156="Closed",IF($AA156="","Closed",IF($AA156<=$W156,"Closed on time","Closed late")),IF(TODAY()>$W156,"Overdue","Within time")))
A157: =IF($C157="","","R"&TEXT(ROW()-4,"00000")) -> R00153 | B157: 46105 | C157: 100301 | D157: =IF($C157="","",IFERROR(INDEX(Asset_Register!$C$5:$C$1000,MATCH($C157,Asset_Register!$A$5:$A$1000,0)),"Not in register")) -> Transformer TX-01 | E157: =IF($C157="","",IFERROR(INDEX(Asset_Register!$D$5:$D$1000,MATCH($C157,Asset_Register!$A$5:$A$1000,0)),"Not in register")) -> Substation | F157: =IF($C157="","",IFERROR(INDEX(Asset_Register!$R$5:$R$1000,MATCH($C157,Asset_Register!$A$5:$A$1000,0)),"Not in register")) -> A | G157: =IF($C157="","",IFERROR(INDEX(Asset_Register!$Q$5:$Q$1000,MATCH($C157,Asset_Register!$A$5:$A$1000,0)),"Not in register")) -> 86 | H157: Substation inspection | I157: Infrared | J157: LV bushing connection dT | K157: 6 | L157: °C | M157: 4 | N157: 15 | O157: Higher is worse | Q157: =IF($C157="","",IF($P157<>"",$P157,IF(AND(ISNUMBER($K157),ISNUMBER($M157),ISNUMBER($N157)),IF($O157="Lower is worse",IF($K157<=$N157,"Danger",IF($K157<=$M157,"Alert","OK")),IF($K157>=$N157,"Danger",IF($K157>=$M157,"Alert","OK"))),"Not set"))) -> Alert | R157: =IF(OR($Q157="",$Q157="Not set"),"",MATCH($Q157,Lists!$F$2:$F$4,0)-1) -> 1 | U157: =IF(OR($Q157="",$Q157="OK",$Q157="Not set",NOT(ISNUMBER($G157))),"",ROUND($G157*IF($Q157="Danger",Lists!$M$15,Lists!$M$16),0)) -> 52 | V157: =IF($U157="","",IF(OR($Q157="Danger",$U157>=Lists!$M$10),"P1",IF($U157>=Lists!$M$11,"P2","P3"))) -> P2 | W157: =IF(OR($V157="",$B157=""),"",$B157+INDEX(Lists!$N$10:$N$12,MATCH($V157,Lists!$L$10:$L$12,0))) -> 46135 | Y157: No action | Z157: Electrician | AC157: =IF(OR($U157="",$B157=""),"",IF($AA157<>"",$AA157-$B157,TODAY()-$B157)) -> 195 | AD157: =IF($W157="","",IF($Y157="Closed",IF($AA157="","Closed",IF($AA157<=$W157,"Closed on time","Closed late")),IF(TODAY()>$W157,"Overdue","Within time"))) -> Overdue
A158: =IF($C158="","","R"&TEXT(ROW()-4,"00000")) -> R00154 | B158: 46105 | C158: 100302 | D158: =IF($C158="","",IFERROR(INDEX(Asset_Register!$C$5:$C$1000,MATCH($C158,Asset_Register!$A$5:$A$1000,0)),"Not in register")) -> Acid plant MCC | E158: =IF($C158="","",IFERROR(INDEX(Asset_Register!$D$5:$D$1000,MATCH($C158,Asset_Register!$A$5:$A$1000,0)),"Not in register")) -> Substation | F158: =IF($C158="","",IFERROR(INDEX(Asset_Register!$R$5:$R$1000,MATCH($C158,Asset_Register!$A$5:$A$1000,0)),"Not in register")) -> A | G158: =IF($C158="","",IFERROR(INDEX(Asset_Register!$Q$5:$Q$1000,MATCH($C158,Asset_Register!$A$5:$A$1000,0)),"Not in register")) -> 82 | H158: IR survey | I158: Infrared | J158: Hottest termination dT | K158: 3 | L158: °C | M158: 4 | N158: 15 | O158: Higher is worse | Q158: =IF($C158="","",IF($P158<>"",$P158,IF(AND(ISNUMBER($K158),ISNUMBER($M158),ISNUMBER($N158)),IF($O158="Lower is worse",IF($K158<=$N158,"Danger",IF($K158<=$M158,"Alert","OK")),IF($K158>=$N158,"Danger",IF($K158>=$M158,"Alert","OK"))),"Not set"))) -> OK | R158: =IF(OR($Q158="",$Q158="Not set"),"",MATCH($Q158,Lists!$F$2:$F$4,0)-1) -> 0 | U158: =IF(OR($Q158="",$Q158="OK",$Q158="Not set",NOT(ISNUMBER($G158))),"",ROUND($G158*IF($Q158="Danger",Lists!$M$15,Lists!$M$16),0)) | V158: =IF($U158="","",IF(OR($Q158="Danger",$U158>=Lists!$M$10),"P1",IF($U158>=Lists!$M$11,"P2","P3"))) | W158: =IF(OR($V158="",$B158=""),"",$B158+INDEX(Lists!$N$10:$N$12,MATCH($V158,Lists!$L$10:$L$12,0))) | Y158: No action | Z158: RCM Specialist | AC158: =IF(OR($U158="",$B158=""),"",IF($AA158<>"",$AA158-$B158,TODAY()-$B158)) | AD158: =IF($W158="","",IF($Y158="Closed",IF($AA158="","Closed",IF($AA158<=$W158,"Closed on time","Closed late")),IF(TODAY()>$W158,"Overdue","Within time")))
A159: =IF($C159="","","R"&TEXT(ROW()-4,"00000")) -> R00155 | B159: 46109 | C159: 100401 | D159: =IF($C159="","",IFERROR(INDEX(Asset_Register!$C$5:$C$1000,MATCH($C159,Asset_Register!$A$5:$A$1000,0)),"Not in register")) -> Diesel generator Gen 1 | E159: =IF($C159="","",IFERROR(INDEX(Asset_Register!$D$5:$D$1000,MATCH($C159,Asset_Register!$A$5:$A$1000,0)),"Not in register")) -> Power plant | F159: =IF($C159="","",IFERROR(INDEX(Asset_Register!$R$5:$R$1000,MATCH($C159,Asset_Register!$A$5:$A$1000,0)),"Not in register")) -> A | G159: =IF($C159="","",IFERROR(INDEX(Asset_Register!$Q$5:$Q$1000,MATCH($C159,Asset_Register!$A$5:$A$1000,0)),"Not in register")) -> 83 | H159: DG checklist | I159: DG checks | J159: Turbo outlet exhaust temperature | K159: 490 | L159: °C | M159: 520 | N159: 580 | O159: Higher is worse | Q159: =IF($C159="","",IF($P159<>"",$P159,IF(AND(ISNUMBER($K159),ISNUMBER($M159),ISNUMBER($N159)),IF($O159="Lower is worse",IF($K159<=$N159,"Danger",IF($K159<=$M159,"Alert","OK")),IF($K159>=$N159,"Danger",IF($K159>=$M159,"Alert","OK"))),"Not set"))) -> OK | R159: =IF(OR($Q159="",$Q159="Not set"),"",MATCH($Q159,Lists!$F$2:$F$4,0)-1) -> 0 | U159: =IF(OR($Q159="",$Q159="OK",$Q159="Not set",NOT(ISNUMBER($G159))),"",ROUND($G159*IF($Q159="Danger",Lists!$M$15,Lists!$M$16),0)) | V159: =IF($U159="","",IF(OR($Q159="Danger",$U159>=Lists!$M$10),"P1",IF($U159>=Lists!$M$11,"P2","P3"))) | W159: =IF(OR($V159="",$B159=""),"",$B159+INDEX(Lists!$N$10:$N$12,MATCH($V159,Lists!$L$10:$L$12,0))) | Y159: No action | Z159: DG operator | AC159: =IF(OR($U159="",$B159=""),"",IF($AA159<>"",$AA159-$B159,TODAY()-$B159)) | AD159: =IF($W159="","",IF($Y159="Closed",IF($AA159="","Closed",IF($AA159<=$W159,"Closed on time","Closed late")),IF(TODAY()>$W159,"Overdue","Within time")))
A160: =IF($C160="","","R"&TEXT(ROW()-4,"00000")) -> R00156 | B160: 46109 | C160: 100402 | D160: =IF($C160="","",IFERROR(INDEX(Asset_Register!$C$5:$C$1000,MATCH($C160,Asset_Register!$A$5:$A$1000,0)),"Not in register")) -> Diesel generator Gen 2 | E160: =IF($C160="","",IFERROR(INDEX(Asset_Register!$D$5:$D$1000,MATCH($C160,Asset_Register!$A$5:$A$1000,0)),"Not in register")) -> Power plant | F160: =IF($C160="","",IFERROR(INDEX(Asset_Register!$R$5:$R$1000,MATCH($C160,Asset_Register!$A$5:$A$1000,0)),"Not in register")) -> A | G160: =IF($C160="","",IFERROR(INDEX(Asset_Register!$Q$5:$Q$1000,MATCH($C160,Asset_Register!$A$5:$A$1000,0)),"Not in register")) -> 79 | H160: DG checklist | I160: DG checks | J160: Exhaust temperature spread between cylinders | K160: 23 | L160: °C | M160: 50 | N160: 80 | O160: Higher is worse | Q160: =IF($C160="","",IF($P160<>"",$P160,IF(AND(ISNUMBER($K160),ISNUMBER($M160),ISNUMBER($N160)),IF($O160="Lower is worse",IF($K160<=$N160,"Danger",IF($K160<=$M160,"Alert","OK")),IF($K160>=$N160,"Danger",IF($K160>=$M160,"Alert","OK"))),"Not set"))) -> OK | R160: =IF(OR($Q160="",$Q160="Not set"),"",MATCH($Q160,Lists!$F$2:$F$4,0)-1) -> 0 | U160: =IF(OR($Q160="",$Q160="OK",$Q160="Not set",NOT(ISNUMBER($G160))),"",ROUND($G160*IF($Q160="Danger",Lists!$M$15,Lists!$M$16),0)) | V160: =IF($U160="","",IF(OR($Q160="Danger",$U160>=Lists!$M$10),"P1",IF($U160>=Lists!$M$11,"P2","P3"))) | W160: =IF(OR($V160="",$B160=""),"",$B160+INDEX(Lists!$N$10:$N$12,MATCH($V160,Lists!$L$10:$L$12,0))) | Y160: No action | Z160: DG operator | AC160: =IF(OR($U160="",$B160=""),"",IF($AA160<>"",$AA160-$B160,TODAY()-$B160)) | AD160: =IF($W160="","",IF($Y160="Closed",IF($AA160="","Closed",IF($AA160<=$W160,"Closed on time","Closed late")),IF(TODAY()>$W160,"Overdue","Within time")))
A161: =IF($C161="","","R"&TEXT(ROW()-4,"00000")) -> R00157 | B161: 46109 | C161: 100403 | D161: =IF($C161="","",IFERROR(INDEX(Asset_Register!$C$5:$C$1000,MATCH($C161,Asset_Register!$A$5:$A$1000,0)),"Not in register")) -> Diesel generator Gen 3 | E161: =IF($C161="","",IFERROR(INDEX(Asset_Register!$D$5:$D$1000,MATCH($C161,Asset_Register!$A$5:$A$1000,0)),"Not in register")) -> Power plant | F161: =IF($C161="","",IFERROR(INDEX(Asset_Register!$R$5:$R$1000,MATCH($C161,Asset_Register!$A$5:$A$1000,0)),"Not in register")) -> A | G161: =IF($C161="","",IFERROR(INDEX(Asset_Register!$Q$5:$Q$1000,MATCH($C161,Asset_Register!$A$5:$A$1000,0)),"Not in register")) -> 79 | H161: DG checklist | I161: DG checks | J161: Turbo outlet exhaust temperature | K161: 458 | L161: °C | M161: 520 | N161: 580 | O161: Higher is worse | Q161: =IF($C161="","",IF($P161<>"",$P161,IF(AND(ISNUMBER($K161),ISNUMBER($M161),ISNUMBER($N161)),IF($O161="Lower is worse",IF($K161<=$N161,"Danger",IF($K161<=$M161,"Alert","OK")),IF($K161>=$N161,"Danger",IF($K161>=$M161,"Alert","OK"))),"Not set"))) -> OK | R161: =IF(OR($Q161="",$Q161="Not set"),"",MATCH($Q161,Lists!$F$2:$F$4,0)-1) -> 0 | U161: =IF(OR($Q161="",$Q161="OK",$Q161="Not set",NOT(ISNUMBER($G161))),"",ROUND($G161*IF($Q161="Danger",Lists!$M$15,Lists!$M$16),0)) | V161: =IF($U161="","",IF(OR($Q161="Danger",$U161>=Lists!$M$10),"P1",IF($U161>=Lists!$M$11,"P2","P3"))) | W161: =IF(OR($V161="",$B161=""),"",$B161+INDEX(Lists!$N$10:$N$12,MATCH($V161,Lists!$L$10:$L$12,0))) | Y161: No action | Z161: DG operator | AC161: =IF(OR($U161="",$B161=""),"",IF($AA161<>"",$AA161-$B161,TODAY()-$B161)) | AD161: =IF($W161="","",IF($Y161="Closed",IF($AA161="","Closed",IF($AA161<=$W161,"Closed on time","Closed late")),IF(TODAY()>$W161,"Overdue","Within time")))
A162: =IF($C162="","","R"&TEXT(ROW()-4,"00000")) -> R00158 | B162: 46109 | C162: 100404 | D162: =IF($C162="","",IFERROR(INDEX(Asset_Register!$C$5:$C$1000,MATCH($C162,Asset_Register!$A$5:$A$1000,0)),"Not in register")) -> Diesel generator Gen 4 | E162: =IF($C162="","",IFERROR(INDEX(Asset_Register!$D$5:$D$1000,MATCH($C162,Asset_Register!$A$5:$A$1000,0)),"Not in register")) -> Power plant | F162: =IF($C162="","",IFERROR(INDEX(Asset_Register!$R$5:$R$1000,MATCH($C162,Asset_Register!$A$5:$A$1000,0)),"Not in register")) -> A | G162: =IF($C162="","",IFERROR(INDEX(Asset_Register!$Q$5:$Q$1000,MATCH($C162,Asset_Register!$A$5:$A$1000,0)),"Not in register")) -> 92 | H162: DG checklist | I162: DG checks | J162: Lube oil pressure at rated load | K162: 4 | L162: bar | M162: 3.5 | N162: 2.5 | O162: Lower is worse | Q162: =IF($C162="","",IF($P162<>"",$P162,IF(AND(ISNUMBER($K162),ISNUMBER($M162),ISNUMBER($N162)),IF($O162="Lower is worse",IF($K162<=$N162,"Danger",IF($K162<=$M162,"Alert","OK")),IF($K162>=$N162,"Danger",IF($K162>=$M162,"Alert","OK"))),"Not set"))) -> OK | R162: =IF(OR($Q162="",$Q162="Not set"),"",MATCH($Q162,Lists!$F$2:$F$4,0)-1) -> 0 | U162: =IF(OR($Q162="",$Q162="OK",$Q162="Not set",NOT(ISNUMBER($G162))),"",ROUND($G162*IF($Q162="Danger",Lists!$M$15,Lists!$M$16),0)) | V162: =IF($U162="","",IF(OR($Q162="Danger",$U162>=Lists!$M$10),"P1",IF($U162>=Lists!$M$11,"P2","P3"))) | W162: =IF(OR($V162="",$B162=""),"",$B162+INDEX(Lists!$N$10:$N$12,MATCH($V162,Lists!$L$10:$L$12,0))) | Y162: No action | Z162: DG operator | AC162: =IF(OR($U162="",$B162=""),"",IF($AA162<>"",$AA162-$B162,TODAY()-$B162)) | AD162: =IF($W162="","",IF($Y162="Closed",IF($AA162="","Closed",IF($AA162<=$W162,"Closed on time","Closed late")),IF(TODAY()>$W162,"Overdue","Within time")))
A163: =IF($C163="","","R"&TEXT(ROW()-4,"00000")) -> R00159 | B163: 46113 | C163: 100110 | D163: =IF($C163="","",IFERROR(INDEX(Asset_Register!$C$5:$C$1000,MATCH($C163,Asset_Register!$A$5:$A$1000,0)),"Not in register")) -> Molten sulphur pump | E163: =IF($C163="","",IFERROR(INDEX(Asset_Register!$D$5:$D$1000,MATCH($C163,Asset_Register!$A$5:$A$1000,0)),"Not in register")) -> Acid plant | F163: =IF($C163="","",IFERROR(INDEX(Asset_Register!$R$5:$R$1000,MATCH($C163,Asset_Register!$A$5:$A$1000,0)),"Not in register")) -> B | G163: =IF($C163="","",IFERROR(INDEX(Asset_Register!$Q$5:$Q$1000,MATCH($C163,Asset_Register!$A$5:$A$1000,0)),"Not in register")) -> 61 | H163: Vibration & visual route | I163: Vibration | J163: Overall velocity (max point) | K163: 2.6 | L163: mm/s | M163: 4.5 | N163: 7.1 | O163: Higher is worse | Q163: =IF($C163="","",IF($P163<>"",$P163,IF(AND(ISNUMBER($K163),ISNUMBER($M163),ISNUMBER($N163)),IF($O163="Lower is worse",IF($K163<=$N163,"Danger",IF($K163<=$M163,"Alert","OK")),IF($K163>=$N163,"Danger",IF($K163>=$M163,"Alert","OK"))),"Not set"))) -> OK | R163: =IF(OR($Q163="",$Q163="Not set"),"",MATCH($Q163,Lists!$F$2:$F$4,0)-1) -> 0 | U163: =IF(OR($Q163="",$Q163="OK",$Q163="Not set",NOT(ISNUMBER($G163))),"",ROUND($G163*IF($Q163="Danger",Lists!$M$15,Lists!$M$16),0)) | V163: =IF($U163="","",IF(OR($Q163="Danger",$U163>=Lists!$M$10),"P1",IF($U163>=Lists!$M$11,"P2","P3"))) | W163: =IF(OR($V163="",$B163=""),"",$B163+INDEX(Lists!$N$10:$N$12,MATCH($V163,Lists!$L$10:$L$12,0))) | Y163: No action | Z163: RCM Specialist | AC163: =IF(OR($U163="",$B163=""),"",IF($AA163<>"",$AA163-$B163,TODAY()-$B163)) | AD163: =IF($W163="","",IF($Y163="Closed",IF($AA163="","Closed",IF($AA163<=$W163,"Closed on time","Closed late")),IF(TODAY()>$W163,"Overdue","Within time")))
A164: =IF($C164="","","R"&TEXT(ROW()-4,"00000")) -> R00160 | B164: 46113 | C164: 100115 | D164: =IF($C164="","",IFERROR(INDEX(Asset_Register!$C$5:$C$1000,MATCH($C164,Asset_Register!$A$5:$A$1000,0)),"Not in register")) -> Instrument air receiver | E164: =IF($C164="","",IFERROR(INDEX(Asset_Register!$D$5:$D$1000,MATCH($C164,Asset_Register!$A$5:$A$1000,0)),"Not in register")) -> Acid plant | F164: =IF($C164="","",IFERROR(INDEX(Asset_Register!$R$5:$R$1000,MATCH($C164,Asset_Register!$A$5:$A$1000,0)),"Not in register")) -> B | G164: =IF($C164="","",IFERROR(INDEX(Asset_Register!$Q$5:$Q$1000,MATCH($C164,Asset_Register!$A$5:$A$1000,0)),"Not in register")) -> 53 | H164: Ultrasonic report | I164: Ultrasonics (airborne) | J164: Leak survey level | K164: 13 | L164: dBµV | M164: 30 | N164: 40 | O164: Higher is worse | Q164: =IF($C164="","",IF($P164<>"",$P164,IF(AND(ISNUMBER($K164),ISNUMBER($M164),ISNUMBER($N164)),IF($O164="Lower is worse",IF($K164<=$N164,"Danger",IF($K164<=$M164,"Alert","OK")),IF($K164>=$N164,"Danger",IF($K164>=$M164,"Alert","OK"))),"Not set"))) -> OK | R164: =IF(OR($Q164="",$Q164="Not set"),"",MATCH($Q164,Lists!$F$2:$F$4,0)-1) -> 0 | U164: =IF(OR($Q164="",$Q164="OK",$Q164="Not set",NOT(ISNUMBER($G164))),"",ROUND($G164*IF($Q164="Danger",Lists!$M$15,Lists!$M$16),0)) | V164: =IF($U164="","",IF(OR($Q164="Danger",$U164>=Lists!$M$10),"P1",IF($U164>=Lists!$M$11,"P2","P3"))) | W164: =IF(OR($V164="",$B164=""),"",$B164+INDEX(Lists!$N$10:$N$12,MATCH($V164,Lists!$L$10:$L$12,0))) | Y164: No action | Z164: RCM Specialist | AC164: =IF(OR($U164="",$B164=""),"",IF($AA164<>"",$AA164-$B164,TODAY()-$B164)) | AD164: =IF($W164="","",IF($Y164="Closed",IF($AA164="","Closed",IF($AA164<=$W164,"Closed on time","Closed late")),IF(TODAY()>$W164,"Overdue","Within time")))
A165: =IF($C165="","","R"&TEXT(ROW()-4,"00000")) -> R00161 | B165: 46114 | C165: 100108 | D165: =IF($C165="","",IFERROR(INDEX(Asset_Register!$C$5:$C$1000,MATCH($C165,Asset_Register!$A$5:$A$1000,0)),"Not in register")) -> Boiler feed water pump A | E165: =IF($C165="","",IFERROR(INDEX(Asset_Register!$D$5:$D$1000,MATCH($C165,Asset_Register!$A$5:$A$1000,0)),"Not in register")) -> Acid plant | F165: =IF($C165="","",IFERROR(INDEX(Asset_Register!$R$5:$R$1000,MATCH($C165,Asset_Register!$A$5:$A$1000,0)),"Not in register")) -> A | G165: =IF($C165="","",IFERROR(INDEX(Asset_Register!$Q$5:$Q$1000,MATCH($C165,Asset_Register!$A$5:$A$1000,0)),"Not in register")) -> 75 | H165: Vibration & visual route | I165: Vibration | J165: Overall velocity (max point) | K165: 3.4 | L165: mm/s | M165: 4.5 | N165: 7.1 | O165: Higher is worse | Q165: =IF($C165="","",IF($P165<>"",$P165,IF(AND(ISNUMBER($K165),ISNUMBER($M165),ISNUMBER($N165)),IF($O165="Lower is worse",IF($K165<=$N165,"Danger",IF($K165<=$M165,"Alert","OK")),IF($K165>=$N165,"Danger",IF($K165>=$M165,"Alert","OK"))),"Not set"))) -> OK | R165: =IF(OR($Q165="",$Q165="Not set"),"",MATCH($Q165,Lists!$F$2:$F$4,0)-1) -> 0 | U165: =IF(OR($Q165="",$Q165="OK",$Q165="Not set",NOT(ISNUMBER($G165))),"",ROUND($G165*IF($Q165="Danger",Lists!$M$15,Lists!$M$16),0)) | V165: =IF($U165="","",IF(OR($Q165="Danger",$U165>=Lists!$M$10),"P1",IF($U165>=Lists!$M$11,"P2","P3"))) | W165: =IF(OR($V165="",$B165=""),"",$B165+INDEX(Lists!$N$10:$N$12,MATCH($V165,Lists!$L$10:$L$12,0))) | Y165: No action | Z165: RCM Specialist | AC165: =IF(OR($U165="",$B165=""),"",IF($AA165<>"",$AA165-$B165,TODAY()-$B165)) | AD165: =IF($W165="","",IF($Y165="Closed",IF($AA165="","Closed",IF($AA165<=$W165,"Closed on time","Closed late")),IF(TODAY()>$W165,"Overdue","Within time")))
A166: =IF($C166="","","R"&TEXT(ROW()-4,"00000")) -> R00162 | B166: 46114 | C166: 100111 | D166: =IF($C166="","",IFERROR(INDEX(Asset_Register!$C$5:$C$1000,MATCH($C166,Asset_Register!$A$5:$A$1000,0)),"Not in register")) -> Sulphur melter agitator | E166: =IF($C166="","",IFERROR(INDEX(Asset_Register!$D$5:$D$1000,MATCH($C166,Asset_Register!$A$5:$A$1000,0)),"Not in register")) -> Acid plant | F166: =IF($C166="","",IFERROR(INDEX(Asset_Register!$R$5:$R$1000,MATCH($C166,Asset_Register!$A$5:$A$1000,0)),"Not in register")) -> C | G166: =IF($C166="","",IFERROR(INDEX(Asset_Register!$Q$5:$Q$1000,MATCH($C166,Asset_Register!$A$5:$A$1000,0)),"Not in register")) -> 43 | H166: Vibration & visual route | I166: Vibration | J166: Overall velocity (max point) | K166: 1.5 | L166: mm/s | M166: 4.5 | N166: 7.1 | O166: Higher is worse | Q166: =IF($C166="","",IF($P166<>"",$P166,IF(AND(ISNUMBER($K166),ISNUMBER($M166),ISNUMBER($N166)),IF($O166="Lower is worse",IF($K166<=$N166,"Danger",IF($K166<=$M166,"Alert","OK")),IF($K166>=$N166,"Danger",IF($K166>=$M166,"Alert","OK"))),"Not set"))) -> OK | R166: =IF(OR($Q166="",$Q166="Not set"),"",MATCH($Q166,Lists!$F$2:$F$4,0)-1) -> 0 | U166: =IF(OR($Q166="",$Q166="OK",$Q166="Not set",NOT(ISNUMBER($G166))),"",ROUND($G166*IF($Q166="Danger",Lists!$M$15,Lists!$M$16),0)) | V166: =IF($U166="","",IF(OR($Q166="Danger",$U166>=Lists!$M$10),"P1",IF($U166>=Lists!$M$11,"P2","P3"))) | W166: =IF(OR($V166="",$B166=""),"",$B166+INDEX(Lists!$N$10:$N$12,MATCH($V166,Lists!$L$10:$L$12,0))) | Y166: No action | Z166: RCM Specialist | AC166: =IF(OR($U166="",$B166=""),"",IF($AA166<>"",$AA166-$B166,TODAY()-$B166)) | AD166: =IF($W166="","",IF($Y166="Closed",IF($AA166="","Closed",IF($AA166<=$W166,"Closed on time","Closed late")),IF(TODAY()>$W166,"Overdue","Within time")))
A167: =IF($C167="","","R"&TEXT(ROW()-4,"00000")) -> R00163 | B167: 46114 | C167: 100113 | D167: =IF($C167="","",IFERROR(INDEX(Asset_Register!$C$5:$C$1000,MATCH($C167,Asset_Register!$A$5:$A$1000,0)),"Not in register")) -> Product acid storage tank | E167: =IF($C167="","",IFERROR(INDEX(Asset_Register!$D$5:$D$1000,MATCH($C167,Asset_Register!$A$5:$A$1000,0)),"Not in register")) -> Acid plant | F167: =IF($C167="","",IFERROR(INDEX(Asset_Register!$R$5:$R$1000,MATCH($C167,Asset_Register!$A$5:$A$1000,0)),"Not in register")) -> A | G167: =IF($C167="","",IFERROR(INDEX(Asset_Register!$Q$5:$Q$1000,MATCH($C167,Asset_Register!$A$5:$A$1000,0)),"Not in register")) -> 76 | H167: Ultrasonic report | I167: Ultrasonic thickness | J167: Shell course 1 thickness | K167: 7.4 | L167: mm | M167: 7.5 | N167: 6.5 | O167: Lower is worse | Q167: =IF($C167="","",IF($P167<>"",$P167,IF(AND(ISNUMBER($K167),ISNUMBER($M167),ISNUMBER($N167)),IF($O167="Lower is worse",IF($K167<=$N167,"Danger",IF($K167<=$M167,"Alert","OK")),IF($K167>=$N167,"Danger",IF($K167>=$M167,"Alert","OK"))),"Not set"))) -> Alert | R167: =IF(OR($Q167="",$Q167="Not set"),"",MATCH($Q167,Lists!$F$2:$F$4,0)-1) -> 1 | S167: Shell at 74% of nominal 10 mm | T167: Fitness-for-service assessment; UT quarterly | U167: =IF(OR($Q167="",$Q167="OK",$Q167="Not set",NOT(ISNUMBER($G167))),"",ROUND($G167*IF($Q167="Danger",Lists!$M$15,Lists!$M$16),0)) -> 46 | V167: =IF($U167="","",IF(OR($Q167="Danger",$U167>=Lists!$M$10),"P1",IF($U167>=Lists!$M$11,"P2","P3"))) -> P2 | W167: =IF(OR($V167="",$B167=""),"",$B167+INDEX(Lists!$N$10:$N$12,MATCH($V167,Lists!$L$10:$L$12,0))) -> 46144 | Y167: Raised | Z167: UT contractor | AC167: =IF(OR($U167="",$B167=""),"",IF($AA167<>"",$AA167-$B167,TODAY()-$B167)) -> 186 | AD167: =IF($W167="","",IF($Y167="Closed",IF($AA167="","Closed",IF($AA167<=$W167,"Closed on time","Closed late")),IF(TODAY()>$W167,"Overdue","Within time"))) -> Overdue
A168: =IF($C168="","","R"&TEXT(ROW()-4,"00000")) -> R00164 | B168: 46117 | C168: 100109 | D168: =IF($C168="","",IFERROR(INDEX(Asset_Register!$C$5:$C$1000,MATCH($C168,Asset_Register!$A$5:$A$1000,0)),"Not in register")) -> Boiler feed water pump B | E168: =IF($C168="","",IFERROR(INDEX(Asset_Register!$D$5:$D$1000,MATCH($C168,Asset_Register!$A$5:$A$1000,0)),"Not in register")) -> Acid plant | F168: =IF($C168="","",IFERROR(INDEX(Asset_Register!$R$5:$R$1000,MATCH($C168,Asset_Register!$A$5:$A$1000,0)),"Not in register")) -> A | G168: =IF($C168="","",IFERROR(INDEX(Asset_Register!$Q$5:$Q$1000,MATCH($C168,Asset_Register!$A$5:$A$1000,0)),"Not in register")) -> 71 | H168: Vibration & visual route | I168: Vibration | J168: Overall velocity (max point) | K168: 2.1 | L168: mm/s | M168: 4.5 | N168: 7.1 | O168: Higher is worse | Q168: =IF($C168="","",IF($P168<>"",$P168,IF(AND(ISNUMBER($K168),ISNUMBER($M168),ISNUMBER($N168)),IF($O168="Lower is worse",IF($K168<=$N168,"Danger",IF($K168<=$M168,"Alert","OK")),IF($K168>=$N168,"Danger",IF($K168>=$M168,"Alert","OK"))),"Not set"))) -> OK | R168: =IF(OR($Q168="",$Q168="Not set"),"",MATCH($Q168,Lists!$F$2:$F$4,0)-1) -> 0 | U168: =IF(OR($Q168="",$Q168="OK",$Q168="Not set",NOT(ISNUMBER($G168))),"",ROUND($G168*IF($Q168="Danger",Lists!$M$15,Lists!$M$16),0)) | V168: =IF($U168="","",IF(OR($Q168="Danger",$U168>=Lists!$M$10),"P1",IF($U168>=Lists!$M$11,"P2","P3"))) | W168: =IF(OR($V168="",$B168=""),"",$B168+INDEX(Lists!$N$10:$N$12,MATCH($V168,Lists!$L$10:$L$12,0))) | Y168: No action | Z168: RCM Specialist | AC168: =IF(OR($U168="",$B168=""),"",IF($AA168<>"",$AA168-$B168,TODAY()-$B168)) | AD168: =IF($W168="","",IF($Y168="Closed",IF($AA168="","Closed",IF($AA168<=$W168,"Closed on time","Closed late")),IF(TODAY()>$W168,"Overdue","Within time")))
A169: =IF($C169="","","R"&TEXT(ROW()-4,"00000")) -> R00165 | B169: 46117 | C169: 100108 | D169: =IF($C169="","",IFERROR(INDEX(Asset_Register!$C$5:$C$1000,MATCH($C169,Asset_Register!$A$5:$A$1000,0)),"Not in register")) -> Boiler feed water pump A | E169: =IF($C169="","",IFERROR(INDEX(Asset_Register!$D$5:$D$1000,MATCH($C169,Asset_Register!$A$5:$A$1000,0)),"Not in register")) -> Acid plant | F169: =IF($C169="","",IFERROR(INDEX(Asset_Register!$R$5:$R$1000,MATCH($C169,Asset_Register!$A$5:$A$1000,0)),"Not in register")) -> A | G169: =IF($C169="","",IFERROR(INDEX(Asset_Register!$Q$5:$Q$1000,MATCH($C169,Asset_Register!$A$5:$A$1000,0)),"Not in register")) -> 75 | H169: Oil analysis | I169: Lubrication / oil | J169: Water in bearing oil | K169: 420 | L169: ppm | M169: 1000 | N169: 2000 | O169: Higher is worse | Q169: =IF($C169="","",IF($P169<>"",$P169,IF(AND(ISNUMBER($K169),ISNUMBER($M169),ISNUMBER($N169)),IF($O169="Lower is worse",IF($K169<=$N169,"Danger",IF($K169<=$M169,"Alert","OK")),IF($K169>=$N169,"Danger",IF($K169>=$M169,"Alert","OK"))),"Not set"))) -> OK | R169: =IF(OR($Q169="",$Q169="Not set"),"",MATCH($Q169,Lists!$F$2:$F$4,0)-1) -> 0 | U169: =IF(OR($Q169="",$Q169="OK",$Q169="Not set",NOT(ISNUMBER($G169))),"",ROUND($G169*IF($Q169="Danger",Lists!$M$15,Lists!$M$16),0)) | V169: =IF($U169="","",IF(OR($Q169="Danger",$U169>=Lists!$M$10),"P1",IF($U169>=Lists!$M$11,"P2","P3"))) | W169: =IF(OR($V169="",$B169=""),"",$B169+INDEX(Lists!$N$10:$N$12,MATCH($V169,Lists!$L$10:$L$12,0))) | Y169: No action | Z169: RCM Specialist | AC169: =IF(OR($U169="",$B169=""),"",IF($AA169<>"",$AA169-$B169,TODAY()-$B169)) | AD169: =IF($W169="","",IF($Y169="Closed",IF($AA169="","Closed",IF($AA169<=$W169,"Closed on time","Closed late")),IF(TODAY()>$W169,"Overdue","Within time")))
A170: =IF($C170="","","R"&TEXT(ROW()-4,"00000")) -> R00166 | B170: 46117 | C170: 100201 | D170: =IF($C170="","",IFERROR(INDEX(Asset_Register!$C$5:$C$1000,MATCH($C170,Asset_Register!$A$5:$A$1000,0)),"Not in register")) -> Calciner kiln 1080 | E170: =IF($C170="","",IFERROR(INDEX(Asset_Register!$D$5:$D$1000,MATCH($C170,Asset_Register!$A$5:$A$1000,0)),"Not in register")) -> Calciner | F170: =IF($C170="","",IFERROR(INDEX(Asset_Register!$R$5:$R$1000,MATCH($C170,Asset_Register!$A$5:$A$1000,0)),"Not in register")) -> A | G170: =IF($C170="","",IFERROR(INDEX(Asset_Register!$Q$5:$Q$1000,MATCH($C170,Asset_Register!$A$5:$A$1000,0)),"Not in register")) -> 90 | H170: Oil analysis | I170: Lubrication / oil | J170: Girth gear lubricant | P170: Alert | Q170: =IF($C170="","",IF($P170<>"",$P170,IF(AND(ISNUMBER($K170),ISNUMBER($M170),ISNUMBER($N170)),IF($O170="Lower is worse",IF($K170<=$N170,"Danger",IF($K170<=$M170,"Alert","OK")),IF($K170>=$N170,"Danger",IF($K170>=$M170,"Alert","OK"))),"Not set"))) -> Alert | R170: =IF(OR($Q170="",$Q170="Not set"),"",MATCH($Q170,Lists!$F$2:$F$4,0)-1) -> 1 | S170: Girth gear lubricant degraded, high iron | T170: Clean gear and reapply lubricant | U170: =IF(OR($Q170="",$Q170="OK",$Q170="Not set",NOT(ISNUMBER($G170))),"",ROUND($G170*IF($Q170="Danger",Lists!$M$15,Lists!$M$16),0)) -> 54 | V170: =IF($U170="","",IF(OR($Q170="Danger",$U170>=Lists!$M$10),"P1",IF($U170>=Lists!$M$11,"P2","P3"))) -> P2 | W170: =IF(OR($V170="",$B170=""),"",$B170+INDEX(Lists!$N$10:$N$12,MATCH($V170,Lists!$L$10:$L$12,0))) -> 46147 | X170: 243305 | Y170: Closed | Z170: RCM Specialist | AA170: 46162 | AB170: Mechanical Supervisor | AC170: =IF(OR($U170="",$B170=""),"",IF($AA170<>"",$AA170-$B170,TODAY()-$B170)) -> 45 | AD170: =IF($W170="","",IF($Y170="Closed",IF($AA170="","Closed",IF($AA170<=$W170,"Closed on time","Closed late")),IF(TODAY()>$W170,"Overdue","Within time"))) -> Closed late
A171: =IF($C171="","","R"&TEXT(ROW()-4,"00000")) -> R00167 | B171: 46120 | C171: 100101 | D171: =IF($C171="","",IFERROR(INDEX(Asset_Register!$C$5:$C$1000,MATCH($C171,Asset_Register!$A$5:$A$1000,0)),"Not in register")) -> Sulphur furnace | E171: =IF($C171="","",IFERROR(INDEX(Asset_Register!$D$5:$D$1000,MATCH($C171,Asset_Register!$A$5:$A$1000,0)),"Not in register")) -> Acid plant | F171: =IF($C171="","",IFERROR(INDEX(Asset_Register!$R$5:$R$1000,MATCH($C171,Asset_Register!$A$5:$A$1000,0)),"Not in register")) -> A | G171: =IF($C171="","",IFERROR(INDEX(Asset_Register!$Q$5:$Q$1000,MATCH($C171,Asset_Register!$A$5:$A$1000,0)),"Not in register")) -> 94 | H171: IR survey | I171: Infrared | J171: Burner-end shell temperature | K171: 245 | L171: °C | M171: 280 | N171: 320 | O171: Higher is worse | Q171: =IF($C171="","",IF($P171<>"",$P171,IF(AND(ISNUMBER($K171),ISNUMBER($M171),ISNUMBER($N171)),IF($O171="Lower is worse",IF($K171<=$N171,"Danger",IF($K171<=$M171,"Alert","OK")),IF($K171>=$N171,"Danger",IF($K171>=$M171,"Alert","OK"))),"Not set"))) -> OK | R171: =IF(OR($Q171="",$Q171="Not set"),"",MATCH($Q171,Lists!$F$2:$F$4,0)-1) -> 0 | U171: =IF(OR($Q171="",$Q171="OK",$Q171="Not set",NOT(ISNUMBER($G171))),"",ROUND($G171*IF($Q171="Danger",Lists!$M$15,Lists!$M$16),0)) | V171: =IF($U171="","",IF(OR($Q171="Danger",$U171>=Lists!$M$10),"P1",IF($U171>=Lists!$M$11,"P2","P3"))) | W171: =IF(OR($V171="",$B171=""),"",$B171+INDEX(Lists!$N$10:$N$12,MATCH($V171,Lists!$L$10:$L$12,0))) | Y171: No action | Z171: RCM Specialist | AC171: =IF(OR($U171="",$B171=""),"",IF($AA171<>"",$AA171-$B171,TODAY()-$B171)) | AD171: =IF($W171="","",IF($Y171="Closed",IF($AA171="","Closed",IF($AA171<=$W171,"Closed on time","Closed late")),IF(TODAY()>$W171,"Overdue","Within time")))
A172: =IF($C172="","","R"&TEXT(ROW()-4,"00000")) -> R00168 | B172: 46122 | C172: 100112 | D172: =IF($C172="","",IFERROR(INDEX(Asset_Register!$C$5:$C$1000,MATCH($C172,Asset_Register!$A$5:$A$1000,0)),"Not in register")) -> Cooling tower fan 1 | E172: =IF($C172="","",IFERROR(INDEX(Asset_Register!$D$5:$D$1000,MATCH($C172,Asset_Register!$A$5:$A$1000,0)),"Not in register")) -> Acid plant | F172: =IF($C172="","",IFERROR(INDEX(Asset_Register!$R$5:$R$1000,MATCH($C172,Asset_Register!$A$5:$A$1000,0)),"Not in register")) -> B | G172: =IF($C172="","",IFERROR(INDEX(Asset_Register!$Q$5:$Q$1000,MATCH($C172,Asset_Register!$A$5:$A$1000,0)),"Not in register")) -> 50 | H172: Vibration & visual route | I172: Vibration | J172: Gearbox overall velocity | K172: 4.4 | L172: mm/s | M172: 4.5 | N172: 7.1 | O172: Higher is worse | Q172: =IF($C172="","",IF($P172<>"",$P172,IF(AND(ISNUMBER($K172),ISNUMBER($M172),ISNUMBER($N172)),IF($O172="Lower is worse",IF($K172<=$N172,"Danger",IF($K172<=$M172,"Alert","OK")),IF($K172>=$N172,"Danger",IF($K172>=$M172,"Alert","OK"))),"Not set"))) -> OK | R172: =IF(OR($Q172="",$Q172="Not set"),"",MATCH($Q172,Lists!$F$2:$F$4,0)-1) -> 0 | U172: =IF(OR($Q172="",$Q172="OK",$Q172="Not set",NOT(ISNUMBER($G172))),"",ROUND($G172*IF($Q172="Danger",Lists!$M$15,Lists!$M$16),0)) | V172: =IF($U172="","",IF(OR($Q172="Danger",$U172>=Lists!$M$10),"P1",IF($U172>=Lists!$M$11,"P2","P3"))) | W172: =IF(OR($V172="",$B172=""),"",$B172+INDEX(Lists!$N$10:$N$12,MATCH($V172,Lists!$L$10:$L$12,0))) | Y172: No action | Z172: RCM Specialist | AC172: =IF(OR($U172="",$B172=""),"",IF($AA172<>"",$AA172-$B172,TODAY()-$B172)) | AD172: =IF($W172="","",IF($Y172="Closed",IF($AA172="","Closed",IF($AA172<=$W172,"Closed on time","Closed late")),IF(TODAY()>$W172,"Overdue","Within time")))
A173: =IF($C173="","","R"&TEXT(ROW()-4,"00000")) -> R00169 | B173: 46122 | C173: 100201 | D173: =IF($C173="","",IFERROR(INDEX(Asset_Register!$C$5:$C$1000,MATCH($C173,Asset_Register!$A$5:$A$1000,0)),"Not in register")) -> Calciner kiln 1080 | E173: =IF($C173="","",IFERROR(INDEX(Asset_Register!$D$5:$D$1000,MATCH($C173,Asset_Register!$A$5:$A$1000,0)),"Not in register")) -> Calciner | F173: =IF($C173="","",IFERROR(INDEX(Asset_Register!$R$5:$R$1000,MATCH($C173,Asset_Register!$A$5:$A$1000,0)),"Not in register")) -> A | G173: =IF($C173="","",IFERROR(INDEX(Asset_Register!$Q$5:$Q$1000,MATCH($C173,Asset_Register!$A$5:$A$1000,0)),"Not in register")) -> 90 | H173: IR survey | I173: Infrared | J173: Zone 4 shell temperature | K173: 268 | L173: °C | M173: 280 | N173: 350 | O173: Higher is worse | Q173: =IF($C173="","",IF($P173<>"",$P173,IF(AND(ISNUMBER($K173),ISNUMBER($M173),ISNUMBER($N173)),IF($O173="Lower is worse",IF($K173<=$N173,"Danger",IF($K173<=$M173,"Alert","OK")),IF($K173>=$N173,"Danger",IF($K173>=$M173,"Alert","OK"))),"Not set"))) -> OK | R173: =IF(OR($Q173="",$Q173="Not set"),"",MATCH($Q173,Lists!$F$2:$F$4,0)-1) -> 0 | U173: =IF(OR($Q173="",$Q173="OK",$Q173="Not set",NOT(ISNUMBER($G173))),"",ROUND($G173*IF($Q173="Danger",Lists!$M$15,Lists!$M$16),0)) | V173: =IF($U173="","",IF(OR($Q173="Danger",$U173>=Lists!$M$10),"P1",IF($U173>=Lists!$M$11,"P2","P3"))) | W173: =IF(OR($V173="",$B173=""),"",$B173+INDEX(Lists!$N$10:$N$12,MATCH($V173,Lists!$L$10:$L$12,0))) | Y173: No action | Z173: RCM Specialist | AC173: =IF(OR($U173="",$B173=""),"",IF($AA173<>"",$AA173-$B173,TODAY()-$B173)) | AD173: =IF($W173="","",IF($Y173="Closed",IF($AA173="","Closed",IF($AA173<=$W173,"Closed on time","Closed late")),IF(TODAY()>$W173,"Overdue","Within time")))
A174: =IF($C174="","","R"&TEXT(ROW()-4,"00000")) -> R00170 | B174: 46122 | C174: 100112 | D174: =IF($C174="","",IFERROR(INDEX(Asset_Register!$C$5:$C$1000,MATCH($C174,Asset_Register!$A$5:$A$1000,0)),"Not in register")) -> Cooling tower fan 1 | E174: =IF($C174="","",IFERROR(INDEX(Asset_Register!$D$5:$D$1000,MATCH($C174,Asset_Register!$A$5:$A$1000,0)),"Not in register")) -> Acid plant | F174: =IF($C174="","",IFERROR(INDEX(Asset_Register!$R$5:$R$1000,MATCH($C174,Asset_Register!$A$5:$A$1000,0)),"Not in register")) -> B | G174: =IF($C174="","",IFERROR(INDEX(Asset_Register!$Q$5:$Q$1000,MATCH($C174,Asset_Register!$A$5:$A$1000,0)),"Not in register")) -> 50 | H174: Oil analysis | I174: Lubrication / oil | J174: Copper (Cu) in gearbox oil | K174: 22 | L174: ppm | M174: 30 | N174: 60 | O174: Higher is worse | Q174: =IF($C174="","",IF($P174<>"",$P174,IF(AND(ISNUMBER($K174),ISNUMBER($M174),ISNUMBER($N174)),IF($O174="Lower is worse",IF($K174<=$N174,"Danger",IF($K174<=$M174,"Alert","OK")),IF($K174>=$N174,"Danger",IF($K174>=$M174,"Alert","OK"))),"Not set"))) -> OK | R174: =IF(OR($Q174="",$Q174="Not set"),"",MATCH($Q174,Lists!$F$2:$F$4,0)-1) -> 0 | U174: =IF(OR($Q174="",$Q174="OK",$Q174="Not set",NOT(ISNUMBER($G174))),"",ROUND($G174*IF($Q174="Danger",Lists!$M$15,Lists!$M$16),0)) | V174: =IF($U174="","",IF(OR($Q174="Danger",$U174>=Lists!$M$10),"P1",IF($U174>=Lists!$M$11,"P2","P3"))) | W174: =IF(OR($V174="",$B174=""),"",$B174+INDEX(Lists!$N$10:$N$12,MATCH($V174,Lists!$L$10:$L$12,0))) | Y174: No action | Z174: RCM Specialist | AC174: =IF(OR($U174="",$B174=""),"",IF($AA174<>"",$AA174-$B174,TODAY()-$B174)) | AD174: =IF($W174="","",IF($Y174="Closed",IF($AA174="","Closed",IF($AA174<=$W174,"Closed on time","Closed late")),IF(TODAY()>$W174,"Overdue","Within time")))
A175: =IF($C175="","","R"&TEXT(ROW()-4,"00000")) -> R00171 | B175: 46122 | C175: 100603 | D175: =IF($C175="","",IFERROR(INDEX(Asset_Register!$C$5:$C$1000,MATCH($C175,Asset_Register!$A$5:$A$1000,0)),"Not in register")) -> Front-end loader HV-03 | E175: =IF($C175="","",IFERROR(INDEX(Asset_Register!$D$5:$D$1000,MATCH($C175,Asset_Register!$A$5:$A$1000,0)),"Not in register")) -> Mobile fleet | F175: =IF($C175="","",IFERROR(INDEX(Asset_Register!$R$5:$R$1000,MATCH($C175,Asset_Register!$A$5:$A$1000,0)),"Not in register")) -> B | G175: =IF($C175="","",IFERROR(INDEX(Asset_Register!$Q$5:$Q$1000,MATCH($C175,Asset_Register!$A$5:$A$1000,0)),"Not in register")) -> 67 | H175: Oil analysis | I175: Lubrication / oil | J175: Engine oil silicon (Si) | K175: 10 | L175: ppm | M175: 20 | N175: 30 | O175: Higher is worse | Q175: =IF($C175="","",IF($P175<>"",$P175,IF(AND(ISNUMBER($K175),ISNUMBER($M175),ISNUMBER($N175)),IF($O175="Lower is worse",IF($K175<=$N175,"Danger",IF($K175<=$M175,"Alert","OK")),IF($K175>=$N175,"Danger",IF($K175>=$M175,"Alert","OK"))),"Not set"))) -> OK | R175: =IF(OR($Q175="",$Q175="Not set"),"",MATCH($Q175,Lists!$F$2:$F$4,0)-1) -> 0 | U175: =IF(OR($Q175="",$Q175="OK",$Q175="Not set",NOT(ISNUMBER($G175))),"",ROUND($G175*IF($Q175="Danger",Lists!$M$15,Lists!$M$16),0)) | V175: =IF($U175="","",IF(OR($Q175="Danger",$U175>=Lists!$M$10),"P1",IF($U175>=Lists!$M$11,"P2","P3"))) | W175: =IF(OR($V175="",$B175=""),"",$B175+INDEX(Lists!$N$10:$N$12,MATCH($V175,Lists!$L$10:$L$12,0))) | Y175: No action | Z175: RCM Specialist | AC175: =IF(OR($U175="",$B175=""),"",IF($AA175<>"",$AA175-$B175,TODAY()-$B175)) | AD175: =IF($W175="","",IF($Y175="Closed",IF($AA175="","Closed",IF($AA175<=$W175,"Closed on time","Closed late")),IF(TODAY()>$W175,"Overdue","Within time")))
A176: =IF($C176="","","R"&TEXT(ROW()-4,"00000")) -> R00172 | B176: 46122 | C176: 100601 | D176: =IF($C176="","",IFERROR(INDEX(Asset_Register!$C$5:$C$1000,MATCH($C176,Asset_Register!$A$5:$A$1000,0)),"Not in register")) -> Dozer HV-01 | E176: =IF($C176="","",IFERROR(INDEX(Asset_Register!$D$5:$D$1000,MATCH($C176,Asset_Register!$A$5:$A$1000,0)),"Not in register")) -> Mobile fleet | F176: =IF($C176="","",IFERROR(INDEX(Asset_Register!$R$5:$R$1000,MATCH($C176,Asset_Register!$A$5:$A$1000,0)),"Not in register")) -> B | G176: =IF($C176="","",IFERROR(INDEX(Asset_Register!$Q$5:$Q$1000,MATCH($C176,Asset_Register!$A$5:$A$1000,0)),"Not in register")) -> 69 | H176: Oil analysis | I176: Lubrication / oil | J176: Engine oil iron (Fe) | K176: 28 | L176: ppm | M176: 60 | N176: 100 | O176: Higher is worse | Q176: =IF($C176="","",IF($P176<>"",$P176,IF(AND(ISNUMBER($K176),ISNUMBER($M176),ISNUMBER($N176)),IF($O176="Lower is worse",IF($K176<=$N176,"Danger",IF($K176<=$M176,"Alert","OK")),IF($K176>=$N176,"Danger",IF($K176>=$M176,"Alert","OK"))),"Not set"))) -> OK | R176: =IF(OR($Q176="",$Q176="Not set"),"",MATCH($Q176,Lists!$F$2:$F$4,0)-1) -> 0 | U176: =IF(OR($Q176="",$Q176="OK",$Q176="Not set",NOT(ISNUMBER($G176))),"",ROUND($G176*IF($Q176="Danger",Lists!$M$15,Lists!$M$16),0)) | V176: =IF($U176="","",IF(OR($Q176="Danger",$U176>=Lists!$M$10),"P1",IF($U176>=Lists!$M$11,"P2","P3"))) | W176: =IF(OR($V176="",$B176=""),"",$B176+INDEX(Lists!$N$10:$N$12,MATCH($V176,Lists!$L$10:$L$12,0))) | Y176: No action | Z176: RCM Specialist | AC176: =IF(OR($U176="",$B176=""),"",IF($AA176<>"",$AA176-$B176,TODAY()-$B176)) | AD176: =IF($W176="","",IF($Y176="Closed",IF($AA176="","Closed",IF($AA176<=$W176,"Closed on time","Closed late")),IF(TODAY()>$W176,"Overdue","Within time")))
A177: =IF($C177="","","R"&TEXT(ROW()-4,"00000")) -> R00173 | B177: 46122 | C177: 100602 | D177: =IF($C177="","",IFERROR(INDEX(Asset_Register!$C$5:$C$1000,MATCH($C177,Asset_Register!$A$5:$A$1000,0)),"Not in register")) -> Compactor HV-02 | E177: =IF($C177="","",IFERROR(INDEX(Asset_Register!$D$5:$D$1000,MATCH($C177,Asset_Register!$A$5:$A$1000,0)),"Not in register")) -> Mobile fleet | F177: =IF($C177="","",IFERROR(INDEX(Asset_Register!$R$5:$R$1000,MATCH($C177,Asset_Register!$A$5:$A$1000,0)),"Not in register")) -> B | G177: =IF($C177="","",IFERROR(INDEX(Asset_Register!$Q$5:$Q$1000,MATCH($C177,Asset_Register!$A$5:$A$1000,0)),"Not in register")) -> 58 | H177: Oil analysis | I177: Lubrication / oil | J177: Engine oil iron (Fe) | K177: 23 | L177: ppm | M177: 60 | N177: 100 | O177: Higher is worse | Q177: =IF($C177="","",IF($P177<>"",$P177,IF(AND(ISNUMBER($K177),ISNUMBER($M177),ISNUMBER($N177)),IF($O177="Lower is worse",IF($K177<=$N177,"Danger",IF($K177<=$M177,"Alert","OK")),IF($K177>=$N177,"Danger",IF($K177>=$M177,"Alert","OK"))),"Not set"))) -> OK | R177: =IF(OR($Q177="",$Q177="Not set"),"",MATCH($Q177,Lists!$F$2:$F$4,0)-1) -> 0 | U177: =IF(OR($Q177="",$Q177="OK",$Q177="Not set",NOT(ISNUMBER($G177))),"",ROUND($G177*IF($Q177="Danger",Lists!$M$15,Lists!$M$16),0)) | V177: =IF($U177="","",IF(OR($Q177="Danger",$U177>=Lists!$M$10),"P1",IF($U177>=Lists!$M$11,"P2","P3"))) | W177: =IF(OR($V177="",$B177=""),"",$B177+INDEX(Lists!$N$10:$N$12,MATCH($V177,Lists!$L$10:$L$12,0))) | Y177: No action | Z177: RCM Specialist | AC177: =IF(OR($U177="",$B177=""),"",IF($AA177<>"",$AA177-$B177,TODAY()-$B177)) | AD177: =IF($W177="","",IF($Y177="Closed",IF($AA177="","Closed",IF($AA177<=$W177,"Closed on time","Closed late")),IF(TODAY()>$W177,"Overdue","Within time")))
A178: =IF($C178="","","R"&TEXT(ROW()-4,"00000")) -> R00174 | B178: 46124 | C178: 100103 | D178: =IF($C178="","",IFERROR(INDEX(Asset_Register!$C$5:$C$1000,MATCH($C178,Asset_Register!$A$5:$A$1000,0)),"Not in register")) -> Main air blower | E178: =IF($C178="","",IFERROR(INDEX(Asset_Register!$D$5:$D$1000,MATCH($C178,Asset_Register!$A$5:$A$1000,0)),"Not in register")) -> Acid plant | F178: =IF($C178="","",IFERROR(INDEX(Asset_Register!$R$5:$R$1000,MATCH($C178,Asset_Register!$A$5:$A$1000,0)),"Not in register")) -> A | G178: =IF($C178="","",IFERROR(INDEX(Asset_Register!$Q$5:$Q$1000,MATCH($C178,Asset_Register!$A$5:$A$1000,0)),"Not in register")) -> 87 | H178: Vibration & visual route | I178: Vibration | J178: Overall velocity (max point) | K178: 2.9 | L178: mm/s | M178: 4.5 | N178: 7.1 | O178: Higher is worse | Q178: =IF($C178="","",IF($P178<>"",$P178,IF(AND(ISNUMBER($K178),ISNUMBER($M178),ISNUMBER($N178)),IF($O178="Lower is worse",IF($K178<=$N178,"Danger",IF($K178<=$M178,"Alert","OK")),IF($K178>=$N178,"Danger",IF($K178>=$M178,"Alert","OK"))),"Not set"))) -> OK | R178: =IF(OR($Q178="",$Q178="Not set"),"",MATCH($Q178,Lists!$F$2:$F$4,0)-1) -> 0 | U178: =IF(OR($Q178="",$Q178="OK",$Q178="Not set",NOT(ISNUMBER($G178))),"",ROUND($G178*IF($Q178="Danger",Lists!$M$15,Lists!$M$16),0)) | V178: =IF($U178="","",IF(OR($Q178="Danger",$U178>=Lists!$M$10),"P1",IF($U178>=Lists!$M$11,"P2","P3"))) | W178: =IF(OR($V178="",$B178=""),"",$B178+INDEX(Lists!$N$10:$N$12,MATCH($V178,Lists!$L$10:$L$12,0))) | Y178: No action | Z178: RCM Specialist | AC178: =IF(OR($U178="",$B178=""),"",IF($AA178<>"",$AA178-$B178,TODAY()-$B178)) | AD178: =IF($W178="","",IF($Y178="Closed",IF($AA178="","Closed",IF($AA178<=$W178,"Closed on time","Closed late")),IF(TODAY()>$W178,"Overdue","Within time")))
A179: =IF($C179="","","R"&TEXT(ROW()-4,"00000")) -> R00175 | B179: 46127 | C179: 100107 | D179: =IF($C179="","",IFERROR(INDEX(Asset_Register!$C$5:$C$1000,MATCH($C179,Asset_Register!$A$5:$A$1000,0)),"Not in register")) -> Final tower acid pump | E179: =IF($C179="","",IFERROR(INDEX(Asset_Register!$D$5:$D$1000,MATCH($C179,Asset_Register!$A$5:$A$1000,0)),"Not in register")) -> Acid plant | F179: =IF($C179="","",IFERROR(INDEX(Asset_Register!$R$5:$R$1000,MATCH($C179,Asset_Register!$A$5:$A$1000,0)),"Not in register")) -> B | G179: =IF($C179="","",IFERROR(INDEX(Asset_Register!$Q$5:$Q$1000,MATCH($C179,Asset_Register!$A$5:$A$1000,0)),"Not in register")) -> 66 | H179: Vibration & visual route | I179: Vibration | J179: Overall velocity (max point) | K179: 3.9 | L179: mm/s | M179: 4.5 | N179: 7.1 | O179: Higher is worse | Q179: =IF($C179="","",IF($P179<>"",$P179,IF(AND(ISNUMBER($K179),ISNUMBER($M179),ISNUMBER($N179)),IF($O179="Lower is worse",IF($K179<=$N179,"Danger",IF($K179<=$M179,"Alert","OK")),IF($K179>=$N179,"Danger",IF($K179>=$M179,"Alert","OK"))),"Not set"))) -> OK | R179: =IF(OR($Q179="",$Q179="Not set"),"",MATCH($Q179,Lists!$F$2:$F$4,0)-1) -> 0 | U179: =IF(OR($Q179="",$Q179="OK",$Q179="Not set",NOT(ISNUMBER($G179))),"",ROUND($G179*IF($Q179="Danger",Lists!$M$15,Lists!$M$16),0)) | V179: =IF($U179="","",IF(OR($Q179="Danger",$U179>=Lists!$M$10),"P1",IF($U179>=Lists!$M$11,"P2","P3"))) | W179: =IF(OR($V179="",$B179=""),"",$B179+INDEX(Lists!$N$10:$N$12,MATCH($V179,Lists!$L$10:$L$12,0))) | Y179: No action | Z179: RCM Specialist | AC179: =IF(OR($U179="",$B179=""),"",IF($AA179<>"",$AA179-$B179,TODAY()-$B179)) | AD179: =IF($W179="","",IF($Y179="Closed",IF($AA179="","Closed",IF($AA179<=$W179,"Closed on time","Closed late")),IF(TODAY()>$W179,"Overdue","Within time")))
A180: =IF($C180="","","R"&TEXT(ROW()-4,"00000")) -> R00176 | B180: 46130 | C180: 100114 | D180: =IF($C180="","",IFERROR(INDEX(Asset_Register!$C$5:$C$1000,MATCH($C180,Asset_Register!$A$5:$A$1000,0)),"Not in register")) -> Acid transfer line | E180: =IF($C180="","",IFERROR(INDEX(Asset_Register!$D$5:$D$1000,MATCH($C180,Asset_Register!$A$5:$A$1000,0)),"Not in register")) -> Acid plant | F180: =IF($C180="","",IFERROR(INDEX(Asset_Register!$R$5:$R$1000,MATCH($C180,Asset_Register!$A$5:$A$1000,0)),"Not in register")) -> A | G180: =IF($C180="","",IFERROR(INDEX(Asset_Register!$Q$5:$Q$1000,MATCH($C180,Asset_Register!$A$5:$A$1000,0)),"Not in register")) -> 81 | H180: Ultrasonic report | I180: Ultrasonic thickness | J180: Elbow E-07 wall | K180: 5.1 | L180: mm | M180: 4.5 | N180: 4 | O180: Lower is worse | Q180: =IF($C180="","",IF($P180<>"",$P180,IF(AND(ISNUMBER($K180),ISNUMBER($M180),ISNUMBER($N180)),IF($O180="Lower is worse",IF($K180<=$N180,"Danger",IF($K180<=$M180,"Alert","OK")),IF($K180>=$N180,"Danger",IF($K180>=$M180,"Alert","OK"))),"Not set"))) -> OK | R180: =IF(OR($Q180="",$Q180="Not set"),"",MATCH($Q180,Lists!$F$2:$F$4,0)-1) -> 0 | U180: =IF(OR($Q180="",$Q180="OK",$Q180="Not set",NOT(ISNUMBER($G180))),"",ROUND($G180*IF($Q180="Danger",Lists!$M$15,Lists!$M$16),0)) | V180: =IF($U180="","",IF(OR($Q180="Danger",$U180>=Lists!$M$10),"P1",IF($U180>=Lists!$M$11,"P2","P3"))) | W180: =IF(OR($V180="",$B180=""),"",$B180+INDEX(Lists!$N$10:$N$12,MATCH($V180,Lists!$L$10:$L$12,0))) | Y180: No action | Z180: UT contractor | AC180: =IF(OR($U180="",$B180=""),"",IF($AA180<>"",$AA180-$B180,TODAY()-$B180)) | AD180: =IF($W180="","",IF($Y180="Closed",IF($AA180="","Closed",IF($AA180<=$W180,"Closed on time","Closed late")),IF(TODAY()>$W180,"Overdue","Within time")))
A181: =IF($C181="","","R"&TEXT(ROW()-4,"00000")) -> R00177 | B181: 46132 | C181: 100104 | D181: =IF($C181="","",IFERROR(INDEX(Asset_Register!$C$5:$C$1000,MATCH($C181,Asset_Register!$A$5:$A$1000,0)),"Not in register")) -> SO2 converter | E181: =IF($C181="","",IFERROR(INDEX(Asset_Register!$D$5:$D$1000,MATCH($C181,Asset_Register!$A$5:$A$1000,0)),"Not in register")) -> Acid plant | F181: =IF($C181="","",IFERROR(INDEX(Asset_Register!$R$5:$R$1000,MATCH($C181,Asset_Register!$A$5:$A$1000,0)),"Not in register")) -> A | G181: =IF($C181="","",IFERROR(INDEX(Asset_Register!$Q$5:$Q$1000,MATCH($C181,Asset_Register!$A$5:$A$1000,0)),"Not in register")) -> 86 | H181: IR survey | I181: Infrared | J181: Bed 3 outlet flange dT above baseline | K181: 10 | L181: °C | M181: 30 | N181: 60 | O181: Higher is worse | Q181: =IF($C181="","",IF($P181<>"",$P181,IF(AND(ISNUMBER($K181),ISNUMBER($M181),ISNUMBER($N181)),IF($O181="Lower is worse",IF($K181<=$N181,"Danger",IF($K181<=$M181,"Alert","OK")),IF($K181>=$N181,"Danger",IF($K181>=$M181,"Alert","OK"))),"Not set"))) -> OK | R181: =IF(OR($Q181="",$Q181="Not set"),"",MATCH($Q181,Lists!$F$2:$F$4,0)-1) -> 0 | U181: =IF(OR($Q181="",$Q181="OK",$Q181="Not set",NOT(ISNUMBER($G181))),"",ROUND($G181*IF($Q181="Danger",Lists!$M$15,Lists!$M$16),0)) | V181: =IF($U181="","",IF(OR($Q181="Danger",$U181>=Lists!$M$10),"P1",IF($U181>=Lists!$M$11,"P2","P3"))) | W181: =IF(OR($V181="",$B181=""),"",$B181+INDEX(Lists!$N$10:$N$12,MATCH($V181,Lists!$L$10:$L$12,0))) | Y181: No action | Z181: RCM Specialist | AC181: =IF(OR($U181="",$B181=""),"",IF($AA181<>"",$AA181-$B181,TODAY()-$B181)) | AD181: =IF($W181="","",IF($Y181="Closed",IF($AA181="","Closed",IF($AA181<=$W181,"Closed on time","Closed late")),IF(TODAY()>$W181,"Overdue","Within time")))
A182: =IF($C182="","","R"&TEXT(ROW()-4,"00000")) -> R00178 | B182: 46134 | C182: 100105 | D182: =IF($C182="","",IFERROR(INDEX(Asset_Register!$C$5:$C$1000,MATCH($C182,Asset_Register!$A$5:$A$1000,0)),"Not in register")) -> Drying tower acid pump | E182: =IF($C182="","",IFERROR(INDEX(Asset_Register!$D$5:$D$1000,MATCH($C182,Asset_Register!$A$5:$A$1000,0)),"Not in register")) -> Acid plant | F182: =IF($C182="","",IFERROR(INDEX(Asset_Register!$R$5:$R$1000,MATCH($C182,Asset_Register!$A$5:$A$1000,0)),"Not in register")) -> A | G182: =IF($C182="","",IFERROR(INDEX(Asset_Register!$Q$5:$Q$1000,MATCH($C182,Asset_Register!$A$5:$A$1000,0)),"Not in register")) -> 74 | H182: Vibration & visual route | I182: Vibration | J182: Overall velocity (max point) | K182: 2.4 | L182: mm/s | M182: 4.5 | N182: 7.1 | O182: Higher is worse | Q182: =IF($C182="","",IF($P182<>"",$P182,IF(AND(ISNUMBER($K182),ISNUMBER($M182),ISNUMBER($N182)),IF($O182="Lower is worse",IF($K182<=$N182,"Danger",IF($K182<=$M182,"Alert","OK")),IF($K182>=$N182,"Danger",IF($K182>=$M182,"Alert","OK"))),"Not set"))) -> OK | R182: =IF(OR($Q182="",$Q182="Not set"),"",MATCH($Q182,Lists!$F$2:$F$4,0)-1) -> 0 | U182: =IF(OR($Q182="",$Q182="OK",$Q182="Not set",NOT(ISNUMBER($G182))),"",ROUND($G182*IF($Q182="Danger",Lists!$M$15,Lists!$M$16),0)) | V182: =IF($U182="","",IF(OR($Q182="Danger",$U182>=Lists!$M$10),"P1",IF($U182>=Lists!$M$11,"P2","P3"))) | W182: =IF(OR($V182="",$B182=""),"",$B182+INDEX(Lists!$N$10:$N$12,MATCH($V182,Lists!$L$10:$L$12,0))) | Y182: No action | Z182: RCM Specialist | AC182: =IF(OR($U182="",$B182=""),"",IF($AA182<>"",$AA182-$B182,TODAY()-$B182)) | AD182: =IF($W182="","",IF($Y182="Closed",IF($AA182="","Closed",IF($AA182<=$W182,"Closed on time","Closed late")),IF(TODAY()>$W182,"Overdue","Within time")))
... A198: =IF($C198="","","R"&TEXT(ROW()-4,"00000")) -> R00194 | B198: 46150 | C198: 100101 | D198: =IF($C198="","",IFERROR(INDEX(Asset_Register!$C$5:$C$1000,MATCH($C198,Asset_Register!$A$5:$A$1000,0)),"Not in register")) -> Sulphur furnace | E198: =IF($C198="","",IFERROR(INDEX(Asset_Register!$D$5:$D$1000,MATCH($C198,Asset_Register!$A$5:$A$1000,0)),"Not in register")) -> Acid plant | F198: =IF($C198="","",IFERROR(INDEX(Asset_Register!$R$5:$R$1000,MATCH($C198,Asset_Register!$A$5:$A$1000,0)),"Not in register")) -> A | G198: =IF($C198="","",IFERROR(INDEX(Asset_Register!$Q$5:$Q$1000,MATCH($C198,Asset_Register!$A$5:$A$1000,0)),"Not in register")) -> 94 | H198: IR survey | I198: Infrared | J198: Burner-end shell temperature | K198: 248 | L198: °C | M198: 280 | N198: 320 | O198: Higher is worse | Q198: =IF($C198="","",IF($P198<>"",$P198,IF(AND(ISNUMBER($K198),ISNUMBER($M198),ISNUMBER($N198)),IF($O198="Lower is worse",IF($K198<=$N198,"Danger",IF($K198<=$M198,"Alert","OK")),IF($K198>=$N198,"Danger",IF($K198>=$M198,"Alert","OK"))),"Not set"))) -> OK | R198: =IF(OR($Q198="",$Q198="Not set"),"",MATCH($Q198,Lists!$F$2:$F$4,0)-1) -> 0 | U198: =IF(OR($Q198="",$Q198="OK",$Q198="Not set",NOT(ISNUMBER($G198))),"",ROUND($G198*IF($Q198="Danger",Lists!$M$15,Lists!$M$16),0)) | V198: =IF($U198="","",IF(OR($Q198="Danger",$U198>=Lists!$M$10),"P1",IF($U198>=Lists!$M$11,"P2","P3"))) | W198: =IF(OR($V198="",$B198=""),"",$B198+INDEX(Lists!$N$10:$N$12,MATCH($V198,Lists!$L$10:$L$12,0))) | Y198: No action | Z198: RCM Specialist | AC198: =IF(OR($U198="",$B198=""),"",IF($AA198<>"",$AA198-$B198,TODAY()-$B198)) | AD198: =IF($W198="","",IF($Y198="Closed",IF($AA198="","Closed",IF($AA198<=$W198,"Closed on time","Closed late")),IF(TODAY()>$W198,"Overdue","Within time")))
A199: =IF($C199="","","R"&TEXT(ROW()-4,"00000")) -> R00195 | B199: 46152 | C199: 100112 | D199: =IF($C199="","",IFERROR(INDEX(Asset_Register!$C$5:$C$1000,MATCH($C199,Asset_Register!$A$5:$A$1000,0)),"Not in register")) -> Cooling tower fan 1 | E199: =IF($C199="","",IFERROR(INDEX(Asset_Register!$D$5:$D$1000,MATCH($C199,Asset_Register!$A$5:$A$1000,0)),"Not in register")) -> Acid plant | F199: =IF($C199="","",IFERROR(INDEX(Asset_Register!$R$5:$R$1000,MATCH($C199,Asset_Register!$A$5:$A$1000,0)),"Not in register")) -> B | G199: =IF($C199="","",IFERROR(INDEX(Asset_Register!$Q$5:$Q$1000,MATCH($C199,Asset_Register!$A$5:$A$1000,0)),"Not in register")) -> 50 | H199: Vibration & visual route | I199: Vibration | J199: Gearbox overall velocity | K199: 4.8 | L199: mm/s | M199: 4.5 | N199: 7.1 | O199: Higher is worse | Q199: =IF($C199="","",IF($P199<>"",$P199,IF(AND(ISNUMBER($K199),ISNUMBER($M199),ISNUMBER($N199)),IF($O199="Lower is worse",IF($K199<=$N199,"Danger",IF($K199<=$M199,"Alert","OK")),IF($K199>=$N199,"Danger",IF($K199>=$M199,"Alert","OK"))),"Not set"))) -> Alert | R199: =IF(OR($Q199="",$Q199="Not set"),"",MATCH($Q199,Lists!$F$2:$F$4,0)-1) -> 1 | S199: Gear-mesh sidebands rising | T199: Borescope gearbox; plan overhaul and order spare | U199: =IF(OR($Q199="",$Q199="OK",$Q199="Not set",NOT(ISNUMBER($G199))),"",ROUND($G199*IF($Q199="Danger",Lists!$M$15,Lists!$M$16),0)) -> 30 | V199: =IF($U199="","",IF(OR($Q199="Danger",$U199>=Lists!$M$10),"P1",IF($U199>=Lists!$M$11,"P2","P3"))) -> P3 | W199: =IF(OR($V199="",$B199=""),"",$B199+INDEX(Lists!$N$10:$N$12,MATCH($V199,Lists!$L$10:$L$12,0))) -> 46212 | X199: 243766 | Y199: Scheduled | Z199: RCM Specialist | AC199: =IF(OR($U199="",$B199=""),"",IF($AA199<>"",$AA199-$B199,TODAY()-$B199)) -> 148 | AD199: =IF($W199="","",IF($Y199="Closed",IF($AA199="","Closed",IF($AA199<=$W199,"Closed on time","Closed late")),IF(TODAY()>$W199,"Overdue","Within time"))) -> Overdue
